Workbook

Sheet Sheet
A1: ID | B1: sex | C1: age | D1: lifestyle | E1: job | F1: salary | G1: city | H1: expectations | I1: больше 1.5 кг хлебобулочных изделий и круп | J1: больше 1.2 кг картофеля | K1: больше 1.3 кг овощей | L1: больше 700 г фруктов | M1: больше 300 г сахара | N1: больше 700 г мяса | O1: больше 200 г рыбы | P1: больше 3.5 кг молочных продуктов | Q1: больше 3 яиц | R1: больше 150 г масла и жиров | S1: больше 60 г чая и специй | T1: крупа в неделю | U1: Картофель в неделю | V1: Овощи в неделю | W1: фрукты в неделю | X1: сахар в неделю | Y1: мясо в неделю | Z1: рыба в неделю | AA1: молоко в неделю | AB1: яйца в неделю | AC1: масло в неделю | AD1: чай в неделю | AE1: сумма в неделю | AF1: сумма в месяц на продукты | AG1: сумма потребительской корзины | AH1: official | AI1: official_difference | AJ1: mind_difference
A2: 1995902821 | B2: Жен | C2: 20 | D2: active | E2: Да | F2: 60000 | G2: Москва | H2: 7500 | I2: Да | J2: Нет | K2: Да | L2: Нет | M2: Да | N2: Да | O2: Нет | P2: Нет | Q2: Нет | R2: Да | S2: Нет | T2: =IF($G2="Москва",1.3*(IF(IF(I2="Да",1,0)=1,1.4*Лист2!AX$1,Лист2!AX$1)),(IF(IF(I2="Да",1,0)=1,1.4*Лист2!AX$1,Лист2!AX$1))) -> 396.9 | U2: =IF($G2="Москва",1.3*(IF(IF(J2="Да",1,0)=1,1.4*Лист2!AY$1,Лист2!AY$1)),(IF(IF(J2="Да",1,0)=1,1.4*Лист2!AY$1,Лист2!AY$1))) -> 250 | V2: =IF($G2="Москва",1.3*(IF(IF(K2="Да",1,0)=1,1.4*Лист2!AZ$1,Лист2!AZ$1)),(IF(IF(K2="Да",1,0)=1,1.4*Лист2!AZ$1,Лист2!AZ$1))) -> 1197 | W2: =IF($G2="Москва",1.3*(IF(IF(L2="Да",1,0)=1,1.4*Лист2!BA$1,Лист2!BA$1)),(IF(IF(L2="Да",1,0)=1,1.4*Лист2!BA$1,Лист2!BA$1))) -> 300 | X2: =IF($G2="Москва",1.3*(IF(IF(M2="Да",1,0)=1,1.4*Лист2!BB$1,Лист2!BB$1)),(IF(IF(M2="Да",1,0)=1,1.4*Лист2!BB$1,Лист2!BB$1))) -> 64.4 | Y2: =IF($G2="Москва",1.3*(IF(IF(N2="Да",1,0)=1,1.4*Лист2!BC$1,Лист2!BC$1)),(IF(IF(N2="Да",1,0)=1,1.4*Лист2!BC$1,Лист2!BC$1))) -> 1218 | Z2: =IF($G2="Москва",1.3*(IF(IF(O2="Да",1,0)=1,1.4*Лист2!BD$1,Лист2!BD$1)),(IF(IF(O2="Да",1,0)=1,1.4*Лист2!BD$1,Лист2!BD$1))) -> 315 | AA2: =IF($G2="Москва",1.3*(IF(IF(P2="Да",1,0)=1,1.4*Лист2!BE$1,Лист2!BE$1)),(IF(IF(P2="Да",1,0)=1,1.4*Лист2!BE$1,Лист2!BE$1))) -> 725 | ... AD2: =IF($G2="Москва",1.3*(IF(IF(S2="Да",1,0)=1,1.4*Лист2!BH$1,Лист2!BH$1)),(IF(IF(S2="Да",1,0)=1,1.4*Лист2!BH$1,Лист2!BH$1))) -> 156.25 | AE2: =SUM(T2:AD2) -> 4739.45 | AF2: =AE2*4.2 -> 19905.69 | AG2: =AF2*2 -> 39811.38 | AH2: =IF(IF(G2="Москва",1,0)=1,Лист2!$BK$6,Лист2!$BL$6) -> 13651 | AI2: =AH2-AF2 -> -6254.69 | AJ2: =(H2-AE2)*4.2 -> 11594.31
A3: 1996067555 | B3: Муж | C3: 35 | D3: medium | E3: Да | F3: 30000 | G3: Москва | H3: 8000 | I3: Да | J3: Нет | K3: Нет | L3: Нет | M3: Нет | N3: Да | O3: Нет | P3: Да | Q3: Да | R3: Нет | S3: Нет | T3: =IF($G3="Москва",1.3*(IF(IF(I3="Да",1,0)=1,1.4*Лист2!AX$1,Лист2!AX$1)),(IF(IF(I3="Да",1,0)=1,1.4*Лист2!AX$1,Лист2!AX$1))) -> 396.9 | U3: =IF($G3="Москва",1.3*(IF(IF(J3="Да",1,0)=1,1.4*Лист2!AY$1,Лист2!AY$1)),(IF(IF(J3="Да",1,0)=1,1.4*Лист2!AY$1,Лист2!AY$1))) -> 250 | V3: =IF($G3="Москва",1.3*(IF(IF(K3="Да",1,0)=1,1.4*Лист2!AZ$1,Лист2!AZ$1)),(IF(IF(K3="Да",1,0)=1,1.4*Лист2!AZ$1,Лист2!AZ$1))) -> 855 | W3: =IF($G3="Москва",1.3*(IF(IF(L3="Да",1,0)=1,1.4*Лист2!BA$1,Лист2!BA$1)),(IF(IF(L3="Да",1,0)=1,1.4*Лист2!BA$1,Лист2!BA$1))) -> 300 | X3: =IF($G3="Москва",1.3*(IF(IF(M3="Да",1,0)=1,1.4*Лист2!BB$1,Лист2!BB$1)),(IF(IF(M3="Да",1,0)=1,1.4*Лист2!BB$1,Лист2!BB$1))) -> 46 | Y3: =IF($G3="Москва",1.3*(IF(IF(N3="Да",1,0)=1,1.4*Лист2!BC$1,Лист2!BC$1)),(IF(IF(N3="Да",1,0)=1,1.4*Лист2!BC$1,Лист2!BC$1))) -> 1218 | Z3: =IF($G3="Москва",1.3*(IF(IF(O3="Да",1,0)=1,1.4*Лист2!BD$1,Лист2!BD$1)),(IF(IF(O3="Да",1,0)=1,1.4*Лист2!BD$1,Лист2!BD$1))) -> 315 | AA3: =IF($G3="Москва",1.3*(IF(IF(P3="Да",1,0)=1,1.4*Лист2!BE$1,Лист2!BE$1)),(IF(IF(P3="Да",1,0)=1,1.4*Лист2!BE$1,Лист2!BE$1))) -> 1015 | ... AD3: =IF($G3="Москва",1.3*(IF(IF(S3="Да",1,0)=1,1.4*Лист2!BH$1,Лист2!BH$1)),(IF(IF(S3="Да",1,0)=1,1.4*Лист2!BH$1,Лист2!BH$1))) -> 156.25 | AE3: =SUM(T3:AD3) -> 4678.85 | AF3: =AE3*4.2 -> 19651.17 | AG3: =AF3*2 -> 39302.34 | AH3: =IF(IF(G3="Москва",1,0)=1,Лист2!$BK$6,Лист2!$BL$6) -> 13651 | AI3: =AH3-AF3 -> -6000.17 | AJ3: =(H3-AE3)*4.2 -> 13948.83
A4: 1996071674 | B4: Муж | C4: 20 | D4: active | E4: Нет | F4: 60000 | G4: Москва | H4: 8000 | I4: Да | J4: Нет | K4: Да | L4: Нет | M4: Да | N4: Да | O4: Нет | P4: Да | Q4: Да | R4: Нет | S4: Да | T4: =IF($G4="Москва",1.3*(IF(IF(I4="Да",1,0)=1,1.4*Лист2!AX$1,Лист2!AX$1)),(IF(IF(I4="Да",1,0)=1,1.4*Лист2!AX$1,Лист2!AX$1))) -> 396.9 | U4: =IF($G4="Москва",1.3*(IF(IF(J4="Да",1,0)=1,1.4*Лист2!AY$1,Лист2!AY$1)),(IF(IF(J4="Да",1,0)=1,1.4*Лист2!AY$1,Лист2!AY$1))) -> 250 | V4: =IF($G4="Москва",1.3*(IF(IF(K4="Да",1,0)=1,1.4*Лист2!AZ$1,Лист2!AZ$1)),(IF(IF(K4="Да",1,0)=1,1.4*Лист2!AZ$1,Лист2!AZ$1))) -> 1197 | W4: =IF($G4="Москва",1.3*(IF(IF(L4="Да",1,0)=1,1.4*Лист2!BA$1,Лист2!BA$1)),(IF(IF(L4="Да",1,0)=1,1.4*Лист2!BA$1,Лист2!BA$1))) -> 300 | X4: =IF($G4="Москва",1.3*(IF(IF(M4="Да",1,0)=1,1.4*Лист2!BB$1,Лист2!BB$1)),(IF(IF(M4="Да",1,0)=1,1.4*Лист2!BB$1,Лист2!BB$1))) -> 64.4 | Y4: =IF($G4="Москва",1.3*(IF(IF(N4="Да",1,0)=1,1.4*Лист2!BC$1,Лист2!BC$1)),(IF(IF(N4="Да",1,0)=1,1.4*Лист2!BC$1,Лист2!BC$1))) -> 1218 | Z4: =IF($G4="Москва",1.3*(IF(IF(O4="Да",1,0)=1,1.4*Лист2!BD$1,Лист2!BD$1)),(IF(IF(O4="Да",1,0)=1,1.4*Лист2!BD$1,Лист2!BD$1))) -> 315 | AA4: =IF($G4="Москва",1.3*(IF(IF(P4="Да",1,0)=1,1.4*Лист2!BE$1,Лист2!BE$1)),(IF(IF(P4="Да",1,0)=1,1.4*Лист2!BE$1,Лист2!BE$1))) -> 1015 | ... AD4: =IF($G4="Москва",1.3*(IF(IF(S4="Да",1,0)=1,1.4*Лист2!BH$1,Лист2!BH$1)),(IF(IF(S4="Да",1,0)=1,1.4*Лист2!BH$1,Лист2!BH$1))) -> 218.75 | AE4: =SUM(T4:AD4) -> 5101.75 | AF4: =AE4*4.2 -> 21427.35 | AG4: =AF4*2 -> 42854.7 | AH4: =IF(IF(G4="Москва",1,0)=1,Лист2!$BK$6,Лист2!$BL$6) -> 13651 | AI4: =AH4-AF4 -> -7776.35 | AJ4: =(H4-AE4)*4.2 -> 12172.65
A5: 1996073501 | B5: Муж | C5: 20 | D5: active | E5: Да | F5: 60000 | G5: Саратов, Саратовская область | H5: 4000 | I5: Да | J5: Нет | K5: Да | L5: Да | M5: Нет | N5: Да | O5: Да | P5: Нет | Q5: Да | R5: Нет | S5: Нет | T5: =IF($G5="Москва",1.3*(IF(IF(I5="Да",1,0)=1,1.4*Лист2!AX$1,Лист2!AX$1)),(IF(IF(I5="Да",1,0)=1,1.4*Лист2!AX$1,Лист2!AX$1))) -> 305.30769 | U5: =IF($G5="Москва",1.3*(IF(IF(J5="Да",1,0)=1,1.4*Лист2!AY$1,Лист2!AY$1)),(IF(IF(J5="Да",1,0)=1,1.4*Лист2!AY$1,Лист2!AY$1))) -> 192.30769 | V5: =IF($G5="Москва",1.3*(IF(IF(K5="Да",1,0)=1,1.4*Лист2!AZ$1,Лист2!AZ$1)),(IF(IF(K5="Да",1,0)=1,1.4*Лист2!AZ$1,Лист2!AZ$1))) -> 920.76923 | W5: =IF($G5="Москва",1.3*(IF(IF(L5="Да",1,0)=1,1.4*Лист2!BA$1,Лист2!BA$1)),(IF(IF(L5="Да",1,0)=1,1.4*Лист2!BA$1,Лист2!BA$1))) -> 323.07692 | X5: =IF($G5="Москва",1.3*(IF(IF(M5="Да",1,0)=1,1.4*Лист2!BB$1,Лист2!BB$1)),(IF(IF(M5="Да",1,0)=1,1.4*Лист2!BB$1,Лист2!BB$1))) -> 35.384615 | Y5: =IF($G5="Москва",1.3*(IF(IF(N5="Да",1,0)=1,1.4*Лист2!BC$1,Лист2!BC$1)),(IF(IF(N5="Да",1,0)=1,1.4*Лист2!BC$1,Лист2!BC$1))) -> 936.92308 | Z5: =IF($G5="Москва",1.3*(IF(IF(O5="Да",1,0)=1,1.4*Лист2!BD$1,Лист2!BD$1)),(IF(IF(O5="Да",1,0)=1,1.4*Лист2!BD$1,Лист2!BD$1))) -> 339.23077 | AA5: =IF($G5="Москва",1.3*(IF(IF(P5="Да",1,0)=1,1.4*Лист2!BE$1,Лист2!BE$1)),(IF(IF(P5="Да",1,0)=1,1.4*Лист2!BE$1,Лист2!BE$1))) -> 557.69231 | ... AD5: =IF($G5="Москва",1.3*(IF(IF(S5="Да",1,0)=1,1.4*Лист2!BH$1,Лист2!BH$1)),(IF(IF(S5="Да",1,0)=1,1.4*Лист2!BH$1,Лист2!BH$1))) -> 120.19231 | AE5: =SUM(T5:AD5) -> 3828.3462 | AF5: =AE5*4.2 -> 16079.054 | AG5: =AF5*2 -> 32158.108 | AH5: =IF(IF(G5="Москва",1,0)=1,Лист2!$BK$6,Лист2!$BL$6) -> 9230 | AI5: =AH5-AF5 -> -6849.0538 | AJ5: =(H5-AE5)*4.2 -> 720.94615
A6: 1996076712 | B6: Муж | C6: 20 | D6: active | E6: Да | F6: 60000 | G6: Москва | H6: 5000 | I6: Нет | J6: Да | K6: Да | L6: Да | M6: Нет | N6: Да | O6: Да | P6: Да | Q6: Да | R6: Нет | S6: Нет | T6: =IF($G6="Москва",1.3*(IF(IF(I6="Да",1,0)=1,1.4*Лист2!AX$1,Лист2!AX$1)),(IF(IF(I6="Да",1,0)=1,1.4*Лист2!AX$1,Лист2!AX$1))) -> 283.5 | U6: =IF($G6="Москва",1.3*(IF(IF(J6="Да",1,0)=1,1.4*Лист2!AY$1,Лист2!AY$1)),(IF(IF(J6="Да",1,0)=1,1.4*Лист2!AY$1,Лист2!AY$1))) -> 350 | V6: =IF($G6="Москва",1.3*(IF(IF(K6="Да",1,0)=1,1.4*Лист2!AZ$1,Лист2!AZ$1)),(IF(IF(K6="Да",1,0)=1,1.4*Лист2!AZ$1,Лист2!AZ$1))) -> 1197 | W6: =IF($G6="Москва",1.3*(IF(IF(L6="Да",1,0)=1,1.4*Лист2!BA$1,Лист2!BA$1)),(IF(IF(L6="Да",1,0)=1,1.4*Лист2!BA$1,Лист2!BA$1))) -> 420 | X6: =IF($G6="Москва",1.3*(IF(IF(M6="Да",1,0)=1,1.4*Лист2!BB$1,Лист2!BB$1)),(IF(IF(M6="Да",1,0)=1,1.4*Лист2!BB$1,Лист2!BB$1))) -> 46 | Y6: =IF($G6="Москва",1.3*(IF(IF(N6="Да",1,0)=1,1.4*Лист2!BC$1,Лист2!BC$1)),(IF(IF(N6="Да",1,0)=1,1.4*Лист2!BC$1,Лист2!BC$1))) -> 1218 | Z6: =IF($G6="Москва",1.3*(IF(IF(O6="Да",1,0)=1,1.4*Лист2!BD$1,Лист2!BD$1)),(IF(IF(O6="Да",1,0)=1,1.4*Лист2!BD$1,Лист2!BD$1))) -> 441 | AA6: =IF($G6="Москва",1.3*(IF(IF(P6="Да",1,0)=1,1.4*Лист2!BE$1,Лист2!BE$1)),(IF(IF(P6="Да",1,0)=1,1.4*Лист2!BE$1,Лист2!BE$1))) -> 1015 | ... AD6: =IF($G6="Москва",1.3*(IF(IF(S6="Да",1,0)=1,1.4*Лист2!BH$1,Лист2!BH$1)),(IF(IF(S6="Да",1,0)=1,1.4*Лист2!BH$1,Лист2!BH$1))) -> 156.25 | AE6: =SUM(T6:AD6) -> 5253.45 | AF6: =AE6*4.2 -> 22064.49 | AG6: =AF6*2 -> 44128.98 | AH6: =IF(IF(G6="Москва",1,0)=1,Лист2!$BK$6,Лист2!$BL$6) -> 13651 | AI6: =AH6-AF6 -> -8413.49 | AJ6: =(H6-AE6)*4.2 -> -1064.49
A7: 1996077733 | B7: Муж | C7: 20 | D7: medium | E7: Да | F7: 21000 | G7: Ярославль, Ярославская область | H7: 5000 | I7: Нет | J7: Нет | K7: Да | L7: Да | M7: Да | N7: Да | O7: Да | P7: Да | Q7: Да | R7: Нет | S7: Да | T7: =IF($G7="Москва",1.3*(IF(IF(I7="Да",1,0)=1,1.4*Лист2!AX$1,Лист2!AX$1)),(IF(IF(I7="Да",1,0)=1,1.4*Лист2!AX$1,Лист2!AX$1))) -> 218.07692 | U7: =IF($G7="Москва",1.3*(IF(IF(J7="Да",1,0)=1,1.4*Лист2!AY$1,Лист2!AY$1)),(IF(IF(J7="Да",1,0)=1,1.4*Лист2!AY$1,Лист2!AY$1))) -> 192.30769 | V7: =IF($G7="Москва",1.3*(IF(IF(K7="Да",1,0)=1,1.4*Лист2!AZ$1,Лист2!AZ$1)),(IF(IF(K7="Да",1,0)=1,1.4*Лист2!AZ$1,Лист2!AZ$1))) -> 920.76923 | W7: =IF($G7="Москва",1.3*(IF(IF(L7="Да",1,0)=1,1.4*Лист2!BA$1,Лист2!BA$1)),(IF(IF(L7="Да",1,0)=1,1.4*Лист2!BA$1,Лист2!BA$1))) -> 323.07692 | X7: =IF($G7="Москва",1.3*(IF(IF(M7="Да",1,0)=1,1.4*Лист2!BB$1,Лист2!BB$1)),(IF(IF(M7="Да",1,0)=1,1.4*Лист2!BB$1,Лист2!BB$1))) -> 49.538462 | Y7: =IF($G7="Москва",1.3*(IF(IF(N7="Да",1,0)=1,1.4*Лист2!BC$1,Лист2!BC$1)),(IF(IF(N7="Да",1,0)=1,1.4*Лист2!BC$1,Лист2!BC$1))) -> 936.92308 | Z7: =IF($G7="Москва",1.3*(IF(IF(O7="Да",1,0)=1,1.4*Лист2!BD$1,Лист2!BD$1)),(IF(IF(O7="Да",1,0)=1,1.4*Лист2!BD$1,Лист2!BD$1))) -> 339.23077 | AA7: =IF($G7="Москва",1.3*(IF(IF(P7="Да",1,0)=1,1.4*Лист2!BE$1,Лист2!BE$1)),(IF(IF(P7="Да",1,0)=1,1.4*Лист2!BE$1,Лист2!BE$1))) -> 780.76923 | ... AD7: =IF($G7="Москва",1.3*(IF(IF(S7="Да",1,0)=1,1.4*Лист2!BH$1,Лист2!BH$1)),(IF(IF(S7="Да",1,0)=1,1.4*Лист2!BH$1,Лист2!BH$1))) -> 168.26923 | AE7: =SUM(T7:AD7) -> 4026.4231 | AF7: =AE7*4.2 -> 16910.977 | AG7: =AF7*2 -> 33821.954 | AH7: =IF(IF(G7="Москва",1,0)=1,Лист2!$BK$6,Лист2!$BL$6) -> 9230 | AI7: =AH7-AF7 -> -7680.9769 | AJ7: =(H7-AE7)*4.2 -> 4089.0231
A8: 1996080122 | B8: Жен | C8: 20 | D8: active | E8: Нет | F8: 12000 | G8: Москва | H8: 3000 | I8: Нет | J8: Нет | K8: Да | L8: Да | M8: Нет | N8: Да | O8: Нет | P8: Нет | Q8: Да | R8: Нет | S8: Да | T8: =IF($G8="Москва",1.3*(IF(IF(I8="Да",1,0)=1,1.4*Лист2!AX$1,Лист2!AX$1)),(IF(IF(I8="Да",1,0)=1,1.4*Лист2!AX$1,Лист2!AX$1))) -> 283.5 | U8: =IF($G8="Москва",1.3*(IF(IF(J8="Да",1,0)=1,1.4*Лист2!AY$1,Лист2!AY$1)),(IF(IF(J8="Да",1,0)=1,1.4*Лист2!AY$1,Лист2!AY$1))) -> 250 | V8: =IF($G8="Москва",1.3*(IF(IF(K8="Да",1,0)=1,1.4*Лист2!AZ$1,Лист2!AZ$1)),(IF(IF(K8="Да",1,0)=1,1.4*Лист2!AZ$1,Лист2!AZ$1))) -> 1197 | W8: =IF($G8="Москва",1.3*(IF(IF(L8="Да",1,0)=1,1.4*Лист2!BA$1,Лист2!BA$1)),(IF(IF(L8="Да",1,0)=1,1.4*Лист2!BA$1,Лист2!BA$1))) -> 420 | X8: =IF($G8="Москва",1.3*(IF(IF(M8="Да",1,0)=1,1.4*Лист2!BB$1,Лист2!BB$1)),(IF(IF(M8="Да",1,0)=1,1.4*Лист2!BB$1,Лист2!BB$1))) -> 46 | Y8: =IF($G8="Москва",1.3*(IF(IF(N8="Да",1,0)=1,1.4*Лист2!BC$1,Лист2!BC$1)),(IF(IF(N8="Да",1,0)=1,1.4*Лист2!BC$1,Лист2!BC$1))) -> 1218 | Z8: =IF($G8="Москва",1.3*(IF(IF(O8="Да",1,0)=1,1.4*Лист2!BD$1,Лист2!BD$1)),(IF(IF(O8="Да",1,0)=1,1.4*Лист2!BD$1,Лист2!BD$1))) -> 315 | AA8: =IF($G8="Москва",1.3*(IF(IF(P8="Да",1,0)=1,1.4*Лист2!BE$1,Лист2!BE$1)),(IF(IF(P8="Да",1,0)=1,1.4*Лист2!BE$1,Лист2!BE$1))) -> 725 | ... AD8: =IF($G8="Москва",1.3*(IF(IF(S8="Да",1,0)=1,1.4*Лист2!BH$1,Лист2!BH$1)),(IF(IF(S8="Да",1,0)=1,1.4*Лист2!BH$1,Лист2!BH$1))) -> 218.75 | AE8: =SUM(T8:AD8) -> 4799.95 | AF8: =AE8*4.2 -> 20159.79 | AG8: =AF8*2 -> 40319.58 | AH8: =IF(IF(G8="Москва",1,0)=1,Лист2!$BK$6,Лист2!$BL$6) -> 13651 | AI8: =AH8-AF8 -> -6508.79 | AJ8: =(H8-AE8)*4.2 -> -7559.79
A9: 1996092424 | B9: Муж | C9: 20 | D9: active | E9: Да | F9: 60000 | G9: Иркутск, Иркутская область | H9: 4000 | I9: Да | J9: Нет | K9: Да | L9: Да | M9: Нет | N9: Да | O9: Нет | P9: Нет | Q9: Да | R9: Нет | S9: Да | T9: =IF($G9="Москва",1.3*(IF(IF(I9="Да",1,0)=1,1.4*Лист2!AX$1,Лист2!AX$1)),(IF(IF(I9="Да",1,0)=1,1.4*Лист2!AX$1,Лист2!AX$1))) -> 305.30769 | U9: =IF($G9="Москва",1.3*(IF(IF(J9="Да",1,0)=1,1.4*Лист2!AY$1,Лист2!AY$1)),(IF(IF(J9="Да",1,0)=1,1.4*Лист2!AY$1,Лист2!AY$1))) -> 192.30769 | V9: =IF($G9="Москва",1.3*(IF(IF(K9="Да",1,0)=1,1.4*Лист2!AZ$1,Лист2!AZ$1)),(IF(IF(K9="Да",1,0)=1,1.4*Лист2!AZ$1,Лист2!AZ$1))) -> 920.76923 | W9: =IF($G9="Москва",1.3*(IF(IF(L9="Да",1,0)=1,1.4*Лист2!BA$1,Лист2!BA$1)),(IF(IF(L9="Да",1,0)=1,1.4*Лист2!BA$1,Лист2!BA$1))) -> 323.07692 | X9: =IF($G9="Москва",1.3*(IF(IF(M9="Да",1,0)=1,1.4*Лист2!BB$1,Лист2!BB$1)),(IF(IF(M9="Да",1,0)=1,1.4*Лист2!BB$1,Лист2!BB$1))) -> 35.384615 | Y9: =IF($G9="Москва",1.3*(IF(IF(N9="Да",1,0)=1,1.4*Лист2!BC$1,Лист2!BC$1)),(IF(IF(N9="Да",1,0)=1,1.4*Лист2!BC$1,Лист2!BC$1))) -> 936.92308 | Z9: =IF($G9="Москва",1.3*(IF(IF(O9="Да",1,0)=1,1.4*Лист2!BD$1,Лист2!BD$1)),(IF(IF(O9="Да",1,0)=1,1.4*Лист2!BD$1,Лист2!BD$1))) -> 242.30769 | AA9: =IF($G9="Москва",1.3*(IF(IF(P9="Да",1,0)=1,1.4*Лист2!BE$1,Лист2!BE$1)),(IF(IF(P9="Да",1,0)=1,1.4*Лист2!BE$1,Лист2!BE$1))) -> 557.69231 | ... AD9: =IF($G9="Москва",1.3*(IF(IF(S9="Да",1,0)=1,1.4*Лист2!BH$1,Лист2!BH$1)),(IF(IF(S9="Да",1,0)=1,1.4*Лист2!BH$1,Лист2!BH$1))) -> 168.26923 | AE9: =SUM(T9:AD9) -> 3779.5 | AF9: =AE9*4.2 -> 15873.9 | AG9: =AF9*2 -> 31747.8 | AH9: =IF(IF(G9="Москва",1,0)=1,Лист2!$BK$6,Лист2!$BL$6) -> 9230 | AI9: =AH9-AF9 -> -6643.9 | AJ9: =(H9-AE9)*4.2 -> 926.1
A10: 1996104494 | B10: Муж | C10: 20 | D10: medium | E10: Да | F10: 60000 | G10: Москва | H10: 9000 | I10: Да | J10: Нет | K10: Нет | L10: Нет | M10: Да | N10: Да | O10: Нет | P10: Нет | Q10: Да | R10: Нет | S10: Да | T10: =IF($G10="Москва",1.3*(IF(IF(I10="Да",1,0)=1,1.4*Лист2!AX$1,Лист2!AX$1)),(IF(IF(I10="Да",1,0)=1,1.4*Лист2!AX$1,Лист2!AX$1))) -> 396.9 | U10: =IF($G10="Москва",1.3*(IF(IF(J10="Да",1,0)=1,1.4*Лист2!AY$1,Лист2!AY$1)),(IF(IF(J10="Да",1,0)=1,1.4*Лист2!AY$1,Лист2!AY$1))) -> 250 | V10: =IF($G10="Москва",1.3*(IF(IF(K10="Да",1,0)=1,1.4*Лист2!AZ$1,Лист2!AZ$1)),(IF(IF(K10="Да",1,0)=1,1.4*Лист2!AZ$1,Лист2!AZ$1))) -> 855 | W10: =IF($G10="Москва",1.3*(IF(IF(L10="Да",1,0)=1,1.4*Лист2!BA$1,Лист2!BA$1)),(IF(IF(L10="Да",1,0)=1,1.4*Лист2!BA$1,Лист2!BA$1))) -> 300 | X10: =IF($G10="Москва",1.3*(IF(IF(M10="Да",1,0)=1,1.4*Лист2!BB$1,Лист2!BB$1)),(IF(IF(M10="Да",1,0)=1,1.4*Лист2!BB$1,Лист2!BB$1))) -> 64.4 | Y10: =IF($G10="Москва",1.3*(IF(IF(N10="Да",1,0)=1,1.4*Лист2!BC$1,Лист2!BC$1)),(IF(IF(N10="Да",1,0)=1,1.4*Лист2!BC$1,Лист2!BC$1))) -> 1218 | Z10: =IF($G10="Москва",1.3*(IF(IF(O10="Да",1,0)=1,1.4*Лист2!BD$1,Лист2!BD$1)),(IF(IF(O10="Да",1,0)=1,1.4*Лист2!BD$1,Лист2!BD$1))) -> 315 | AA10: =IF($G10="Москва",1.3*(IF(IF(P10="Да",1,0)=1,1.4*Лист2!BE$1,Лист2!BE$1)),(IF(IF(P10="Да",1,0)=1,1.4*Лист2!BE$1,Лист2!BE$1))) -> 725 | ... AD10: =IF($G10="Москва",1.3*(IF(IF(S10="Да",1,0)=1,1.4*Лист2!BH$1,Лист2!BH$1)),(IF(IF(S10="Да",1,0)=1,1.4*Лист2!BH$1,Лист2!BH$1))) -> 218.75 | AE10: =SUM(T10:AD10) -> 4469.75 | AF10: =AE10*4.2 -> 18772.95 | AG10: =AF10*2 -> 37545.9 | AH10: =IF(IF(G10="Москва",1,0)=1,Лист2!$BK$6,Лист2!$BL$6) -> 13651 | AI10: =AH10-AF10 -> -5121.95 | AJ10: =(H10-AE10)*4.2 -> 19027.05
A11: 1996106993 | B11: Жен | C11: 20 | D11: passive | E11: Нет | F11: 12000 | G11: Екатеринбург, Свердловская область | H11: 20000 | I11: Нет | J11: Нет | K11: Нет | L11: Нет | M11: Да | N11: Да | O11: Нет | P11: Нет | Q11: Нет | R11: Да | S11: Нет | T11: =IF($G11="Москва",1.3*(IF(IF(I11="Да",1,0)=1,1.4*Лист2!AX$1,Лист2!AX$1)),(IF(IF(I11="Да",1,0)=1,1.4*Лист2!AX$1,Лист2!AX$1))) -> 218.07692 | U11: =IF($G11="Москва",1.3*(IF(IF(J11="Да",1,0)=1,1.4*Лист2!AY$1,Лист2!AY$1)),(IF(IF(J11="Да",1,0)=1,1.4*Лист2!AY$1,Лист2!AY$1))) -> 192.30769 | V11: =IF($G11="Москва",1.3*(IF(IF(K11="Да",1,0)=1,1.4*Лист2!AZ$1,Лист2!AZ$1)),(IF(IF(K11="Да",1,0)=1,1.4*Лист2!AZ$1,Лист2!AZ$1))) -> 657.69231 | W11: =IF($G11="Москва",1.3*(IF(IF(L11="Да",1,0)=1,1.4*Лист2!BA$1,Лист2!BA$1)),(IF(IF(L11="Да",1,0)=1,1.4*Лист2!BA$1,Лист2!BA$1))) -> 230.76923 | X11: =IF($G11="Москва",1.3*(IF(IF(M11="Да",1,0)=1,1.4*Лист2!BB$1,Лист2!BB$1)),(IF(IF(M11="Да",1,0)=1,1.4*Лист2!BB$1,Лист2!BB$1))) -> 49.538462 | Y11: =IF($G11="Москва",1.3*(IF(IF(N11="Да",1,0)=1,1.4*Лист2!BC$1,Лист2!BC$1)),(IF(IF(N11="Да",1,0)=1,1.4*Лист2!BC$1,Лист2!BC$1))) -> 936.92308 | Z11: =IF($G11="Москва",1.3*(IF(IF(O11="Да",1,0)=1,1.4*Лист2!BD$1,Лист2!BD$1)),(IF(IF(O11="Да",1,0)=1,1.4*Лист2!BD$1,Лист2!BD$1))) -> 242.30769 | AA11: =IF($G11="Москва",1.3*(IF(IF(P11="Да",1,0)=1,1.4*Лист2!BE$1,Лист2!BE$1)),(IF(IF(P11="Да",1,0)=1,1.4*Лист2!BE$1,Лист2!BE$1))) -> 557.69231 | ... AD11: =IF($G11="Москва",1.3*(IF(IF(S11="Да",1,0)=1,1.4*Лист2!BH$1,Лист2!BH$1)),(IF(IF(S11="Да",1,0)=1,1.4*Лист2!BH$1,Лист2!BH$1))) -> 120.19231 | AE11: =SUM(T11:AD11) -> 3295.4231 | AF11: =AE11*4.2 -> 13840.777 | AG11: =AF11*2 -> 27681.554 | AH11: =IF(IF(G11="Москва",1,0)=1,Лист2!$BK$6,Лист2!$BL$6) -> 9230 | AI11: =AH11-AF11 -> -4610.7769 | AJ11: =(H11-AE11)*4.2 -> 70159.223
A12: 1996114680 | B12: Жен | C12: 20 | D12: active | E12: Да | F12: 21000 | G12: Волжский, Волгоградская область | H12: 5000 | I12: Нет | J12: Да | K12: Нет | L12: Нет | M12: Да | N12: Да | O12: Да | P12: Нет | Q12: Да | R12: Да | S12: Да | T12: =IF($G12="Москва",1.3*(IF(IF(I12="Да",1,0)=1,1.4*Лист2!AX$1,Лист2!AX$1)),(IF(IF(I12="Да",1,0)=1,1.4*Лист2!AX$1,Лист2!AX$1))) -> 218.07692 | U12: =IF($G12="Москва",1.3*(IF(IF(J12="Да",1,0)=1,1.4*Лист2!AY$1,Лист2!AY$1)),(IF(IF(J12="Да",1,0)=1,1.4*Лист2!AY$1,Лист2!AY$1))) -> 269.23077 | V12: =IF($G12="Москва",1.3*(IF(IF(K12="Да",1,0)=1,1.4*Лист2!AZ$1,Лист2!AZ$1)),(IF(IF(K12="Да",1,0)=1,1.4*Лист2!AZ$1,Лист2!AZ$1))) -> 657.69231 | W12: =IF($G12="Москва",1.3*(IF(IF(L12="Да",1,0)=1,1.4*Лист2!BA$1,Лист2!BA$1)),(IF(IF(L12="Да",1,0)=1,1.4*Лист2!BA$1,Лист2!BA$1))) -> 230.76923 | X12: =IF($G12="Москва",1.3*(IF(IF(M12="Да",1,0)=1,1.4*Лист2!BB$1,Лист2!BB$1)),(IF(IF(M12="Да",1,0)=1,1.4*Лист2!BB$1,Лист2!BB$1))) -> 49.538462 | Y12: =IF($G12="Москва",1.3*(IF(IF(N12="Да",1,0)=1,1.4*Лист2!BC$1,Лист2!BC$1)),(IF(IF(N12="Да",1,0)=1,1.4*Лист2!BC$1,Лист2!BC$1))) -> 936.92308 | Z12: =IF($G12="Москва",1.3*(IF(IF(O12="Да",1,0)=1,1.4*Лист2!BD$1,Лист2!BD$1)),(IF(IF(O12="Да",1,0)=1,1.4*Лист2!BD$1,Лист2!BD$1))) -> 339.23077 | AA12: =IF($G12="Москва",1.3*(IF(IF(P12="Да",1,0)=1,1.4*Лист2!BE$1,Лист2!BE$1)),(IF(IF(P12="Да",1,0)=1,1.4*Лист2!BE$1,Лист2!BE$1))) -> 557.69231 | ... AD12: =IF($G12="Москва",1.3*(IF(IF(S12="Да",1,0)=1,1.4*Лист2!BH$1,Лист2!BH$1)),(IF(IF(S12="Да",1,0)=1,1.4*Лист2!BH$1,Лист2!BH$1))) -> 168.26923 | AE12: =SUM(T12:AD12) -> 3536.7308 | AF12: =AE12*4.2 -> 14854.269 | AG12: =AF12*2 -> 29708.538 | AH12: =IF(IF(G12="Москва",1,0)=1,Лист2!$BK$6,Лист2!$BL$6) -> 9230 | AI12: =AH12-AF12 -> -5624.2692 | AJ12: =(H12-AE12)*4.2 -> 6145.7308
A13: 1996121848 | B13: Муж | C13: 20 | D13: medium | E13: Да | F13: 60000 | G13: Москва | H13: 7000 | I13: Да | J13: Да | K13: Да | L13: Да | M13: Нет | N13: Да | O13: Нет | P13: Нет | Q13: Да | R13: Нет | S13: Нет | T13: =IF($G13="Москва",1.3*(IF(IF(I13="Да",1,0)=1,1.4*Лист2!AX$1,Лист2!AX$1)),(IF(IF(I13="Да",1,0)=1,1.4*Лист2!AX$1,Лист2!AX$1))) -> 396.9 | U13: =IF($G13="Москва",1.3*(IF(IF(J13="Да",1,0)=1,1.4*Лист2!AY$1,Лист2!AY$1)),(IF(IF(J13="Да",1,0)=1,1.4*Лист2!AY$1,Лист2!AY$1))) -> 350 | V13: =IF($G13="Москва",1.3*(IF(IF(K13="Да",1,0)=1,1.4*Лист2!AZ$1,Лист2!AZ$1)),(IF(IF(K13="Да",1,0)=1,1.4*Лист2!AZ$1,Лист2!AZ$1))) -> 1197 | W13: =IF($G13="Москва",1.3*(IF(IF(L13="Да",1,0)=1,1.4*Лист2!BA$1,Лист2!BA$1)),(IF(IF(L13="Да",1,0)=1,1.4*Лист2!BA$1,Лист2!BA$1))) -> 420 | X13: =IF($G13="Москва",1.3*(IF(IF(M13="Да",1,0)=1,1.4*Лист2!BB$1,Лист2!BB$1)),(IF(IF(M13="Да",1,0)=1,1.4*Лист2!BB$1,Лист2!BB$1))) -> 46 | Y13: =IF($G13="Москва",1.3*(IF(IF(N13="Да",1,0)=1,1.4*Лист2!BC$1,Лист2!BC$1)),(IF(IF(N13="Да",1,0)=1,1.4*Лист2!BC$1,Лист2!BC$1))) -> 1218 | Z13: =IF($G13="Москва",1.3*(IF(IF(O13="Да",1,0)=1,1.4*Лист2!BD$1,Лист2!BD$1)),(IF(IF(O13="Да",1,0)=1,1.4*Лист2!BD$1,Лист2!BD$1))) -> 315 | AA13: =IF($G13="Москва",1.3*(IF(IF(P13="Да",1,0)=1,1.4*Лист2!BE$1,Лист2!BE$1)),(IF(IF(P13="Да",1,0)=1,1.4*Лист2!BE$1,Лист2!BE$1))) -> 725 | ... AD13: =IF($G13="Москва",1.3*(IF(IF(S13="Да",1,0)=1,1.4*Лист2!BH$1,Лист2!BH$1)),(IF(IF(S13="Да",1,0)=1,1.4*Лист2!BH$1,Лист2!BH$1))) -> 156.25 | AE13: =SUM(T13:AD13) -> 4950.85 | AF13: =AE13*4.2 -> 20793.57 | AG13: =AF13*2 -> 41587.14 | AH13: =IF(IF(G13="Москва",1,0)=1,Лист2!$BK$6,Лист2!$BL$6) -> 13651 | AI13: =AH13-AF13 -> -7142.57 | AJ13: =(H13-AE13)*4.2 -> 8606.43
... A24: 1996305312 | B24: Жен | C24: 20 | D24: active | E24: Нет | F24: 60000 | G24: Москва | H24: 4000 | I24: Да | J24: Нет | K24: Да | L24: Нет | M24: Нет | N24: Да | O24: Нет | P24: Нет | Q24: Нет | R24: Нет | S24: Да | T24: =IF($G24="Москва",1.3*(IF(IF(I24="Да",1,0)=1,1.4*Лист2!AX$1,Лист2!AX$1)),(IF(IF(I24="Да",1,0)=1,1.4*Лист2!AX$1,Лист2!AX$1))) -> 396.9 | U24: =IF($G24="Москва",1.3*(IF(IF(J24="Да",1,0)=1,1.4*Лист2!AY$1,Лист2!AY$1)),(IF(IF(J24="Да",1,0)=1,1.4*Лист2!AY$1,Лист2!AY$1))) -> 250 | V24: =IF($G24="Москва",1.3*(IF(IF(K24="Да",1,0)=1,1.4*Лист2!AZ$1,Лист2!AZ$1)),(IF(IF(K24="Да",1,0)=1,1.4*Лист2!AZ$1,Лист2!AZ$1))) -> 1197 | W24: =IF($G24="Москва",1.3*(IF(IF(L24="Да",1,0)=1,1.4*Лист2!BA$1,Лист2!BA$1)),(IF(IF(L24="Да",1,0)=1,1.4*Лист2!BA$1,Лист2!BA$1))) -> 300 | X24: =IF($G24="Москва",1.3*(IF(IF(M24="Да",1,0)=1,1.4*Лист2!BB$1,Лист2!BB$1)),(IF(IF(M24="Да",1,0)=1,1.4*Лист2!BB$1,Лист2!BB$1))) -> 46 | Y24: =IF($G24="Москва",1.3*(IF(IF(N24="Да",1,0)=1,1.4*Лист2!BC$1,Лист2!BC$1)),(IF(IF(N24="Да",1,0)=1,1.4*Лист2!BC$1,Лист2!BC$1))) -> 1218 | Z24: =IF($G24="Москва",1.3*(IF(IF(O24="Да",1,0)=1,1.4*Лист2!BD$1,Лист2!BD$1)),(IF(IF(O24="Да",1,0)=1,1.4*Лист2!BD$1,Лист2!BD$1))) -> 315 | AA24: =IF($G24="Москва",1.3*(IF(IF(P24="Да",1,0)=1,1.4*Лист2!BE$1,Лист2!BE$1)),(IF(IF(P24="Да",1,0)=1,1.4*Лист2!BE$1,Лист2!BE$1))) -> 725 | ... AD24: =IF($G24="Москва",1.3*(IF(IF(S24="Да",1,0)=1,1.4*Лист2!BH$1,Лист2!BH$1)),(IF(IF(S24="Да",1,0)=1,1.4*Лист2!BH$1,Лист2!BH$1))) -> 218.75 | AE24: =SUM(T24:AD24) -> 4768.15 | AF24: =AE24*4.2 -> 20026.23 | AG24: =AF24*2 -> 40052.46 | AH24: =IF(IF(G24="Москва",1,0)=1,Лист2!$BK$6,Лист2!$BL$6) -> 13651 | AI24: =AH24-AF24 -> -6375.23 | AJ24: =(H24-AE24)*4.2 -> -3226.23
A25: 1996328039 | B25: Муж | C25: 20 | D25: medium | E25: Да | F25: 60000 | G25: Москва | H25: 5000 | I25: Нет | J25: Нет | K25: Нет | L25: Нет | M25: Нет | N25: Нет | O25: Нет | P25: Да | Q25: Да | R25: Нет | S25: Да | T25: =IF($G25="Москва",1.3*(IF(IF(I25="Да",1,0)=1,1.4*Лист2!AX$1,Лист2!AX$1)),(IF(IF(I25="Да",1,0)=1,1.4*Лист2!AX$1,Лист2!AX$1))) -> 283.5 | U25: =IF($G25="Москва",1.3*(IF(IF(J25="Да",1,0)=1,1.4*Лист2!AY$1,Лист2!AY$1)),(IF(IF(J25="Да",1,0)=1,1.4*Лист2!AY$1,Лист2!AY$1))) -> 250 | V25: =IF($G25="Москва",1.3*(IF(IF(K25="Да",1,0)=1,1.4*Лист2!AZ$1,Лист2!AZ$1)),(IF(IF(K25="Да",1,0)=1,1.4*Лист2!AZ$1,Лист2!AZ$1))) -> 855 | W25: =IF($G25="Москва",1.3*(IF(IF(L25="Да",1,0)=1,1.4*Лист2!BA$1,Лист2!BA$1)),(IF(IF(L25="Да",1,0)=1,1.4*Лист2!BA$1,Лист2!BA$1))) -> 300 | X25: =IF($G25="Москва",1.3*(IF(IF(M25="Да",1,0)=1,1.4*Лист2!BB$1,Лист2!BB$1)),(IF(IF(M25="Да",1,0)=1,1.4*Лист2!BB$1,Лист2!BB$1))) -> 46 | Y25: =IF($G25="Москва",1.3*(IF(IF(N25="Да",1,0)=1,1.4*Лист2!BC$1,Лист2!BC$1)),(IF(IF(N25="Да",1,0)=1,1.4*Лист2!BC$1,Лист2!BC$1))) -> 870 | Z25: =IF($G25="Москва",1.3*(IF(IF(O25="Да",1,0)=1,1.4*Лист2!BD$1,Лист2!BD$1)),(IF(IF(O25="Да",1,0)=1,1.4*Лист2!BD$1,Лист2!BD$1))) -> 315 | AA25: =IF($G25="Москва",1.3*(IF(IF(P25="Да",1,0)=1,1.4*Лист2!BE$1,Лист2!BE$1)),(IF(IF(P25="Да",1,0)=1,1.4*Лист2!BE$1,Лист2!BE$1))) -> 1015 | ... AD25: =IF($G25="Москва",1.3*(IF(IF(S25="Да",1,0)=1,1.4*Лист2!BH$1,Лист2!BH$1)),(IF(IF(S25="Да",1,0)=1,1.4*Лист2!BH$1,Лист2!BH$1))) -> 218.75 | AE25: =SUM(T25:AD25) -> 4279.95 | AF25: =AE25*4.2 -> 17975.79 | AG25: =AF25*2 -> 35951.58 | AH25: =IF(IF(G25="Москва",1,0)=1,Лист2!$BK$6,Лист2!$BL$6) -> 13651 | AI25: =AH25-AF25 -> -4324.79 | AJ25: =(H25-AE25)*4.2 -> 3024.21
A26: 1996328591 | B26: Муж | C26: 20 | D26: active | E26: Да | F26: 30000 | G26: Москва | H26: 10000 | I26: Нет | J26: Нет | K26: Нет | L26: Нет | M26: Нет | N26: Нет | O26: Нет | P26: Нет | Q26: Нет | R26: Нет | S26: Нет | T26: =IF($G26="Москва",1.3*(IF(IF(I26="Да",1,0)=1,1.4*Лист2!AX$1,Лист2!AX$1)),(IF(IF(I26="Да",1,0)=1,1.4*Лист2!AX$1,Лист2!AX$1))) -> 283.5 | U26: =IF($G26="Москва",1.3*(IF(IF(J26="Да",1,0)=1,1.4*Лист2!AY$1,Лист2!AY$1)),(IF(IF(J26="Да",1,0)=1,1.4*Лист2!AY$1,Лист2!AY$1))) -> 250 | V26: =IF($G26="Москва",1.3*(IF(IF(K26="Да",1,0)=1,1.4*Лист2!AZ$1,Лист2!AZ$1)),(IF(IF(K26="Да",1,0)=1,1.4*Лист2!AZ$1,Лист2!AZ$1))) -> 855 | W26: =IF($G26="Москва",1.3*(IF(IF(L26="Да",1,0)=1,1.4*Лист2!BA$1,Лист2!BA$1)),(IF(IF(L26="Да",1,0)=1,1.4*Лист2!BA$1,Лист2!BA$1))) -> 300 | X26: =IF($G26="Москва",1.3*(IF(IF(M26="Да",1,0)=1,1.4*Лист2!BB$1,Лист2!BB$1)),(IF(IF(M26="Да",1,0)=1,1.4*Лист2!BB$1,Лист2!BB$1))) -> 46 | Y26: =IF($G26="Москва",1.3*(IF(IF(N26="Да",1,0)=1,1.4*Лист2!BC$1,Лист2!BC$1)),(IF(IF(N26="Да",1,0)=1,1.4*Лист2!BC$1,Лист2!BC$1))) -> 870 | Z26: =IF($G26="Москва",1.3*(IF(IF(O26="Да",1,0)=1,1.4*Лист2!BD$1,Лист2!BD$1)),(IF(IF(O26="Да",1,0)=1,1.4*Лист2!BD$1,Лист2!BD$1))) -> 315 | AA26: =IF($G26="Москва",1.3*(IF(IF(P26="Да",1,0)=1,1.4*Лист2!BE$1,Лист2!BE$1)),(IF(IF(P26="Да",1,0)=1,1.4*Лист2!BE$1,Лист2!BE$1))) -> 725 | ... AD26: =IF($G26="Москва",1.3*(IF(IF(S26="Да",1,0)=1,1.4*Лист2!BH$1,Лист2!BH$1)),(IF(IF(S26="Да",1,0)=1,1.4*Лист2!BH$1,Лист2!BH$1))) -> 156.25 | AE26: =SUM(T26:AD26) -> 3902.25 | AF26: =AE26*4.2 -> 16389.45 | AG26: =AF26*2 -> 32778.9 | AH26: =IF(IF(G26="Москва",1,0)=1,Лист2!$BK$6,Лист2!$BL$6) -> 13651 | AI26: =AH26-AF26 -> -2738.45 | AJ26: =(H26-AE26)*4.2 -> 25610.55
A27: 1996330348 | B27: Жен | C27: 20 | D27: active | E27: Да | F27: 60000 | G27: Москва | H27: 7000 | I27: Да | J27: Нет | K27: Нет | L27: Да | M27: Нет | N27: Да | O27: Нет | P27: Нет | Q27: Да | R27: Нет | S27: Да | T27: =IF($G27="Москва",1.3*(IF(IF(I27="Да",1,0)=1,1.4*Лист2!AX$1,Лист2!AX$1)),(IF(IF(I27="Да",1,0)=1,1.4*Лист2!AX$1,Лист2!AX$1))) -> 396.9 | U27: =IF($G27="Москва",1.3*(IF(IF(J27="Да",1,0)=1,1.4*Лист2!AY$1,Лист2!AY$1)),(IF(IF(J27="Да",1,0)=1,1.4*Лист2!AY$1,Лист2!AY$1))) -> 250 | V27: =IF($G27="Москва",1.3*(IF(IF(K27="Да",1,0)=1,1.4*Лист2!AZ$1,Лист2!AZ$1)),(IF(IF(K27="Да",1,0)=1,1.4*Лист2!AZ$1,Лист2!AZ$1))) -> 855 | W27: =IF($G27="Москва",1.3*(IF(IF(L27="Да",1,0)=1,1.4*Лист2!BA$1,Лист2!BA$1)),(IF(IF(L27="Да",1,0)=1,1.4*Лист2!BA$1,Лист2!BA$1))) -> 420 | X27: =IF($G27="Москва",1.3*(IF(IF(M27="Да",1,0)=1,1.4*Лист2!BB$1,Лист2!BB$1)),(IF(IF(M27="Да",1,0)=1,1.4*Лист2!BB$1,Лист2!BB$1))) -> 46 | Y27: =IF($G27="Москва",1.3*(IF(IF(N27="Да",1,0)=1,1.4*Лист2!BC$1,Лист2!BC$1)),(IF(IF(N27="Да",1,0)=1,1.4*Лист2!BC$1,Лист2!BC$1))) -> 1218 | Z27: =IF($G27="Москва",1.3*(IF(IF(O27="Да",1,0)=1,1.4*Лист2!BD$1,Лист2!BD$1)),(IF(IF(O27="Да",1,0)=1,1.4*Лист2!BD$1,Лист2!BD$1))) -> 315 | AA27: =IF($G27="Москва",1.3*(IF(IF(P27="Да",1,0)=1,1.4*Лист2!BE$1,Лист2!BE$1)),(IF(IF(P27="Да",1,0)=1,1.4*Лист2!BE$1,Лист2!BE$1))) -> 725 | ... AD27: =IF($G27="Москва",1.3*(IF(IF(S27="Да",1,0)=1,1.4*Лист2!BH$1,Лист2!BH$1)),(IF(IF(S27="Да",1,0)=1,1.4*Лист2!BH$1,Лист2!BH$1))) -> 218.75 | AE27: =SUM(T27:AD27) -> 4571.35 | AF27: =AE27*4.2 -> 19199.67 | AG27: =AF27*2 -> 38399.34 | AH27: =IF(IF(G27="Москва",1,0)=1,Лист2!$BK$6,Лист2!$BL$6) -> 13651 | AI27: =AH27-AF27 -> -5548.67 | AJ27: =(H27-AE27)*4.2 -> 10200.33
A28: 1996330598 | B28: Жен | C28: 20 | D28: medium | E28: Да | F28: 60000 | G28: Москва | H28: 15000 | I28: Нет | J28: Нет | K28: Нет | L28: Да | M28: Нет | N28: Да | O28: Да | P28: Нет | Q28: Да | R28: Да | S28: Нет | T28: =IF($G28="Москва",1.3*(IF(IF(I28="Да",1,0)=1,1.4*Лист2!AX$1,Лист2!AX$1)),(IF(IF(I28="Да",1,0)=1,1.4*Лист2!AX$1,Лист2!AX$1))) -> 283.5 | U28: =IF($G28="Москва",1.3*(IF(IF(J28="Да",1,0)=1,1.4*Лист2!AY$1,Лист2!AY$1)),(IF(IF(J28="Да",1,0)=1,1.4*Лист2!AY$1,Лист2!AY$1))) -> 250 | V28: =IF($G28="Москва",1.3*(IF(IF(K28="Да",1,0)=1,1.4*Лист2!AZ$1,Лист2!AZ$1)),(IF(IF(K28="Да",1,0)=1,1.4*Лист2!AZ$1,Лист2!AZ$1))) -> 855 | W28: =IF($G28="Москва",1.3*(IF(IF(L28="Да",1,0)=1,1.4*Лист2!BA$1,Лист2!BA$1)),(IF(IF(L28="Да",1,0)=1,1.4*Лист2!BA$1,Лист2!BA$1))) -> 420 | X28: =IF($G28="Москва",1.3*(IF(IF(M28="Да",1,0)=1,1.4*Лист2!BB$1,Лист2!BB$1)),(IF(IF(M28="Да",1,0)=1,1.4*Лист2!BB$1,Лист2!BB$1))) -> 46 | Y28: =IF($G28="Москва",1.3*(IF(IF(N28="Да",1,0)=1,1.4*Лист2!BC$1,Лист2!BC$1)),(IF(IF(N28="Да",1,0)=1,1.4*Лист2!BC$1,Лист2!BC$1))) -> 1218 | Z28: =IF($G28="Москва",1.3*(IF(IF(O28="Да",1,0)=1,1.4*Лист2!BD$1,Лист2!BD$1)),(IF(IF(O28="Да",1,0)=1,1.4*Лист2!BD$1,Лист2!BD$1))) -> 441 | AA28: =IF($G28="Москва",1.3*(IF(IF(P28="Да",1,0)=1,1.4*Лист2!BE$1,Лист2!BE$1)),(IF(IF(P28="Да",1,0)=1,1.4*Лист2!BE$1,Лист2!BE$1))) -> 725 | ... AD28: =IF($G28="Москва",1.3*(IF(IF(S28="Да",1,0)=1,1.4*Лист2!BH$1,Лист2!BH$1)),(IF(IF(S28="Да",1,0)=1,1.4*Лист2!BH$1,Лист2!BH$1))) -> 156.25 | AE28: =SUM(T28:AD28) -> 4536.85 | AF28: =AE28*4.2 -> 19054.77 | AG28: =AF28*2 -> 38109.54 | AH28: =IF(IF(G28="Москва",1,0)=1,Лист2!$BK$6,Лист2!$BL$6) -> 13651 | AI28: =AH28-AF28 -> -5403.77 | AJ28: =(H28-AE28)*4.2 -> 43945.23
A29: 1996331297 | B29: Муж | C29: 20 | D29: medium | E29: Нет | F29: 12000 | G29: Москва | H29: 20000 | I29: Нет | J29: Нет | K29: Да | L29: Нет | M29: Нет | N29: Да | O29: Нет | P29: Да | Q29: Да | R29: Нет | S29: Нет | T29: =IF($G29="Москва",1.3*(IF(IF(I29="Да",1,0)=1,1.4*Лист2!AX$1,Лист2!AX$1)),(IF(IF(I29="Да",1,0)=1,1.4*Лист2!AX$1,Лист2!AX$1))) -> 283.5 | U29: =IF($G29="Москва",1.3*(IF(IF(J29="Да",1,0)=1,1.4*Лист2!AY$1,Лист2!AY$1)),(IF(IF(J29="Да",1,0)=1,1.4*Лист2!AY$1,Лист2!AY$1))) -> 250 | V29: =IF($G29="Москва",1.3*(IF(IF(K29="Да",1,0)=1,1.4*Лист2!AZ$1,Лист2!AZ$1)),(IF(IF(K29="Да",1,0)=1,1.4*Лист2!AZ$1,Лист2!AZ$1))) -> 1197 | W29: =IF($G29="Москва",1.3*(IF(IF(L29="Да",1,0)=1,1.4*Лист2!BA$1,Лист2!BA$1)),(IF(IF(L29="Да",1,0)=1,1.4*Лист2!BA$1,Лист2!BA$1))) -> 300 | X29: =IF($G29="Москва",1.3*(IF(IF(M29="Да",1,0)=1,1.4*Лист2!BB$1,Лист2!BB$1)),(IF(IF(M29="Да",1,0)=1,1.4*Лист2!BB$1,Лист2!BB$1))) -> 46 | Y29: =IF($G29="Москва",1.3*(IF(IF(N29="Да",1,0)=1,1.4*Лист2!BC$1,Лист2!BC$1)),(IF(IF(N29="Да",1,0)=1,1.4*Лист2!BC$1,Лист2!BC$1))) -> 1218 | Z29: =IF($G29="Москва",1.3*(IF(IF(O29="Да",1,0)=1,1.4*Лист2!BD$1,Лист2!BD$1)),(IF(IF(O29="Да",1,0)=1,1.4*Лист2!BD$1,Лист2!BD$1))) -> 315 | AA29: =IF($G29="Москва",1.3*(IF(IF(P29="Да",1,0)=1,1.4*Лист2!BE$1,Лист2!BE$1)),(IF(IF(P29="Да",1,0)=1,1.4*Лист2!BE$1,Лист2!BE$1))) -> 1015 | ... AD29: =IF($G29="Москва",1.3*(IF(IF(S29="Да",1,0)=1,1.4*Лист2!BH$1,Лист2!BH$1)),(IF(IF(S29="Да",1,0)=1,1.4*Лист2!BH$1,Лист2!BH$1))) -> 156.25 | AE29: =SUM(T29:AD29) -> 4907.45 | AF29: =AE29*4.2 -> 20611.29 | AG29: =AF29*2 -> 41222.58 | AH29: =IF(IF(G29="Москва",1,0)=1,Лист2!$BK$6,Лист2!$BL$6) -> 13651 | AI29: =AH29-AF29 -> -6960.29 | AJ29: =(H29-AE29)*4.2 -> 63388.71
A30: 1996352201 | B30: Муж | C30: 20 | D30: passive | E30: Нет | F30: 12000 | G30: Волжский, Волгоградская область | H30: 20000 | I30: Нет | J30: Да | K30: Нет | L30: Да | M30: Нет | N30: Да | O30: Нет | P30: Да | Q30: Да | R30: Да | S30: Нет | T30: =IF($G30="Москва",1.3*(IF(IF(I30="Да",1,0)=1,1.4*Лист2!AX$1,Лист2!AX$1)),(IF(IF(I30="Да",1,0)=1,1.4*Лист2!AX$1,Лист2!AX$1))) -> 218.07692 | U30: =IF($G30="Москва",1.3*(IF(IF(J30="Да",1,0)=1,1.4*Лист2!AY$1,Лист2!AY$1)),(IF(IF(J30="Да",1,0)=1,1.4*Лист2!AY$1,Лист2!AY$1))) -> 269.23077 | V30: =IF($G30="Москва",1.3*(IF(IF(K30="Да",1,0)=1,1.4*Лист2!AZ$1,Лист2!AZ$1)),(IF(IF(K30="Да",1,0)=1,1.4*Лист2!AZ$1,Лист2!AZ$1))) -> 657.69231 | W30: =IF($G30="Москва",1.3*(IF(IF(L30="Да",1,0)=1,1.4*Лист2!BA$1,Лист2!BA$1)),(IF(IF(L30="Да",1,0)=1,1.4*Лист2!BA$1,Лист2!BA$1))) -> 323.07692 | X30: =IF($G30="Москва",1.3*(IF(IF(M30="Да",1,0)=1,1.4*Лист2!BB$1,Лист2!BB$1)),(IF(IF(M30="Да",1,0)=1,1.4*Лист2!BB$1,Лист2!BB$1))) -> 35.384615 | Y30: =IF($G30="Москва",1.3*(IF(IF(N30="Да",1,0)=1,1.4*Лист2!BC$1,Лист2!BC$1)),(IF(IF(N30="Да",1,0)=1,1.4*Лист2!BC$1,Лист2!BC$1))) -> 936.92308 | Z30: =IF($G30="Москва",1.3*(IF(IF(O30="Да",1,0)=1,1.4*Лист2!BD$1,Лист2!BD$1)),(IF(IF(O30="Да",1,0)=1,1.4*Лист2!BD$1,Лист2!BD$1))) -> 242.30769 | AA30: =IF($G30="Москва",1.3*(IF(IF(P30="Да",1,0)=1,1.4*Лист2!BE$1,Лист2!BE$1)),(IF(IF(P30="Да",1,0)=1,1.4*Лист2!BE$1,Лист2!BE$1))) -> 780.76923 | ... AD30: =IF($G30="Москва",1.3*(IF(IF(S30="Да",1,0)=1,1.4*Лист2!BH$1,Лист2!BH$1)),(IF(IF(S30="Да",1,0)=1,1.4*Лист2!BH$1,Лист2!BH$1))) -> 120.19231 | AE30: =SUM(T30:AD30) -> 3692.9615 | AF30: =AE30*4.2 -> 15510.438 | AG30: =AF30*2 -> 31020.877 | AH30: =IF(IF(G30="Москва",1,0)=1,Лист2!$BK$6,Лист2!$BL$6) -> 9230 | AI30: =AH30-AF30 -> -6280.4385 | AJ30: =(H30-AE30)*4.2 -> 68489.562
A31: 1996357490 | B31: Муж | C31: 20 | D31: medium | E31: Да | F31: 60000 | G31: Москва | H31: 1000 | I31: Нет | J31: Нет | K31: Нет | L31: Да | M31: Нет | N31: Нет | O31: Нет | P31: Да | Q31: Да | R31: Нет | S31: Нет | T31: =IF($G31="Москва",1.3*(IF(IF(I31="Да",1,0)=1,1.4*Лист2!AX$1,Лист2!AX$1)),(IF(IF(I31="Да",1,0)=1,1.4*Лист2!AX$1,Лист2!AX$1))) -> 283.5 | U31: =IF($G31="Москва",1.3*(IF(IF(J31="Да",1,0)=1,1.4*Лист2!AY$1,Лист2!AY$1)),(IF(IF(J31="Да",1,0)=1,1.4*Лист2!AY$1,Лист2!AY$1))) -> 250 | V31: =IF($G31="Москва",1.3*(IF(IF(K31="Да",1,0)=1,1.4*Лист2!AZ$1,Лист2!AZ$1)),(IF(IF(K31="Да",1,0)=1,1.4*Лист2!AZ$1,Лист2!AZ$1))) -> 855 | W31: =IF($G31="Москва",1.3*(IF(IF(L31="Да",1,0)=1,1.4*Лист2!BA$1,Лист2!BA$1)),(IF(IF(L31="Да",1,0)=1,1.4*Лист2!BA$1,Лист2!BA$1))) -> 420 | X31: =IF($G31="Москва",1.3*(IF(IF(M31="Да",1,0)=1,1.4*Лист2!BB$1,Лист2!BB$1)),(IF(IF(M31="Да",1,0)=1,1.4*Лист2!BB$1,Лист2!BB$1))) -> 46 | Y31: =IF($G31="Москва",1.3*(IF(IF(N31="Да",1,0)=1,1.4*Лист2!BC$1,Лист2!BC$1)),(IF(IF(N31="Да",1,0)=1,1.4*Лист2!BC$1,Лист2!BC$1))) -> 870 | Z31: =IF($G31="Москва",1.3*(IF(IF(O31="Да",1,0)=1,1.4*Лист2!BD$1,Лист2!BD$1)),(IF(IF(O31="Да",1,0)=1,1.4*Лист2!BD$1,Лист2!BD$1))) -> 315 | AA31: =IF($G31="Москва",1.3*(IF(IF(P31="Да",1,0)=1,1.4*Лист2!BE$1,Лист2!BE$1)),(IF(IF(P31="Да",1,0)=1,1.4*Лист2!BE$1,Лист2!BE$1))) -> 1015 | ... AD31: =IF($G31="Москва",1.3*(IF(IF(S31="Да",1,0)=1,1.4*Лист2!BH$1,Лист2!BH$1)),(IF(IF(S31="Да",1,0)=1,1.4*Лист2!BH$1,Лист2!BH$1))) -> 156.25 | AE31: =SUM(T31:AD31) -> 4337.45 | AF31: =AE31*4.2 -> 18217.29 | AG31: =AF31*2 -> 36434.58 | AH31: =IF(IF(G31="Москва",1,0)=1,Лист2!$BK$6,Лист2!$BL$6) -> 13651 | AI31: =AH31-AF31 -> -4566.29 | AJ31: =(H31-AE31)*4.2 -> -14017.29
A32: 1996382686 | B32: Муж | C32: 20 | D32: medium | E32: Нет | F32: 12000 | G32: Щёлково, Москва и Московская область | H32: 2777 | I32: Да | J32: Нет | K32: Нет | L32: Нет | M32: Да | N32: Да | O32: Нет | P32: Нет | Q32: Да | R32: Да | S32: Да | T32: =IF($G32="Москва",1.3*(IF(IF(I32="Да",1,0)=1,1.4*Лист2!AX$1,Лист2!AX$1)),(IF(IF(I32="Да",1,0)=1,1.4*Лист2!AX$1,Лист2!AX$1))) -> 305.30769 | U32: =IF($G32="Москва",1.3*(IF(IF(J32="Да",1,0)=1,1.4*Лист2!AY$1,Лист2!AY$1)),(IF(IF(J32="Да",1,0)=1,1.4*Лист2!AY$1,Лист2!AY$1))) -> 192.30769 | V32: =IF($G32="Москва",1.3*(IF(IF(K32="Да",1,0)=1,1.4*Лист2!AZ$1,Лист2!AZ$1)),(IF(IF(K32="Да",1,0)=1,1.4*Лист2!AZ$1,Лист2!AZ$1))) -> 657.69231 | W32: =IF($G32="Москва",1.3*(IF(IF(L32="Да",1,0)=1,1.4*Лист2!BA$1,Лист2!BA$1)),(IF(IF(L32="Да",1,0)=1,1.4*Лист2!BA$1,Лист2!BA$1))) -> 230.76923 | X32: =IF($G32="Москва",1.3*(IF(IF(M32="Да",1,0)=1,1.4*Лист2!BB$1,Лист2!BB$1)),(IF(IF(M32="Да",1,0)=1,1.4*Лист2!BB$1,Лист2!BB$1))) -> 49.538462 | Y32: =IF($G32="Москва",1.3*(IF(IF(N32="Да",1,0)=1,1.4*Лист2!BC$1,Лист2!BC$1)),(IF(IF(N32="Да",1,0)=1,1.4*Лист2!BC$1,Лист2!BC$1))) -> 936.92308 | Z32: =IF($G32="Москва",1.3*(IF(IF(O32="Да",1,0)=1,1.4*Лист2!BD$1,Лист2!BD$1)),(IF(IF(O32="Да",1,0)=1,1.4*Лист2!BD$1,Лист2!BD$1))) -> 242.30769 | AA32: =IF($G32="Москва",1.3*(IF(IF(P32="Да",1,0)=1,1.4*Лист2!BE$1,Лист2!BE$1)),(IF(IF(P32="Да",1,0)=1,1.4*Лист2!BE$1,Лист2!BE$1))) -> 557.69231 | ... AD32: =IF($G32="Москва",1.3*(IF(IF(S32="Да",1,0)=1,1.4*Лист2!BH$1,Лист2!BH$1)),(IF(IF(S32="Да",1,0)=1,1.4*Лист2!BH$1,Лист2!BH$1))) -> 168.26923 | AE32: =SUM(T32:AD32) -> 3450.1154 | AF32: =AE32*4.2 -> 14490.485 | AG32: =AF32*2 -> 28980.969 | AH32: =IF(IF(G32="Москва",1,0)=1,Лист2!$BK$6,Лист2!$BL$6) -> 9230 | AI32: =AH32-AF32 -> -5260.4846 | AJ32: =(H32-AE32)*4.2 -> -2827.0846
A33: 1996462484 | B33: Жен | C33: 35 | D33: active | E33: Да | F33: 60000 | G33: Улан-Удэ, Республика Бурятия | H33: 20000 | I33: Нет | J33: Нет | K33: Да | L33: Да | M33: Нет | N33: Да | O33: Нет | P33: Нет | Q33: Да | R33: Нет | S33: Нет | T33: =IF($G33="Москва",1.3*(IF(IF(I33="Да",1,0)=1,1.4*Лист2!AX$1,Лист2!AX$1)),(IF(IF(I33="Да",1,0)=1,1.4*Лист2!AX$1,Лист2!AX$1))) -> 218.07692 | U33: =IF($G33="Москва",1.3*(IF(IF(J33="Да",1,0)=1,1.4*Лист2!AY$1,Лист2!AY$1)),(IF(IF(J33="Да",1,0)=1,1.4*Лист2!AY$1,Лист2!AY$1))) -> 192.30769 | V33: =IF($G33="Москва",1.3*(IF(IF(K33="Да",1,0)=1,1.4*Лист2!AZ$1,Лист2!AZ$1)),(IF(IF(K33="Да",1,0)=1,1.4*Лист2!AZ$1,Лист2!AZ$1))) -> 920.76923 | W33: =IF($G33="Москва",1.3*(IF(IF(L33="Да",1,0)=1,1.4*Лист2!BA$1,Лист2!BA$1)),(IF(IF(L33="Да",1,0)=1,1.4*Лист2!BA$1,Лист2!BA$1))) -> 323.07692 | X33: =IF($G33="Москва",1.3*(IF(IF(M33="Да",1,0)=1,1.4*Лист2!BB$1,Лист2!BB$1)),(IF(IF(M33="Да",1,0)=1,1.4*Лист2!BB$1,Лист2!BB$1))) -> 35.384615 | Y33: =IF($G33="Москва",1.3*(IF(IF(N33="Да",1,0)=1,1.4*Лист2!BC$1,Лист2!BC$1)),(IF(IF(N33="Да",1,0)=1,1.4*Лист2!BC$1,Лист2!BC$1))) -> 936.92308 | Z33: =IF($G33="Москва",1.3*(IF(IF(O33="Да",1,0)=1,1.4*Лист2!BD$1,Лист2!BD$1)),(IF(IF(O33="Да",1,0)=1,1.4*Лист2!BD$1,Лист2!BD$1))) -> 242.30769 | AA33: =IF($G33="Москва",1.3*(IF(IF(P33="Да",1,0)=1,1.4*Лист2!BE$1,Лист2!BE$1)),(IF(IF(P33="Да",1,0)=1,1.4*Лист2!BE$1,Лист2!BE$1))) -> 557.69231 | ... AD33: =IF($G33="Москва",1.3*(IF(IF(S33="Да",1,0)=1,1.4*Лист2!BH$1,Лист2!BH$1)),(IF(IF(S33="Да",1,0)=1,1.4*Лист2!BH$1,Лист2!BH$1))) -> 120.19231 | AE33: =SUM(T33:AD33) -> 3644.1923 | AF33: =AE33*4.2 -> 15305.608 | AG33: =AF33*2 -> 30611.215 | AH33: =IF(IF(G33="Москва",1,0)=1,Лист2!$BK$6,Лист2!$BL$6) -> 9230 | AI33: =AH33-AF33 -> -6075.6077 | AJ33: =(H33-AE33)*4.2 -> 68694.392
A34: 1996671051 | B34: Жен | C34: 20 | D34: medium | E34: Да | F34: 30000 | G34: Тула, Тульская область | H34: 5000 | I34: Нет | J34: Нет | K34: Да | L34: Да | M34: Нет | N34: Да | O34: Да | P34: Нет | Q34: Да | R34: Да | S34: Да | T34: =IF($G34="Москва",1.3*(IF(IF(I34="Да",1,0)=1,1.4*Лист2!AX$1,Лист2!AX$1)),(IF(IF(I34="Да",1,0)=1,1.4*Лист2!AX$1,Лист2!AX$1))) -> 218.07692 | U34: =IF($G34="Москва",1.3*(IF(IF(J34="Да",1,0)=1,1.4*Лист2!AY$1,Лист2!AY$1)),(IF(IF(J34="Да",1,0)=1,1.4*Лист2!AY$1,Лист2!AY$1))) -> 192.30769 | V34: =IF($G34="Москва",1.3*(IF(IF(K34="Да",1,0)=1,1.4*Лист2!AZ$1,Лист2!AZ$1)),(IF(IF(K34="Да",1,0)=1,1.4*Лист2!AZ$1,Лист2!AZ$1))) -> 920.76923 | W34: =IF($G34="Москва",1.3*(IF(IF(L34="Да",1,0)=1,1.4*Лист2!BA$1,Лист2!BA$1)),(IF(IF(L34="Да",1,0)=1,1.4*Лист2!BA$1,Лист2!BA$1))) -> 323.07692 | X34: =IF($G34="Москва",1.3*(IF(IF(M34="Да",1,0)=1,1.4*Лист2!BB$1,Лист2!BB$1)),(IF(IF(M34="Да",1,0)=1,1.4*Лист2!BB$1,Лист2!BB$1))) -> 35.384615 | Y34: =IF($G34="Москва",1.3*(IF(IF(N34="Да",1,0)=1,1.4*Лист2!BC$1,Лист2!BC$1)),(IF(IF(N34="Да",1,0)=1,1.4*Лист2!BC$1,Лист2!BC$1))) -> 936.92308 | Z34: =IF($G34="Москва",1.3*(IF(IF(O34="Да",1,0)=1,1.4*Лист2!BD$1,Лист2!BD$1)),(IF(IF(O34="Да",1,0)=1,1.4*Лист2!BD$1,Лист2!BD$1))) -> 339.23077 | AA34: =IF($G34="Москва",1.3*(IF(IF(P34="Да",1,0)=1,1.4*Лист2!BE$1,Лист2!BE$1)),(IF(IF(P34="Да",1,0)=1,1.4*Лист2!BE$1,Лист2!BE$1))) -> 557.69231 | ... AD34: =IF($G34="Москва",1.3*(IF(IF(S34="Да",1,0)=1,1.4*Лист2!BH$1,Лист2!BH$1)),(IF(IF(S34="Да",1,0)=1,1.4*Лист2!BH$1,Лист2!BH$1))) -> 168.26923 | AE34: =SUM(T34:AD34) -> 3801.0385 | AF34: =AE34*4.2 -> 15964.362 | AG34: =AF34*2 -> 31928.723 | AH34: =IF(IF(G34="Москва",1,0)=1,Лист2!$BK$6,Лист2!$BL$6) -> 9230 | AI34: =AH34-AF34 -> -6734.3615 | AJ34: =(H34-AE34)*4.2 -> 5035.6385
A35: 1997094996 | B35: Жен | C35: 20 | D35: active | E35: Да | F35: 60000 | G35: Волжский, Волгоградская область | H35: 5000 | I35: Нет | J35: Нет | K35: Да | L35: Да | M35: Нет | N35: Да | O35: Да | P35: Да | Q35: Да | R35: Нет | S35: Нет | T35: =IF($G35="Москва",1.3*(IF(IF(I35="Да",1,0)=1,1.4*Лист2!AX$1,Лист2!AX$1)),(IF(IF(I35="Да",1,0)=1,1.4*Лист2!AX$1,Лист2!AX$1))) -> 218.07692 | U35: =IF($G35="Москва",1.3*(IF(IF(J35="Да",1,0)=1,1.4*Лист2!AY$1,Лист2!AY$1)),(IF(IF(J35="Да",1,0)=1,1.4*Лист2!AY$1,Лист2!AY$1))) -> 192.30769 | V35: =IF($G35="Москва",1.3*(IF(IF(K35="Да",1,0)=1,1.4*Лист2!AZ$1,Лист2!AZ$1)),(IF(IF(K35="Да",1,0)=1,1.4*Лист2!AZ$1,Лист2!AZ$1))) -> 920.76923 | W35: =IF($G35="Москва",1.3*(IF(IF(L35="Да",1,0)=1,1.4*Лист2!BA$1,Лист2!BA$1)),(IF(IF(L35="Да",1,0)=1,1.4*Лист2!BA$1,Лист2!BA$1))) -> 323.07692 | X35: =IF($G35="Москва",1.3*(IF(IF(M35="Да",1,0)=1,1.4*Лист2!BB$1,Лист2!BB$1)),(IF(IF(M35="Да",1,0)=1,1.4*Лист2!BB$1,Лист2!BB$1))) -> 35.384615 | Y35: =IF($G35="Москва",1.3*(IF(IF(N35="Да",1,0)=1,1.4*Лист2!BC$1,Лист2!BC$1)),(IF(IF(N35="Да",1,0)=1,1.4*Лист2!BC$1,Лист2!BC$1))) -> 936.92308 | Z35: =IF($G35="Москва",1.3*(IF(IF(O35="Да",1,0)=1,1.4*Лист2!BD$1,Лист2!BD$1)),(IF(IF(O35="Да",1,0)=1,1.4*Лист2!BD$1,Лист2!BD$1))) -> 339.23077 | AA35: =IF($G35="Москва",1.3*(IF(IF(P35="Да",1,0)=1,1.4*Лист2!BE$1,Лист2!BE$1)),(IF(IF(P35="Да",1,0)=1,1.4*Лист2!BE$1,Лист2!BE$1))) -> 780.76923 | ... AD35: =IF($G35="Москва",1.3*(IF(IF(S35="Да",1,0)=1,1.4*Лист2!BH$1,Лист2!BH$1)),(IF(IF(S35="Да",1,0)=1,1.4*Лист2!BH$1,Лист2!BH$1))) -> 120.19231 | AE35: =SUM(T35:AD35) -> 3964.1923 | AF35: =AE35*4.2 -> 16649.608 | AG35: =AF35*2 -> 33299.215 | AH35: =IF(IF(G35="Москва",1,0)=1,Лист2!$BK$6,Лист2!$BL$6) -> 9230 | AI35: =AH35-AF35 -> -7419.6077 | AJ35: =(H35-AE35)*4.2 -> 4350.3923
A36: 1997394046 | B36: Жен | C36: 20 | D36: active | E36: Да | F36: 12000 | G36: Волжский, Волгоградская область | H36: 10000 | I36: Нет | J36: Нет | K36: Да | L36: Да | M36: Нет | N36: Да | O36: Да | P36: Да | Q36: Да | R36: Да | S36: Да | T36: =IF($G36="Москва",1.3*(IF(IF(I36="Да",1,0)=1,1.4*Лист2!AX$1,Лист2!AX$1)),(IF(IF(I36="Да",1,0)=1,1.4*Лист2!AX$1,Лист2!AX$1))) -> 218.07692 | U36: =IF($G36="Москва",1.3*(IF(IF(J36="Да",1,0)=1,1.4*Лист2!AY$1,Лист2!AY$1)),(IF(IF(J36="Да",1,0)=1,1.4*Лист2!AY$1,Лист2!AY$1))) -> 192.30769 | V36: =IF($G36="Москва",1.3*(IF(IF(K36="Да",1,0)=1,1.4*Лист2!AZ$1,Лист2!AZ$1)),(IF(IF(K36="Да",1,0)=1,1.4*Лист2!AZ$1,Лист2!AZ$1))) -> 920.76923 | W36: =IF($G36="Москва",1.3*(IF(IF(L36="Да",1,0)=1,1.4*Лист2!BA$1,Лист2!BA$1)),(IF(IF(L36="Да",1,0)=1,1.4*Лист2!BA$1,Лист2!BA$1))) -> 323.07692 | X36: =IF($G36="Москва",1.3*(IF(IF(M36="Да",1,0)=1,1.4*Лист2!BB$1,Лист2!BB$1)),(IF(IF(M36="Да",1,0)=1,1.4*Лист2!BB$1,Лист2!BB$1))) -> 35.384615 | Y36: =IF($G36="Москва",1.3*(IF(IF(N36="Да",1,0)=1,1.4*Лист2!BC$1,Лист2!BC$1)),(IF(IF(N36="Да",1,0)=1,1.4*Лист2!BC$1,Лист2!BC$1))) -> 936.92308 | Z36: =IF($G36="Москва",1.3*(IF(IF(O36="Да",1,0)=1,1.4*Лист2!BD$1,Лист2!BD$1)),(IF(IF(O36="Да",1,0)=1,1.4*Лист2!BD$1,Лист2!BD$1))) -> 339.23077 | AA36: =IF($G36="Москва",1.3*(IF(IF(P36="Да",1,0)=1,1.4*Лист2!BE$1,Лист2!BE$1)),(IF(IF(P36="Да",1,0)=1,1.4*Лист2!BE$1,Лист2!BE$1))) -> 780.76923 | ... AD36: =IF($G36="Москва",1.3*(IF(IF(S36="Да",1,0)=1,1.4*Лист2!BH$1,Лист2!BH$1)),(IF(IF(S36="Да",1,0)=1,1.4*Лист2!BH$1,Лист2!BH$1))) -> 168.26923 | AE36: =SUM(T36:AD36) -> 4024.1154 | AF36: =AE36*4.2 -> 16901.285 | AG36: =AF36*2 -> 33802.569 | AH36: =IF(IF(G36="Москва",1,0)=1,Лист2!$BK$6,Лист2!$BL$6) -> 9230 | AI36: =AH36-AF36 -> -7671.2846 | AJ36: =(H36-AE36)*4.2 -> 25098.715
A37: 1997430362 | B37: Муж | C37: 18 | D37: active | E37: Нет | F37: 12000 | G37: Волжский, Волгоградская область | H37: 4000 | I37: Да | J37: Нет | K37: Нет | L37: Нет | M37: Нет | N37: Да | O37: Нет | P37: Нет | Q37: Да | R37: Да | S37: Да | T37: =IF($G37="Москва",1.3*(IF(IF(I37="Да",1,0)=1,1.4*Лист2!AX$1,Лист2!AX$1)),(IF(IF(I37="Да",1,0)=1,1.4*Лист2!AX$1,Лист2!AX$1))) -> 305.30769 | U37: =IF($G37="Москва",1.3*(IF(IF(J37="Да",1,0)=1,1.4*Лист2!AY$1,Лист2!AY$1)),(IF(IF(J37="Да",1,0)=1,1.4*Лист2!AY$1,Лист2!AY$1))) -> 192.30769 | V37: =IF($G37="Москва",1.3*(IF(IF(K37="Да",1,0)=1,1.4*Лист2!AZ$1,Лист2!AZ$1)),(IF(IF(K37="Да",1,0)=1,1.4*Лист2!AZ$1,Лист2!AZ$1))) -> 657.69231 | W37: =IF($G37="Москва",1.3*(IF(IF(L37="Да",1,0)=1,1.4*Лист2!BA$1,Лист2!BA$1)),(IF(IF(L37="Да",1,0)=1,1.4*Лист2!BA$1,Лист2!BA$1))) -> 230.76923 | X37: =IF($G37="Москва",1.3*(IF(IF(M37="Да",1,0)=1,1.4*Лист2!BB$1,Лист2!BB$1)),(IF(IF(M37="Да",1,0)=1,1.4*Лист2!BB$1,Лист2!BB$1))) -> 35.384615 | Y37: =IF($G37="Москва",1.3*(IF(IF(N37="Да",1,0)=1,1.4*Лист2!BC$1,Лист2!BC$1)),(IF(IF(N37="Да",1,0)=1,1.4*Лист2!BC$1,Лист2!BC$1))) -> 936.92308 | Z37: =IF($G37="Москва",1.3*(IF(IF(O37="Да",1,0)=1,1.4*Лист2!BD$1,Лист2!BD$1)),(IF(IF(O37="Да",1,0)=1,1.4*Лист2!BD$1,Лист2!BD$1))) -> 242.30769 | AA37: =IF($G37="Москва",1.3*(IF(IF(P37="Да",1,0)=1,1.4*Лист2!BE$1,Лист2!BE$1)),(IF(IF(P37="Да",1,0)=1,1.4*Лист2!BE$1,Лист2!BE$1))) -> 557.69231 | ... AD37: =IF($G37="Москва",1.3*(IF(IF(S37="Да",1,0)=1,1.4*Лист2!BH$1,Лист2!BH$1)),(IF(IF(S37="Да",1,0)=1,1.4*Лист2!BH$1,Лист2!BH$1))) -> 168.26923 | AE37: =SUM(T37:AD37) -> 3435.9615 | AF37: =AE37*4.2 -> 14431.038 | AG37: =AF37*2 -> 28862.077 | AH37: =IF(IF(G37="Москва",1,0)=1,Лист2!$BK$6,Лист2!$BL$6) -> 9230 | AI37: =AH37-AF37 -> -5201.0385 | AJ37: =(H37-AE37)*4.2 -> 2368.9615
... A39: 1999577997 | B39: Жен | C39: 50 | D39: active | E39: Да | F39: 60000 | G39: Волжский, Волгоградская область | H39: 5000 | I39: Нет | J39: Да | K39: Да | L39: Нет | M39: Нет | N39: Да | O39: Нет | P39: Нет | Q39: Да | R39: Да | S39: Да | T39: =IF($G39="Москва",1.3*(IF(IF(I39="Да",1,0)=1,1.4*Лист2!AX$1,Лист2!AX$1)),(IF(IF(I39="Да",1,0)=1,1.4*Лист2!AX$1,Лист2!AX$1))) -> 218.07692 | U39: =IF($G39="Москва",1.3*(IF(IF(J39="Да",1,0)=1,1.4*Лист2!AY$1,Лист2!AY$1)),(IF(IF(J39="Да",1,0)=1,1.4*Лист2!AY$1,Лист2!AY$1))) -> 269.23077 | V39: =IF($G39="Москва",1.3*(IF(IF(K39="Да",1,0)=1,1.4*Лист2!AZ$1,Лист2!AZ$1)),(IF(IF(K39="Да",1,0)=1,1.4*Лист2!AZ$1,Лист2!AZ$1))) -> 920.76923 | W39: =IF($G39="Москва",1.3*(IF(IF(L39="Да",1,0)=1,1.4*Лист2!BA$1,Лист2!BA$1)),(IF(IF(L39="Да",1,0)=1,1.4*Лист2!BA$1,Лист2!BA$1))) -> 230.76923 | X39: =IF($G39="Москва",1.3*(IF(IF(M39="Да",1,0)=1,1.4*Лист2!BB$1,Лист2!BB$1)),(IF(IF(M39="Да",1,0)=1,1.4*Лист2!BB$1,Лист2!BB$1))) -> 35.384615 | Y39: =IF($G39="Москва",1.3*(IF(IF(N39="Да",1,0)=1,1.4*Лист2!BC$1,Лист2!BC$1)),(IF(IF(N39="Да",1,0)=1,1.4*Лист2!BC$1,Лист2!BC$1))) -> 936.92308 | Z39: =IF($G39="Москва",1.3*(IF(IF(O39="Да",1,0)=1,1.4*Лист2!BD$1,Лист2!BD$1)),(IF(IF(O39="Да",1,0)=1,1.4*Лист2!BD$1,Лист2!BD$1))) -> 242.30769 | AA39: =IF($G39="Москва",1.3*(IF(IF(P39="Да",1,0)=1,1.4*Лист2!BE$1,Лист2!BE$1)),(IF(IF(P39="Да",1,0)=1,1.4*Лист2!BE$1,Лист2!BE$1))) -> 557.69231 | ... AD39: =IF($G39="Москва",1.3*(IF(IF(S39="Да",1,0)=1,1.4*Лист2!BH$1,Лист2!BH$1)),(IF(IF(S39="Да",1,0)=1,1.4*Лист2!BH$1,Лист2!BH$1))) -> 168.26923 | AE39: =SUM(T39:AD39) -> 3688.7308 | AF39: =AE39*4.2 -> 15492.669 | AG39: =AF39*2 -> 30985.338 | AH39: =IF(IF(G39="Москва",1,0)=1,Лист2!$BK$6,Лист2!$BL$6) -> 9230 | AI39: =AH39-AF39 -> -6262.6692 | AJ39: =(H39-AE39)*4.2 -> 5507.3308
A40: 2009568744 | B40: Жен | C40: 20 | D40: active | E40: Нет | F40: 12000 | G40: Новосибирск, Новосибирская область | H40: 20000 | I40: Да | J40: Нет | K40: Да | L40: Да | M40: Нет | N40: Да | O40: Нет | P40: Да | Q40: Нет | R40: Нет | S40: Да | T40: =IF($G40="Москва",1.3*(IF(IF(I40="Да",1,0)=1,1.4*Лист2!AX$1,Лист2!AX$1)),(IF(IF(I40="Да",1,0)=1,1.4*Лист2!AX$1,Лист2!AX$1))) -> 305.30769 | U40: =IF($G40="Москва",1.3*(IF(IF(J40="Да",1,0)=1,1.4*Лист2!AY$1,Лист2!AY$1)),(IF(IF(J40="Да",1,0)=1,1.4*Лист2!AY$1,Лист2!AY$1))) -> 192.30769 | V40: =IF($G40="Москва",1.3*(IF(IF(K40="Да",1,0)=1,1.4*Лист2!AZ$1,Лист2!AZ$1)),(IF(IF(K40="Да",1,0)=1,1.4*Лист2!AZ$1,Лист2!AZ$1))) -> 920.76923 | W40: =IF($G40="Москва",1.3*(IF(IF(L40="Да",1,0)=1,1.4*Лист2!BA$1,Лист2!BA$1)),(IF(IF(L40="Да",1,0)=1,1.4*Лист2!BA$1,Лист2!BA$1))) -> 323.07692 | X40: =IF($G40="Москва",1.3*(IF(IF(M40="Да",1,0)=1,1.4*Лист2!BB$1,Лист2!BB$1)),(IF(IF(M40="Да",1,0)=1,1.4*Лист2!BB$1,Лист2!BB$1))) -> 35.384615 | Y40: =IF($G40="Москва",1.3*(IF(IF(N40="Да",1,0)=1,1.4*Лист2!BC$1,Лист2!BC$1)),(IF(IF(N40="Да",1,0)=1,1.4*Лист2!BC$1,Лист2!BC$1))) -> 936.92308 | Z40: =IF($G40="Москва",1.3*(IF(IF(O40="Да",1,0)=1,1.4*Лист2!BD$1,Лист2!BD$1)),(IF(IF(O40="Да",1,0)=1,1.4*Лист2!BD$1,Лист2!BD$1))) -> 242.30769 | AA40: =IF($G40="Москва",1.3*(IF(IF(P40="Да",1,0)=1,1.4*Лист2!BE$1,Лист2!BE$1)),(IF(IF(P40="Да",1,0)=1,1.4*Лист2!BE$1,Лист2!BE$1))) -> 780.76923 | ... AD40: =IF($G40="Москва",1.3*(IF(IF(S40="Да",1,0)=1,1.4*Лист2!BH$1,Лист2!BH$1)),(IF(IF(S40="Да",1,0)=1,1.4*Лист2!BH$1,Лист2!BH$1))) -> 168.26923 | AE40: =SUM(T40:AD40) -> 3983.1923 | AF40: =AE40*4.2 -> 16729.408 | AG40: =AF40*2 -> 33458.815 | AH40: =IF(IF(G40="Москва",1,0)=1,Лист2!$BK$6,Лист2!$BL$6) -> 9230 | AI40: =AH40-AF40 -> -7499.4077 | AJ40: =(H40-AE40)*4.2 -> 67270.592

Sheet Лист3

Sheet Лист2
S1: Мин. потребление в нед | T1: 2.4230769 | U1: 1.9230769 | V1: 2.1923077 | W1: 1.1538462 | X1: 0.44230769 | Y1: 1.1153846 | Z1: 0.34615385 | AA1: 5.5769231 | AB1: 4.0384615 | AC1: 0.21153846 | AD1: 0.096153846 | AJ1: Цена за ед. (₽) | AK1: 90 | AL1: 100 | AM1: 300 | AN1: 200 | AO1: 80 | AP1: 600 | AQ1: 700 | AR1: 100 | AS1: 12 | AT1: 140 | AU1: 1250 | AW1: Цена за ед. (₽) норма | AX1: 218.07692 | AY1: 192.30769 | AZ1: 657.69231 | BA1: 230.76923 | BB1: 35.384615 | BC1: 669.23077 | BD1: 242.30769 | BE1: 557.69231 | BF1: 48.461538 | BG1: 29.615385 | BH1: 120.19231 | BI1: оф. продуктовая Корзина Данные москва | BJ1: оф. Данные по регионам продуктовая Корзина | BK1: 13651 | BL1: 9230
A2: ID | B2: Ваш пол | C2: Ваш возраст | D2: Я веду образ жизни | E2: Вы трудоустроены? | F2: Ваш доход в месяц в рублях? | G2: В каком городе Вы проживаете? | H2: Как Вы считаете, сколько денег Вам нужно в неделю на продукты? | I2: Оцените по шкале необходимость продуктов в Вашем рационе на неделю / Хлебобулочные изделия и крупы | J2: Оцените по шкале необходимость продуктов в Вашем рационе на неделю / Картофель | K2: Оцените по шкале необходимость продуктов в Вашем рационе на неделю / Овощи | L2: Оцените по шкале необходимость продуктов в Вашем рационе на неделю / Фрукты | M2: Оцените по шкале необходимость продуктов в Вашем рационе на неделю / Сахар | N2: Оцените по шкале необходимость продуктов в Вашем рационе на неделю / Мясо | O2: Оцените по шкале необходимость продуктов в Вашем рационе на неделю / Рыба | P2: Оцените по шкале необходимость продуктов в Вашем рационе на неделю / Молочные продукты | Q2: Оцените по шкале необходимость продуктов в Вашем рационе на неделю / Яйца | R2: Оцените по шкале необходимость продуктов в Вашем рационе на неделю / Масло и жиры | S2: Оцените по шкале необходимость продуктов в Вашем рационе на неделю / Чай и специи | T2: Я потребляю в НЕДЕЛЮ больше 1.5 кг хлебобулочных изделий и круп | U2: Я потребляю в НЕДЕЛЮ больше 1.2 кг картофеля | V2: Я потребляю в НЕДЕЛЮ больше 1.3 кг овощей | W2: Я потребляю в НЕДЕЛЮ больше 700 г фруктов | X2: Я потребляю в НЕДЕЛЮ больше 300 г сахара | Y2: Я потребляю в НЕДЕЛЮ больше 700 г мяса (птица тоже считается) | Z2: Я потребляю в НЕДЕЛЮ больше 200 г рыбы | AA2: Я потребляю в НЕДЕЛЮ больше 3.5 кг молочных продуктов (кисломолочка тоже считается) | AB2: Я потребляю в НЕДЕЛЮ больше 3 яиц | AC2: Я потребляю в НЕДЕЛЮ больше 150 г масла и жиров (если потребляете продукты во фритюре, то примерно 20% веса в них - жиры) | AD2: Я потребляю в НЕДЕЛЮ больше 60 г чая и специй | AE2: москва ли (если москва, то =1, если не москва, то =0) | AF2: больше нормы или нет (больше = 1, если вписывается в норму, то =0) | AQ2: сумма траты на продукт в неделю | AR2: Хлебобулочные изделия и крупы | AS2: Картофель | AT2: Овощи | AU2: Фрукты | AV2: Сахар | AW2: Мясо | AX2: Рыба | AY2: Молочные продукты | AZ2: Яйца | BA2: Масло и жиры | BB2: Чай и специи | BC2: сумма в неделю | BD2: сумма в месяц на продукты | BE2: сумма потребительской корзины | BF2: оф данные | BG2: official_difference | BH2: mind_difference
A3: 1995902821 | B3: Жен | C3: 20 | D3: Активный (выхожу из дома не менее 6 дней в неделю) | E3: Да, официально | F3: 60000 | G3: Москва | H3: 7500 | I3: 4 | J3: 6 | K3: 8 | L3: 4 | M3: 4 | N3: 10 | O3: 5 | P3: 7 | Q3: 5 | R3: 5 | S3: 1 | T3: Да | U3: Нет | V3: Да | W3: Нет | X3: Да | Y3: Да | Z3: Нет | AA3: Нет | AB3: Нет | AC3: Да | AD3: Нет | AE3: =IF(G25 = "Москва",1,0) -> 1 | AF3: =IF(T3="Да",1,0) -> 1 | AG3: =IF(U3="Да",1,0) -> 0 | AH3: =IF(V3="Да",1,0) -> 1 | AI3: =IF(W3="Да",1,0) -> 0 | AJ3: =IF(X3="Да",1,0) -> 1 | AK3: =IF(Y3="Да",1,0) -> 1 | AL3: =IF(Z3="Да",1,0) -> 0 | AM3: =IF(AA3="Да",1,0) -> 0 | ... AP3: =IF(AD3="Да",1,0) -> 0 | AR3: =IF($AE3=1,1.3*(IF(AF3=1,1.4*AX$1,AX$1)),(IF(AF3=1,1.4*AX$1,AX$1))) -> 396.9 | AS3: =IF($AE3=1,1.3*(IF(AG3=1,1.4*AY$1,AY$1)),(IF(AG3=1,1.4*AY$1,AY$1))) -> 250 | AT3: =IF($AE3=1,1.3*(IF(AH3=1,1.4*AZ$1,AZ$1)),(IF(AH3=1,1.4*AZ$1,AZ$1))) -> 1197 | AU3: =IF($AE3=1,1.3*(IF(AI3=1,1.4*BA$1,BA$1)),(IF(AI3=1,1.4*BA$1,BA$1))) -> 300 | AV3: =IF($AE3=1,1.3*(IF(AJ3=1,1.4*BB$1,BB$1)),(IF(AJ3=1,1.4*BB$1,BB$1))) -> 64.4 | AW3: =IF($AE3=1,1.3*(IF(AK3=1,1.4*BC$1,BC$1)),(IF(AK3=1,1.4*BC$1,BC$1))) -> 1218 | AX3: =IF($AE3=1,1.3*(IF(AL3=1,1.4*BD$1,BD$1)),(IF(AL3=1,1.4*BD$1,BD$1))) -> 315 | AY3: =IF($AE3=1,1.3*(IF(AM3=1,1.4*BE$1,BE$1)),(IF(AM3=1,1.4*BE$1,BE$1))) -> 725 | ... BB3: =IF($AE3=1,1.3*(IF(AP3=1,1.4*BH$1,BH$1)),(IF(AP3=1,1.4*BH$1,BH$1))) -> 156.25 | BC3: =SUM(AR3:BB3) -> 4739.45 | BD3: =BC3*4.2 -> 19905.69 | BE3: =BD3*2 -> 39811.38 | BF3: =IF(AE3=1,$BK$1,$BL$1) -> 13651 | BG3: =BF3-BD3 -> -6254.69 | BH3: =(H3-BC3)*4.2 -> 11594.31 | BJ3: Мин. потребление в нед | BK3: 2.4230769 | BL3: 1.9230769 | BM3: 2.1923077 | BN3: 1.1538462 | BO3: 0.44230769 | BP3: 1.1153846 | BQ3: 0.34615385 | BR3: 5.5769231 | BS3: 4.0384615 | BT3: 0.21153846 | BU3: 0.096153846 | BV3: Цена за ед. (₽) | BW3: 90 | BX3: 100 | BY3: 300 | BZ3: 200 | CA3: 80 | CB3: 600 | CC3: 700 | CD3: 100 | CE3: 12 | CF3: 140 | CG3: 1250 | CH3: Цена за ед. (₽) норма | CI3: =BK3*BW3 -> 218.07692 | CJ3: =BL3*BX3 -> 192.30769 | CK3: =BM3*BY3 -> 657.69231 | CL3: =BN3*BZ3 -> 230.76923 | CM3: =BO3*CA3 -> 35.384615 | CN3: =BP3*CB3 -> 669.23077 | CO3: =BQ3*CC3 -> 242.30769 | CP3: =BR3*CD3 -> 557.69231 | ... CS3: =BU3*CG3 -> 120.19231
A4: 1996067555 | B4: Муж | C4: 35 | D4: Довольно активный (выхожу из дома не менее 4 дней в неделю) | E4: Да, официально | F4: 30000 | G4: Москва | H4: 8000 | I4: 10 | J4: 7 | K4: 7 | L4: 6 | M4: 2 | N4: 10 | O4: 3 | P4: 6 | Q4: 10 | R4: 4 | S4: 6 | T4: Да | U4: Нет | V4: Нет | W4: Нет | X4: Нет | Y4: Да | Z4: Нет | AA4: Да | AB4: Да | AC4: Нет | AD4: Нет | AE4: 1 | AF4: =IF(T4="Да",1,0) -> 1 | AG4: =IF(U3="Да",1,0) -> 0 | AH4: =IF(V3="Да",1,0) -> 1 | AI4: =IF(W3="Да",1,0) -> 0 | AJ4: =IF(X3="Да",1,0) -> 1 | AK4: =IF(Y3="Да",1,0) -> 1 | AL4: =IF(Z3="Да",1,0) -> 0 | AM4: =IF(AA3="Да",1,0) -> 0 | AN4: =IF(AB3="Да",1,0) -> 0 | ... AP4: =IF(AD3="Да",1,0) -> 0 | AR4: =IF($AE4=1,1.3*(IF(AF4=1,1.4*AX$1,AX$1)),(IF(AF4=1,1.4*AX$1,AX$1))) -> 396.9 | AS4: =IF($AE4=1,1.3*(IF(AG4=1,1.4*AY$1,AY$1)),(IF(AG4=1,1.4*AY$1,AY$1))) -> 250 | AT4: =IF($AE4=1,1.3*(IF(AH4=1,1.4*AZ$1,AZ$1)),(IF(AH4=1,1.4*AZ$1,AZ$1))) -> 1197 | AU4: =IF($AE4=1,1.3*(IF(AI4=1,1.4*BA$1,BA$1)),(IF(AI4=1,1.4*BA$1,BA$1))) -> 300 | AV4: =IF($AE4=1,1.3*(IF(AJ4=1,1.4*BB$1,BB$1)),(IF(AJ4=1,1.4*BB$1,BB$1))) -> 64.4 | AW4: =IF($AE4=1,1.3*(IF(AK4=1,1.4*BC$1,BC$1)),(IF(AK4=1,1.4*BC$1,BC$1))) -> 1218 | AX4: =IF($AE4=1,1.3*(IF(AL4=1,1.4*BD$1,BD$1)),(IF(AL4=1,1.4*BD$1,BD$1))) -> 315 | AY4: =IF($AE4=1,1.3*(IF(AM4=1,1.4*BE$1,BE$1)),(IF(AM4=1,1.4*BE$1,BE$1))) -> 725 | ... BB4: =IF($AE4=1,1.3*(IF(AP4=1,1.4*BH$1,BH$1)),(IF(AP4=1,1.4*BH$1,BH$1))) -> 156.25 | BC4: =SUM(AR4:BB4) -> 4739.45 | BD4: =BC4*4.2 -> 19905.69 | BE4: =BD4*2 -> 39811.38 | BF4: =IF(AE4=1,$BK$1,$BL$1) -> 13651 | BG4: =BF4-BD4 -> -6254.69 | BH4: =(H4-BC4)*4.2 -> 13694.31
A5: 1996071674 | B5: Муж | C5: 20 | D5: Активный (выхожу из дома не менее 6 дней в неделю) | E5: Нет | F5: 60000 | G5: Москва | H5: 8000 | I5: 10 | J5: 10 | K5: 10 | L5: 10 | M5: 10 | N5: 10 | O5: 5 | P5: 10 | Q5: 10 | R5: 5 | S5: 10 | T5: Да | U5: Нет | V5: Да | W5: Нет | X5: Да | Y5: Да | Z5: Нет | AA5: Да | AB5: Да | AC5: Нет | AD5: Да | AE5: =IF(G27 = "Москва",1,0) -> 1 | AF5: =IF(T5="Да",1,0) -> 1 | AG5: =IF(U4="Да",1,0) -> 0 | AH5: =IF(V4="Да",1,0) -> 0 | AI5: =IF(W4="Да",1,0) -> 0 | AJ5: =IF(X4="Да",1,0) -> 0 | AK5: =IF(Y4="Да",1,0) -> 1 | AL5: =IF(Z4="Да",1,0) -> 0 | AM5: =IF(AA4="Да",1,0) -> 1 | AN5: =IF(AB4="Да",1,0) -> 1 | ... AP5: =IF(AD4="Да",1,0) -> 0 | AR5: =IF($AE5=1,1.3*(IF(AF5=1,1.4*AX$1,AX$1)),(IF(AF5=1,1.4*AX$1,AX$1))) -> 396.9 | AS5: =IF($AE5=1,1.3*(IF(AG5=1,1.4*AY$1,AY$1)),(IF(AG5=1,1.4*AY$1,AY$1))) -> 250 | AT5: =IF($AE5=1,1.3*(IF(AH5=1,1.4*AZ$1,AZ$1)),(IF(AH5=1,1.4*AZ$1,AZ$1))) -> 855 | AU5: =IF($AE5=1,1.3*(IF(AI5=1,1.4*BA$1,BA$1)),(IF(AI5=1,1.4*BA$1,BA$1))) -> 300 | AV5: =IF($AE5=1,1.3*(IF(AJ5=1,1.4*BB$1,BB$1)),(IF(AJ5=1,1.4*BB$1,BB$1))) -> 46 | AW5: =IF($AE5=1,1.3*(IF(AK5=1,1.4*BC$1,BC$1)),(IF(AK5=1,1.4*BC$1,BC$1))) -> 1218 | AX5: =IF($AE5=1,1.3*(IF(AL5=1,1.4*BD$1,BD$1)),(IF(AL5=1,1.4*BD$1,BD$1))) -> 315 | AY5: =IF($AE5=1,1.3*(IF(AM5=1,1.4*BE$1,BE$1)),(IF(AM5=1,1.4*BE$1,BE$1))) -> 1015 | ... BB5: =IF($AE5=1,1.3*(IF(AP5=1,1.4*BH$1,BH$1)),(IF(AP5=1,1.4*BH$1,BH$1))) -> 156.25 | BC5: =SUM(AR5:BB5) -> 4678.85 | BD5: =BC5*4.2 -> 19651.17 | BE5: =BD5*2 -> 39302.34 | BF5: =IF(AE5=1,$BK$1,$BL$1) -> 13651 | BG5: =BF5-BD5 -> -6000.17 | BH5: =(H5-BC5)*4.2 -> 13948.83 | BK5: оф. продуктовая Корзина Данные москва | BL5: оф. Данные по регионам продуктовая Корзина
A6: 1996073501 | B6: Муж | C6: 20 | D6: Активный (выхожу из дома не менее 6 дней в неделю) | E6: Да, официально | F6: 60000 | G6: Саратов, Саратовская область | H6: 4000 | I6: 7 | J6: 2 | K6: 7 | L6: 10 | M6: 6 | N6: 10 | O6: 8 | P6: 7 | Q6: 10 | R6: 1 | S6: 3 | T6: Да | U6: Нет | V6: Да | W6: Да | X6: Нет | Y6: Да | Z6: Да | AA6: Нет | AB6: Да | AC6: Нет | AD6: Нет | AE6: =IF(G28 = "Москва",1,0) -> 1 | AF6: =IF(T6="Да",1,0) -> 1 | AG6: =IF(U5="Да",1,0) -> 0 | AH6: =IF(V5="Да",1,0) -> 1 | AI6: =IF(W5="Да",1,0) -> 0 | AJ6: =IF(X5="Да",1,0) -> 1 | AK6: =IF(Y5="Да",1,0) -> 1 | AL6: =IF(Z5="Да",1,0) -> 0 | AM6: =IF(AA5="Да",1,0) -> 1 | AN6: =IF(AB5="Да",1,0) -> 1 | ... AP6: =IF(AD5="Да",1,0) -> 1 | AR6: =IF($AE6=1,1.3*(IF(AF6=1,1.4*AX$1,AX$1)),(IF(AF6=1,1.4*AX$1,AX$1))) -> 396.9 | AS6: =IF($AE6=1,1.3*(IF(AG6=1,1.4*AY$1,AY$1)),(IF(AG6=1,1.4*AY$1,AY$1))) -> 250 | AT6: =IF($AE6=1,1.3*(IF(AH6=1,1.4*AZ$1,AZ$1)),(IF(AH6=1,1.4*AZ$1,AZ$1))) -> 1197 | AU6: =IF($AE6=1,1.3*(IF(AI6=1,1.4*BA$1,BA$1)),(IF(AI6=1,1.4*BA$1,BA$1))) -> 300 | AV6: =IF($AE6=1,1.3*(IF(AJ6=1,1.4*BB$1,BB$1)),(IF(AJ6=1,1.4*BB$1,BB$1))) -> 64.4 | AW6: =IF($AE6=1,1.3*(IF(AK6=1,1.4*BC$1,BC$1)),(IF(AK6=1,1.4*BC$1,BC$1))) -> 1218 | AX6: =IF($AE6=1,1.3*(IF(AL6=1,1.4*BD$1,BD$1)),(IF(AL6=1,1.4*BD$1,BD$1))) -> 315 | AY6: =IF($AE6=1,1.3*(IF(AM6=1,1.4*BE$1,BE$1)),(IF(AM6=1,1.4*BE$1,BE$1))) -> 1015 | ... BB6: =IF($AE6=1,1.3*(IF(AP6=1,1.4*BH$1,BH$1)),(IF(AP6=1,1.4*BH$1,BH$1))) -> 218.75 | BC6: =SUM(AR6:BB6) -> 5101.75 | BD6: =BC6*4.2 -> 21427.35 | BE6: =BD6*2 -> 42854.7 | BF6: =IF(AE6=1,$BK$1,$BL$1) -> 13651 | BG6: =BF6-BD6 -> -7776.35 | BH6: =(H6-BC6)*4.2 -> -4627.35 | BK6: 13651 | BL6: 9230
A7: 1996076712 | B7: Муж | C7: 20 | D7: Активный (выхожу из дома не менее 6 дней в неделю) | E7: Да, официально | F7: 60000 | G7: Москва | H7: 5000 | I7: 10 | J7: 10 | K7: 10 | L7: 10 | M7: 5 | N7: 10 | O7: 10 | P7: 10 | Q7: 10 | R7: 10 | S7: 8 | T7: Нет | U7: Да | V7: Да | W7: Да | X7: Нет | Y7: Да | Z7: Да | AA7: Да | AB7: Да | AC7: Нет | AD7: Нет | AE7: =IF(G29 = "Москва",1,0) -> 1 | AF7: =IF(T7="Да",1,0) -> 0 | AG7: =IF(U6="Да",1,0) -> 0 | AH7: =IF(V6="Да",1,0) -> 1 | AI7: =IF(W6="Да",1,0) -> 1 | AJ7: =IF(X6="Да",1,0) -> 0 | AK7: =IF(Y6="Да",1,0) -> 1 | AL7: =IF(Z6="Да",1,0) -> 1 | AM7: =IF(AA6="Да",1,0) -> 0 | AN7: =IF(AB6="Да",1,0) -> 1 | ... AP7: =IF(AD6="Да",1,0) -> 0 | AR7: =IF($AE7=1,1.3*(IF(AF7=1,1.4*AX$1,AX$1)),(IF(AF7=1,1.4*AX$1,AX$1))) -> 283.5 | AS7: =IF($AE7=1,1.3*(IF(AG7=1,1.4*AY$1,AY$1)),(IF(AG7=1,1.4*AY$1,AY$1))) -> 250 | AT7: =IF($AE7=1,1.3*(IF(AH7=1,1.4*AZ$1,AZ$1)),(IF(AH7=1,1.4*AZ$1,AZ$1))) -> 1197 | AU7: =IF($AE7=1,1.3*(IF(AI7=1,1.4*BA$1,BA$1)),(IF(AI7=1,1.4*BA$1,BA$1))) -> 420 | AV7: =IF($AE7=1,1.3*(IF(AJ7=1,1.4*BB$1,BB$1)),(IF(AJ7=1,1.4*BB$1,BB$1))) -> 46 | AW7: =IF($AE7=1,1.3*(IF(AK7=1,1.4*BC$1,BC$1)),(IF(AK7=1,1.4*BC$1,BC$1))) -> 1218 | AX7: =IF($AE7=1,1.3*(IF(AL7=1,1.4*BD$1,BD$1)),(IF(AL7=1,1.4*BD$1,BD$1))) -> 441 | AY7: =IF($AE7=1,1.3*(IF(AM7=1,1.4*BE$1,BE$1)),(IF(AM7=1,1.4*BE$1,BE$1))) -> 725 | ... BB7: =IF($AE7=1,1.3*(IF(AP7=1,1.4*BH$1,BH$1)),(IF(AP7=1,1.4*BH$1,BH$1))) -> 156.25 | BC7: =SUM(AR7:BB7) -> 4863.45 | BD7: =BC7*4.2 -> 20426.49 | BE7: =BD7*2 -> 40852.98 | BF7: =IF(AE7=1,$BK$1,$BL$1) -> 13651 | BG7: =BF7-BD7 -> -6775.49 | BH7: =(H7-BC7)*4.2 -> 573.51
A8: 1996077733 | B8: Муж | C8: 20 | D8: Довольно активный (выхожу из дома не менее 4 дней в неделю) | E8: Да, неофициально | F8: 21000 | G8: Ярославль, Ярославская область | H8: 5000 | I8: 5 | J8: 1 | K8: 8 | L8: 8 | M8: 5 | N8: 10 | O8: 6 | P8: 8 | Q8: 5 | R8: 3 | S8: 9 | T8: Нет | U8: Нет | V8: Да | W8: Да | X8: Да | Y8: Да | Z8: Да | AA8: Да | AB8: Да | AC8: Нет | AD8: Да | AE8: =IF(G30 = "Москва",1,0) -> 1 | AF8: =IF(T8="Да",1,0) -> 0 | AG8: =IF(U7="Да",1,0) -> 1 | AH8: =IF(V7="Да",1,0) -> 1 | AI8: =IF(W7="Да",1,0) -> 1 | AJ8: =IF(X7="Да",1,0) -> 0 | AK8: =IF(Y7="Да",1,0) -> 1 | AL8: =IF(Z7="Да",1,0) -> 1 | AM8: =IF(AA7="Да",1,0) -> 1 | AN8: =IF(AB7="Да",1,0) -> 1 | ... AP8: =IF(AD7="Да",1,0) -> 0 | AR8: =IF($AE8=1,1.3*(IF(AF8=1,1.4*AX$1,AX$1)),(IF(AF8=1,1.4*AX$1,AX$1))) -> 283.5 | AS8: =IF($AE8=1,1.3*(IF(AG8=1,1.4*AY$1,AY$1)),(IF(AG8=1,1.4*AY$1,AY$1))) -> 350 | AT8: =IF($AE8=1,1.3*(IF(AH8=1,1.4*AZ$1,AZ$1)),(IF(AH8=1,1.4*AZ$1,AZ$1))) -> 1197 | AU8: =IF($AE8=1,1.3*(IF(AI8=1,1.4*BA$1,BA$1)),(IF(AI8=1,1.4*BA$1,BA$1))) -> 420 | AV8: =IF($AE8=1,1.3*(IF(AJ8=1,1.4*BB$1,BB$1)),(IF(AJ8=1,1.4*BB$1,BB$1))) -> 46 | AW8: =IF($AE8=1,1.3*(IF(AK8=1,1.4*BC$1,BC$1)),(IF(AK8=1,1.4*BC$1,BC$1))) -> 1218 | AX8: =IF($AE8=1,1.3*(IF(AL8=1,1.4*BD$1,BD$1)),(IF(AL8=1,1.4*BD$1,BD$1))) -> 441 | AY8: =IF($AE8=1,1.3*(IF(AM8=1,1.4*BE$1,BE$1)),(IF(AM8=1,1.4*BE$1,BE$1))) -> 1015 | ... BB8: =IF($AE8=1,1.3*(IF(AP8=1,1.4*BH$1,BH$1)),(IF(AP8=1,1.4*BH$1,BH$1))) -> 156.25 | BC8: =SUM(AR8:BB8) -> 5253.45 | BD8: =BC8*4.2 -> 22064.49 | BE8: =BD8*2 -> 44128.98 | BF8: =IF(AE8=1,$BK$1,$BL$1) -> 13651 | BG8: =BF8-BD8 -> -8413.49 | BH8: =(H8-BC8)*4.2 -> -1064.49
A9: 1996080122 | B9: Жен | C9: 20 | D9: Активный (выхожу из дома не менее 6 дней в неделю) | E9: Нет | F9: 12000 | G9: Москва | H9: 3000 | I9: 7 | J9: 2 | K9: 10 | L9: 10 | M9: 2 | N9: 10 | O9: 7 | P9: 7 | Q9: 10 | R9: 5 | S9: 10 | T9: Нет | U9: Нет | V9: Да | W9: Да | X9: Нет | Y9: Да | Z9: Нет | AA9: Нет | AB9: Да | AC9: Нет | AD9: Да | AE9: =IF(G31 = "Москва",1,0) -> 0 | AF9: =IF(T9="Да",1,0) -> 0 | AG9: =IF(U8="Да",1,0) -> 0 | AH9: =IF(V8="Да",1,0) -> 1 | AI9: =IF(W8="Да",1,0) -> 1 | AJ9: =IF(X8="Да",1,0) -> 1 | AK9: =IF(Y8="Да",1,0) -> 1 | AL9: =IF(Z8="Да",1,0) -> 1 | AM9: =IF(AA8="Да",1,0) -> 1 | AN9: =IF(AB8="Да",1,0) -> 1 | ... AP9: =IF(AD8="Да",1,0) -> 1 | AR9: =IF($AE9=1,1.3*(IF(AF9=1,1.4*AX$1,AX$1)),(IF(AF9=1,1.4*AX$1,AX$1))) -> 218.07692 | AS9: =IF($AE9=1,1.3*(IF(AG9=1,1.4*AY$1,AY$1)),(IF(AG9=1,1.4*AY$1,AY$1))) -> 192.30769 | AT9: =IF($AE9=1,1.3*(IF(AH9=1,1.4*AZ$1,AZ$1)),(IF(AH9=1,1.4*AZ$1,AZ$1))) -> 920.76923 | AU9: =IF($AE9=1,1.3*(IF(AI9=1,1.4*BA$1,BA$1)),(IF(AI9=1,1.4*BA$1,BA$1))) -> 323.07692 | AV9: =IF($AE9=1,1.3*(IF(AJ9=1,1.4*BB$1,BB$1)),(IF(AJ9=1,1.4*BB$1,BB$1))) -> 49.538462 | AW9: =IF($AE9=1,1.3*(IF(AK9=1,1.4*BC$1,BC$1)),(IF(AK9=1,1.4*BC$1,BC$1))) -> 936.92308 | AX9: =IF($AE9=1,1.3*(IF(AL9=1,1.4*BD$1,BD$1)),(IF(AL9=1,1.4*BD$1,BD$1))) -> 339.23077 | AY9: =IF($AE9=1,1.3*(IF(AM9=1,1.4*BE$1,BE$1)),(IF(AM9=1,1.4*BE$1,BE$1))) -> 780.76923 | ... BB9: =IF($AE9=1,1.3*(IF(AP9=1,1.4*BH$1,BH$1)),(IF(AP9=1,1.4*BH$1,BH$1))) -> 168.26923 | BC9: =SUM(AR9:BB9) -> 4026.4231 | BD9: =BC9*4.2 -> 16910.977 | BE9: =BD9*2 -> 33821.954 | BF9: =IF(AE9=1,$BK$1,$BL$1) -> 9230 | BG9: =BF9-BD9 -> -7680.9769 | BH9: =(H9-BC9)*4.2 -> -4310.9769
A10: 1996092424 | B10: Муж | C10: 20 | D10: Активный (выхожу из дома не менее 6 дней в неделю) | E10: Да, неофициально | F10: 60000 | G10: Иркутск, Иркутская область | H10: 4000 | I10: 10 | J10: 7 | K10: 9 | L10: 8 | M10: 3 | N10: 10 | O10: 3 | P10: 6 | Q10: 6 | R10: 4 | S10: 9 | T10: Да | U10: Нет | V10: Да | W10: Да | X10: Нет | Y10: Да | Z10: Нет | AA10: Нет | AB10: Да | AC10: Нет | AD10: Да | AE10: =IF(G32 = "Москва",1,0) -> 1 | AF10: =IF(T10="Да",1,0) -> 1 | AG10: =IF(U9="Да",1,0) -> 0 | AH10: =IF(V9="Да",1,0) -> 1 | AI10: =IF(W9="Да",1,0) -> 1 | AJ10: =IF(X9="Да",1,0) -> 0 | AK10: =IF(Y9="Да",1,0) -> 1 | AL10: =IF(Z9="Да",1,0) -> 0 | AM10: =IF(AA9="Да",1,0) -> 0 | AN10: =IF(AB9="Да",1,0) -> 1 | ... AP10: =IF(AD9="Да",1,0) -> 1 | AR10: =IF($AE10=1,1.3*(IF(AF10=1,1.4*AX$1,AX$1)),(IF(AF10=1,1.4*AX$1,AX$1))) -> 396.9 | AS10: =IF($AE10=1,1.3*(IF(AG10=1,1.4*AY$1,AY$1)),(IF(AG10=1,1.4*AY$1,AY$1))) -> 250 | AT10: =IF($AE10=1,1.3*(IF(AH10=1,1.4*AZ$1,AZ$1)),(IF(AH10=1,1.4*AZ$1,AZ$1))) -> 1197 | AU10: =IF($AE10=1,1.3*(IF(AI10=1,1.4*BA$1,BA$1)),(IF(AI10=1,1.4*BA$1,BA$1))) -> 420 | AV10: =IF($AE10=1,1.3*(IF(AJ10=1,1.4*BB$1,BB$1)),(IF(AJ10=1,1.4*BB$1,BB$1))) -> 46 | AW10: =IF($AE10=1,1.3*(IF(AK10=1,1.4*BC$1,BC$1)),(IF(AK10=1,1.4*BC$1,BC$1))) -> 1218 | AX10: =IF($AE10=1,1.3*(IF(AL10=1,1.4*BD$1,BD$1)),(IF(AL10=1,1.4*BD$1,BD$1))) -> 315 | AY10: =IF($AE10=1,1.3*(IF(AM10=1,1.4*BE$1,BE$1)),(IF(AM10=1,1.4*BE$1,BE$1))) -> 725 | ... BB10: =IF($AE10=1,1.3*(IF(AP10=1,1.4*BH$1,BH$1)),(IF(AP10=1,1.4*BH$1,BH$1))) -> 218.75 | BC10: =SUM(AR10:BB10) -> 4913.35 | BD10: =BC10*4.2 -> 20636.07 | BE10: =BD10*2 -> 41272.14 | BF10: =IF(AE10=1,$BK$1,$BL$1) -> 13651 | BG10: =BF10-BD10 -> -6985.07 | BH10: =(H10-BC10)*4.2 -> -3836.07
A11: 1996104494 | B11: Муж | C11: 20 | D11: Довольно активный (выхожу из дома не менее 4 дней в неделю) | E11: Да, неофициально | F11: 60000 | G11: Москва | H11: 9000 | I11: 8 | J11: 7 | K11: 6 | L11: 6 | M11: 3 | N11: 10 | O11: 8 | P11: 7 | Q11: 10 | R11: 6 | S11: 6 | T11: Да | U11: Нет | V11: Нет | W11: Нет | X11: Да | Y11: Да | Z11: Нет | AA11: Нет | AB11: Да | AC11: Нет | AD11: Да | AE11: =IF(G33 = "Москва",1,0) -> 0 | AF11: =IF(T11="Да",1,0) -> 1 | AG11: =IF(U10="Да",1,0) -> 0 | AH11: =IF(V10="Да",1,0) -> 1 | AI11: =IF(W10="Да",1,0) -> 1 | AJ11: =IF(X10="Да",1,0) -> 0 | AK11: =IF(Y10="Да",1,0) -> 1 | AL11: =IF(Z10="Да",1,0) -> 0 | AM11: =IF(AA10="Да",1,0) -> 0 | AN11: =IF(AB10="Да",1,0) -> 1 | ... AP11: =IF(AD10="Да",1,0) -> 1 | AR11: =IF($AE11=1,1.3*(IF(AF11=1,1.4*AX$1,AX$1)),(IF(AF11=1,1.4*AX$1,AX$1))) -> 305.30769 | AS11: =IF($AE11=1,1.3*(IF(AG11=1,1.4*AY$1,AY$1)),(IF(AG11=1,1.4*AY$1,AY$1))) -> 192.30769 | AT11: =IF($AE11=1,1.3*(IF(AH11=1,1.4*AZ$1,AZ$1)),(IF(AH11=1,1.4*AZ$1,AZ$1))) -> 920.76923 | AU11: =IF($AE11=1,1.3*(IF(AI11=1,1.4*BA$1,BA$1)),(IF(AI11=1,1.4*BA$1,BA$1))) -> 323.07692 | AV11: =IF($AE11=1,1.3*(IF(AJ11=1,1.4*BB$1,BB$1)),(IF(AJ11=1,1.4*BB$1,BB$1))) -> 35.384615 | AW11: =IF($AE11=1,1.3*(IF(AK11=1,1.4*BC$1,BC$1)),(IF(AK11=1,1.4*BC$1,BC$1))) -> 936.92308 | AX11: =IF($AE11=1,1.3*(IF(AL11=1,1.4*BD$1,BD$1)),(IF(AL11=1,1.4*BD$1,BD$1))) -> 242.30769 | AY11: =IF($AE11=1,1.3*(IF(AM11=1,1.4*BE$1,BE$1)),(IF(AM11=1,1.4*BE$1,BE$1))) -> 557.69231 | ... BB11: =IF($AE11=1,1.3*(IF(AP11=1,1.4*BH$1,BH$1)),(IF(AP11=1,1.4*BH$1,BH$1))) -> 168.26923 | BC11: =SUM(AR11:BB11) -> 3779.5 | BD11: =BC11*4.2 -> 15873.9 | BE11: =BD11*2 -> 31747.8 | BF11: =IF(AE11=1,$BK$1,$BL$1) -> 9230 | BG11: =BF11-BD11 -> -6643.9 | BH11: =(H11-BC11)*4.2 -> 21926.1
A12: 1996106993 | B12: Жен | C12: 20 | D12: Скорее пассивный (выхожу из дома не менее 2 дней в неделю) | E12: Нет | F12: 12000 | G12: Екатеринбург, Свердловская область | H12: 20000 | I12: 5 | J12: 3 | K12: 3 | L12: 3 | M12: 2 | N12: 9 | O12: 9 | P12: 5 | Q12: 3 | R12: 5 | S12: 3 | T12: Нет | U12: Нет | V12: Нет | W12: Нет | X12: Да | Y12: Да | Z12: Нет | AA12: Нет | AB12: Нет | AC12: Да | AD12: Нет | AE12: =IF(G34 = "Москва",1,0) -> 0 | AF12: =IF(T12="Да",1,0) -> 0 | AG12: =IF(U11="Да",1,0) -> 0 | AH12: =IF(V11="Да",1,0) -> 0 | AI12: =IF(W11="Да",1,0) -> 0 | AJ12: =IF(X11="Да",1,0) -> 1 | AK12: =IF(Y11="Да",1,0) -> 1 | AL12: =IF(Z11="Да",1,0) -> 0 | AM12: =IF(AA11="Да",1,0) -> 0 | AN12: =IF(AB11="Да",1,0) -> 1 | ... AP12: =IF(AD11="Да",1,0) -> 1 | AR12: =IF($AE12=1,1.3*(IF(AF12=1,1.4*AX$1,AX$1)),(IF(AF12=1,1.4*AX$1,AX$1))) -> 218.07692 | AS12: =IF($AE12=1,1.3*(IF(AG12=1,1.4*AY$1,AY$1)),(IF(AG12=1,1.4*AY$1,AY$1))) -> 192.30769 | AT12: =IF($AE12=1,1.3*(IF(AH12=1,1.4*AZ$1,AZ$1)),(IF(AH12=1,1.4*AZ$1,AZ$1))) -> 657.69231 | AU12: =IF($AE12=1,1.3*(IF(AI12=1,1.4*BA$1,BA$1)),(IF(AI12=1,1.4*BA$1,BA$1))) -> 230.76923 | AV12: =IF($AE12=1,1.3*(IF(AJ12=1,1.4*BB$1,BB$1)),(IF(AJ12=1,1.4*BB$1,BB$1))) -> 49.538462 | AW12: =IF($AE12=1,1.3*(IF(AK12=1,1.4*BC$1,BC$1)),(IF(AK12=1,1.4*BC$1,BC$1))) -> 936.92308 | AX12: =IF($AE12=1,1.3*(IF(AL12=1,1.4*BD$1,BD$1)),(IF(AL12=1,1.4*BD$1,BD$1))) -> 242.30769 | AY12: =IF($AE12=1,1.3*(IF(AM12=1,1.4*BE$1,BE$1)),(IF(AM12=1,1.4*BE$1,BE$1))) -> 557.69231 | ... BB12: =IF($AE12=1,1.3*(IF(AP12=1,1.4*BH$1,BH$1)),(IF(AP12=1,1.4*BH$1,BH$1))) -> 168.26923 | BC12: =SUM(AR12:BB12) -> 3351.0385 | BD12: =BC12*4.2 -> 14074.362 | BE12: =BD12*2 -> 28148.723 | BF12: =IF(AE12=1,$BK$1,$BL$1) -> 9230 | BG12: =BF12-BD12 -> -4844.3615 | BH12: =(H12-BC12)*4.2 -> 69925.638
A13: 1996114680 | B13: Жен | C13: 20 | D13: Активный (выхожу из дома не менее 6 дней в неделю) | E13: Да, официально | F13: 21000 | G13: Волжский, Волгоградская область | H13: 5000 | I13: 7 | J13: 7 | K13: 5 | L13: 5 | M13: 1 | N13: 10 | O13: 7 | P13: 10 | Q13: 10 | R13: 1 | S13: 5 | T13: Нет | U13: Да | V13: Нет | W13: Нет | X13: Да | Y13: Да | Z13: Да | AA13: Нет | AB13: Да | AC13: Да | AD13: Да | AE13: =IF(G35 = "Москва",1,0) -> 0 | AF13: =IF(T13="Да",1,0) -> 0 | AG13: =IF(U12="Да",1,0) -> 0 | AH13: =IF(V12="Да",1,0) -> 0 | AI13: =IF(W12="Да",1,0) -> 0 | AJ13: =IF(X12="Да",1,0) -> 1 | AK13: =IF(Y12="Да",1,0) -> 1 | AL13: =IF(Z12="Да",1,0) -> 0 | AM13: =IF(AA12="Да",1,0) -> 0 | AN13: =IF(AB12="Да",1,0) -> 0 | ... AP13: =IF(AD12="Да",1,0) -> 0 | AR13: =IF($AE13=1,1.3*(IF(AF13=1,1.4*AX$1,AX$1)),(IF(AF13=1,1.4*AX$1,AX$1))) -> 218.07692 | AS13: =IF($AE13=1,1.3*(IF(AG13=1,1.4*AY$1,AY$1)),(IF(AG13=1,1.4*AY$1,AY$1))) -> 192.30769 | AT13: =IF($AE13=1,1.3*(IF(AH13=1,1.4*AZ$1,AZ$1)),(IF(AH13=1,1.4*AZ$1,AZ$1))) -> 657.69231 | AU13: =IF($AE13=1,1.3*(IF(AI13=1,1.4*BA$1,BA$1)),(IF(AI13=1,1.4*BA$1,BA$1))) -> 230.76923 | AV13: =IF($AE13=1,1.3*(IF(AJ13=1,1.4*BB$1,BB$1)),(IF(AJ13=1,1.4*BB$1,BB$1))) -> 49.538462 | AW13: =IF($AE13=1,1.3*(IF(AK13=1,1.4*BC$1,BC$1)),(IF(AK13=1,1.4*BC$1,BC$1))) -> 936.92308 | AX13: =IF($AE13=1,1.3*(IF(AL13=1,1.4*BD$1,BD$1)),(IF(AL13=1,1.4*BD$1,BD$1))) -> 242.30769 | AY13: =IF($AE13=1,1.3*(IF(AM13=1,1.4*BE$1,BE$1)),(IF(AM13=1,1.4*BE$1,BE$1))) -> 557.69231 | ... BB13: =IF($AE13=1,1.3*(IF(AP13=1,1.4*BH$1,BH$1)),(IF(AP13=1,1.4*BH$1,BH$1))) -> 120.19231 | BC13: =SUM(AR13:BB13) -> 3295.4231 | BD13: =BC13*4.2 -> 13840.777 | BE13: =BD13*2 -> 27681.554 | BF13: =IF(AE13=1,$BK$1,$BL$1) -> 9230 | BG13: =BF13-BD13 -> -4610.7769 | BH13: =(H13-BC13)*4.2 -> 7159.2231
A14: 1996121848 | B14: Муж | C14: 20 | D14: Довольно активный (выхожу из дома не менее 4 дней в неделю) | E14: Да, официально | F14: 60000 | G14: Москва | H14: 7000 | I14: 5 | J14: 6 | K14: 10 | L14: 8 | M14: 1 | N14: 9 | O14: 9 | P14: 1 | Q14: 9 | R14: 1 | S14: 1 | T14: Да | U14: Да | V14: Да | W14: Да | X14: Нет | Y14: Да | Z14: Нет | AA14: Нет | AB14: Да | AC14: Нет | AD14: Нет | AE14: =IF(G36 = "Москва",1,0) -> 0 | AF14: =IF(T14="Да",1,0) -> 1 | AG14: =IF(U13="Да",1,0) -> 1 | AH14: =IF(V13="Да",1,0) -> 0 | AI14: =IF(W13="Да",1,0) -> 0 | AJ14: =IF(X13="Да",1,0) -> 1 | AK14: =IF(Y13="Да",1,0) -> 1 | AL14: =IF(Z13="Да",1,0) -> 1 | AM14: =IF(AA13="Да",1,0) -> 0 | AN14: =IF(AB13="Да",1,0) -> 1 | ... AP14: =IF(AD13="Да",1,0) -> 1 | AR14: =IF($AE14=1,1.3*(IF(AF14=1,1.4*AX$1,AX$1)),(IF(AF14=1,1.4*AX$1,AX$1))) -> 305.30769 | AS14: =IF($AE14=1,1.3*(IF(AG14=1,1.4*AY$1,AY$1)),(IF(AG14=1,1.4*AY$1,AY$1))) -> 269.23077 | AT14: =IF($AE14=1,1.3*(IF(AH14=1,1.4*AZ$1,AZ$1)),(IF(AH14=1,1.4*AZ$1,AZ$1))) -> 657.69231 | AU14: =IF($AE14=1,1.3*(IF(AI14=1,1.4*BA$1,BA$1)),(IF(AI14=1,1.4*BA$1,BA$1))) -> 230.76923 | AV14: =IF($AE14=1,1.3*(IF(AJ14=1,1.4*BB$1,BB$1)),(IF(AJ14=1,1.4*BB$1,BB$1))) -> 49.538462 | AW14: =IF($AE14=1,1.3*(IF(AK14=1,1.4*BC$1,BC$1)),(IF(AK14=1,1.4*BC$1,BC$1))) -> 936.92308 | AX14: =IF($AE14=1,1.3*(IF(AL14=1,1.4*BD$1,BD$1)),(IF(AL14=1,1.4*BD$1,BD$1))) -> 339.23077 | AY14: =IF($AE14=1,1.3*(IF(AM14=1,1.4*BE$1,BE$1)),(IF(AM14=1,1.4*BE$1,BE$1))) -> 557.69231 | ... BB14: =IF($AE14=1,1.3*(IF(AP14=1,1.4*BH$1,BH$1)),(IF(AP14=1,1.4*BH$1,BH$1))) -> 168.26923 | BC14: =SUM(AR14:BB14) -> 3623.9615 | BD14: =BC14*4.2 -> 15220.638 | BE14: =BD14*2 -> 30441.277 | BF14: =IF(AE14=1,$BK$1,$BL$1) -> 9230 | BG14: =BF14-BD14 -> -5990.6385 | BH14: =(H14-BC14)*4.2 -> 14179.362
A15: 1996132591 | B15: Жен | C15: 20 | D15: Активный (выхожу из дома не менее 6 дней в неделю) | E15: Да, официально | F15: 60000 | G15: Москва | H15: 8000 | I15: 5 | J15: 5 | K15: 10 | L15: 10 | M15: 1 | N15: 10 | O15: 1 | P15: 5 | Q15: 5 | R15: 1 | S15: 1 | T15: Нет | U15: Нет | V15: Нет | W15: Да | X15: Да | Y15: Да | Z15: Нет | AA15: Нет | AB15: Нет | AC15: Нет | AD15: Да | AE15: =IF(G37 = "Москва",1,0) -> 0 | AF15: =IF(T15="Да",1,0) -> 0 | AG15: =IF(U14="Да",1,0) -> 1 | AH15: =IF(V14="Да",1,0) -> 1 | AI15: =IF(W14="Да",1,0) -> 1 | AJ15: =IF(X14="Да",1,0) -> 0 | AK15: =IF(Y14="Да",1,0) -> 1 | AL15: =IF(Z14="Да",1,0) -> 0 | AM15: =IF(AA14="Да",1,0) -> 0 | AN15: =IF(AB14="Да",1,0) -> 1 | ... AP15: =IF(AD14="Да",1,0) -> 0 | AR15: =IF($AE15=1,1.3*(IF(AF15=1,1.4*AX$1,AX$1)),(IF(AF15=1,1.4*AX$1,AX$1))) -> 218.07692 | AS15: =IF($AE15=1,1.3*(IF(AG15=1,1.4*AY$1,AY$1)),(IF(AG15=1,1.4*AY$1,AY$1))) -> 269.23077 | AT15: =IF($AE15=1,1.3*(IF(AH15=1,1.4*AZ$1,AZ$1)),(IF(AH15=1,1.4*AZ$1,AZ$1))) -> 920.76923 | AU15: =IF($AE15=1,1.3*(IF(AI15=1,1.4*BA$1,BA$1)),(IF(AI15=1,1.4*BA$1,BA$1))) -> 323.07692 | AV15: =IF($AE15=1,1.3*(IF(AJ15=1,1.4*BB$1,BB$1)),(IF(AJ15=1,1.4*BB$1,BB$1))) -> 35.384615 | AW15: =IF($AE15=1,1.3*(IF(AK15=1,1.4*BC$1,BC$1)),(IF(AK15=1,1.4*BC$1,BC$1))) -> 936.92308 | AX15: =IF($AE15=1,1.3*(IF(AL15=1,1.4*BD$1,BD$1)),(IF(AL15=1,1.4*BD$1,BD$1))) -> 242.30769 | AY15: =IF($AE15=1,1.3*(IF(AM15=1,1.4*BE$1,BE$1)),(IF(AM15=1,1.4*BE$1,BE$1))) -> 557.69231 | ... BB15: =IF($AE15=1,1.3*(IF(AP15=1,1.4*BH$1,BH$1)),(IF(AP15=1,1.4*BH$1,BH$1))) -> 120.19231 | BC15: =SUM(AR15:BB15) -> 3721.1154 | BD15: =BC15*4.2 -> 15628.685 | BE15: =BD15*2 -> 31257.369 | BF15: =IF(AE15=1,$BK$1,$BL$1) -> 9230 | BG15: =BF15-BD15 -> -6398.6846 | BH15: =(H15-BC15)*4.2 -> 17971.315
A16: 1996138979 | B16: Жен | C16: 20 | D16: Довольно активный (выхожу из дома не менее 4 дней в неделю) | E16: Да, официально | F16: 12000 | G16: Тула, Тульская область | H16: 2000 | I16: 7 | J16: 7 | K16: 9 | L16: 9 | M16: 5 | N16: 9 | O16: 8 | P16: 8 | Q16: 10 | R16: 7 | S16: 5 | T16: Нет | U16: Нет | V16: Нет | W16: Нет | X16: Да | Y16: Да | Z16: Нет | AA16: Да | AB16: Да | AC16: Да | AD16: Да | AE16: =IF(G38 = "Москва",1,0) -> 0 | AF16: =IF(T16="Да",1,0) -> 0 | AG16: =IF(U15="Да",1,0) -> 0 | AH16: =IF(V15="Да",1,0) -> 0 | AI16: =IF(W15="Да",1,0) -> 1 | AJ16: =IF(X15="Да",1,0) -> 1 | AK16: =IF(Y15="Да",1,0) -> 1 | AL16: =IF(Z15="Да",1,0) -> 0 | AM16: =IF(AA15="Да",1,0) -> 0 | AN16: =IF(AB15="Да",1,0) -> 0 | ... AP16: =IF(AD15="Да",1,0) -> 1 | AR16: =IF($AE16=1,1.3*(IF(AF16=1,1.4*AX$1,AX$1)),(IF(AF16=1,1.4*AX$1,AX$1))) -> 218.07692 | AS16: =IF($AE16=1,1.3*(IF(AG16=1,1.4*AY$1,AY$1)),(IF(AG16=1,1.4*AY$1,AY$1))) -> 192.30769 | AT16: =IF($AE16=1,1.3*(IF(AH16=1,1.4*AZ$1,AZ$1)),(IF(AH16=1,1.4*AZ$1,AZ$1))) -> 657.69231 | AU16: =IF($AE16=1,1.3*(IF(AI16=1,1.4*BA$1,BA$1)),(IF(AI16=1,1.4*BA$1,BA$1))) -> 323.07692 | AV16: =IF($AE16=1,1.3*(IF(AJ16=1,1.4*BB$1,BB$1)),(IF(AJ16=1,1.4*BB$1,BB$1))) -> 49.538462 | AW16: =IF($AE16=1,1.3*(IF(AK16=1,1.4*BC$1,BC$1)),(IF(AK16=1,1.4*BC$1,BC$1))) -> 936.92308 | AX16: =IF($AE16=1,1.3*(IF(AL16=1,1.4*BD$1,BD$1)),(IF(AL16=1,1.4*BD$1,BD$1))) -> 242.30769 | AY16: =IF($AE16=1,1.3*(IF(AM16=1,1.4*BE$1,BE$1)),(IF(AM16=1,1.4*BE$1,BE$1))) -> 557.69231 | ... BB16: =IF($AE16=1,1.3*(IF(AP16=1,1.4*BH$1,BH$1)),(IF(AP16=1,1.4*BH$1,BH$1))) -> 168.26923 | BC16: =SUM(AR16:BB16) -> 3423.9615 | BD16: =BC16*4.2 -> 14380.638 | BE16: =BD16*2 -> 28761.277 | BF16: =IF(AE16=1,$BK$1,$BL$1) -> 9230 | BG16: =BF16-BD16 -> -5150.6385 | BH16: =(H16-BC16)*4.2 -> -5980.6385
A17: 1996145371 | B17: Муж | C17: 20 | D17: Довольно активный (выхожу из дома не менее 4 дней в неделю) | E17: Да, официально | F17: 60000 | G17: Смоленск, Смоленская область | H17: 6000 | I17: 5 | J17: 10 | K17: 10 | L17: 10 | M17: 10 | N17: 7 | O17: 6 | P17: 6 | Q17: 5 | R17: 5 | S17: 8 | T17: Нет | U17: Да | V17: Нет | W17: Да | X17: Да | Y17: Нет | Z17: Нет | AA17: Нет | AB17: Нет | AC17: Нет | AD17: Нет | AE17: =IF(G39 = "Москва",1,0) -> 0 | AF17: =IF(T17="Да",1,0) -> 0 | AG17: =IF(U16="Да",1,0) -> 0 | AH17: =IF(V16="Да",1,0) -> 0 | AI17: =IF(W16="Да",1,0) -> 0 | AJ17: =IF(X16="Да",1,0) -> 1 | AK17: =IF(Y16="Да",1,0) -> 1 | AL17: =IF(Z16="Да",1,0) -> 0 | AM17: =IF(AA16="Да",1,0) -> 1 | AN17: =IF(AB16="Да",1,0) -> 1 | ... AP17: =IF(AD16="Да",1,0) -> 1 | AR17: =IF($AE17=1,1.3*(IF(AF17=1,1.4*AX$1,AX$1)),(IF(AF17=1,1.4*AX$1,AX$1))) -> 218.07692 | AS17: =IF($AE17=1,1.3*(IF(AG17=1,1.4*AY$1,AY$1)),(IF(AG17=1,1.4*AY$1,AY$1))) -> 192.30769 | AT17: =IF($AE17=1,1.3*(IF(AH17=1,1.4*AZ$1,AZ$1)),(IF(AH17=1,1.4*AZ$1,AZ$1))) -> 657.69231 | AU17: =IF($AE17=1,1.3*(IF(AI17=1,1.4*BA$1,BA$1)),(IF(AI17=1,1.4*BA$1,BA$1))) -> 230.76923 | AV17: =IF($AE17=1,1.3*(IF(AJ17=1,1.4*BB$1,BB$1)),(IF(AJ17=1,1.4*BB$1,BB$1))) -> 49.538462 | AW17: =IF($AE17=1,1.3*(IF(AK17=1,1.4*BC$1,BC$1)),(IF(AK17=1,1.4*BC$1,BC$1))) -> 936.92308 | AX17: =IF($AE17=1,1.3*(IF(AL17=1,1.4*BD$1,BD$1)),(IF(AL17=1,1.4*BD$1,BD$1))) -> 242.30769 | AY17: =IF($AE17=1,1.3*(IF(AM17=1,1.4*BE$1,BE$1)),(IF(AM17=1,1.4*BE$1,BE$1))) -> 780.76923 | ... BB17: =IF($AE17=1,1.3*(IF(AP17=1,1.4*BH$1,BH$1)),(IF(AP17=1,1.4*BH$1,BH$1))) -> 168.26923 | BC17: =SUM(AR17:BB17) -> 3585.9615 | BD17: =BC17*4.2 -> 15061.038 | BE17: =BD17*2 -> 30122.077 | BF17: =IF(AE17=1,$BK$1,$BL$1) -> 9230 | BG17: =BF17-BD17 -> -5831.0385 | BH17: =(H17-BC17)*4.2 -> 10138.962
A18: 1996145750 | B18: Жен | C18: 20 | D18: Активный (выхожу из дома не менее 6 дней в неделю) | E18: Нет | F18: 21000 | G18: Москва | H18: 5000 | I18: 8 | J18: 6 | K18: 7 | L18: 8 | M18: 2 | N18: 10 | O18: 3 | P18: 9 | Q18: 7 | R18: 6 | S18: 10 | T18: Да | U18: Нет | V18: Нет | W18: Да | X18: Нет | Y18: Да | Z18: Нет | AA18: Нет | AB18: Нет | AC18: Нет | AD18: Да | AE18: =IF(G40 = "Москва",1,0) -> 0 | AF18: =IF(T18="Да",1,0) -> 1 | AG18: =IF(U17="Да",1,0) -> 1 | AH18: =IF(V17="Да",1,0) -> 0 | AI18: =IF(W17="Да",1,0) -> 1 | AJ18: =IF(X17="Да",1,0) -> 1 | AK18: =IF(Y17="Да",1,0) -> 0 | AL18: =IF(Z17="Да",1,0) -> 0 | AM18: =IF(AA17="Да",1,0) -> 0 | AN18: =IF(AB17="Да",1,0) -> 0 | ... AP18: =IF(AD17="Да",1,0) -> 0 | AR18: =IF($AE18=1,1.3*(IF(AF18=1,1.4*AX$1,AX$1)),(IF(AF18=1,1.4*AX$1,AX$1))) -> 305.30769 | AS18: =IF($AE18=1,1.3*(IF(AG18=1,1.4*AY$1,AY$1)),(IF(AG18=1,1.4*AY$1,AY$1))) -> 269.23077 | AT18: =IF($AE18=1,1.3*(IF(AH18=1,1.4*AZ$1,AZ$1)),(IF(AH18=1,1.4*AZ$1,AZ$1))) -> 657.69231 | AU18: =IF($AE18=1,1.3*(IF(AI18=1,1.4*BA$1,BA$1)),(IF(AI18=1,1.4*BA$1,BA$1))) -> 323.07692 | AV18: =IF($AE18=1,1.3*(IF(AJ18=1,1.4*BB$1,BB$1)),(IF(AJ18=1,1.4*BB$1,BB$1))) -> 49.538462 | AW18: =IF($AE18=1,1.3*(IF(AK18=1,1.4*BC$1,BC$1)),(IF(AK18=1,1.4*BC$1,BC$1))) -> 669.23077 | AX18: =IF($AE18=1,1.3*(IF(AL18=1,1.4*BD$1,BD$1)),(IF(AL18=1,1.4*BD$1,BD$1))) -> 242.30769 | AY18: =IF($AE18=1,1.3*(IF(AM18=1,1.4*BE$1,BE$1)),(IF(AM18=1,1.4*BE$1,BE$1))) -> 557.69231 | ... BB18: =IF($AE18=1,1.3*(IF(AP18=1,1.4*BH$1,BH$1)),(IF(AP18=1,1.4*BH$1,BH$1))) -> 120.19231 | BC18: =SUM(AR18:BB18) -> 3272.3462 | BD18: =BC18*4.2 -> 13743.854 | BE18: =BD18*2 -> 27487.708 | BF18: =IF(AE18=1,$BK$1,$BL$1) -> 9230 | BG18: =BF18-BD18 -> -4513.8538 | BH18: =(H18-BC18)*4.2 -> 7256.1462
... A25: 1996305312 | B25: Жен | C25: 20 | D25: Активный (выхожу из дома не менее 6 дней в неделю) | E25: Нет | F25: 60000 | G25: Москва | H25: 4000 | I25: 10 | J25: 1 | K25: 8 | L25: 5 | M25: 1 | N25: 8 | O25: 1 | P25: 10 | Q25: 3 | R25: 7 | S25: 10 | T25: Да | U25: Нет | V25: Да | W25: Нет | X25: Нет | Y25: Да | Z25: Нет | AA25: Нет | AB25: Нет | AC25: Нет | AD25: Да | AE25: =IF(G47 = "Москва",1,0) -> 0 | AF25: =IF(T25="Да",1,0) -> 1 | AG25: =IF(U24="Да",1,0) -> 0 | AH25: =IF(V24="Да",1,0) -> 1 | AI25: =IF(W24="Да",1,0) -> 1 | AJ25: =IF(X24="Да",1,0) -> 0 | AK25: =IF(Y24="Да",1,0) -> 1 | AL25: =IF(Z24="Да",1,0) -> 0 | AM25: =IF(AA24="Да",1,0) -> 0 | AN25: =IF(AB24="Да",1,0) -> 1 | ... AP25: =IF(AD24="Да",1,0) -> 1 | AR25: =IF($AE25=1,1.3*(IF(AF25=1,1.4*AX$1,AX$1)),(IF(AF25=1,1.4*AX$1,AX$1))) -> 305.30769 | AS25: =IF($AE25=1,1.3*(IF(AG25=1,1.4*AY$1,AY$1)),(IF(AG25=1,1.4*AY$1,AY$1))) -> 192.30769 | AT25: =IF($AE25=1,1.3*(IF(AH25=1,1.4*AZ$1,AZ$1)),(IF(AH25=1,1.4*AZ$1,AZ$1))) -> 920.76923 | AU25: =IF($AE25=1,1.3*(IF(AI25=1,1.4*BA$1,BA$1)),(IF(AI25=1,1.4*BA$1,BA$1))) -> 323.07692 | AV25: =IF($AE25=1,1.3*(IF(AJ25=1,1.4*BB$1,BB$1)),(IF(AJ25=1,1.4*BB$1,BB$1))) -> 35.384615 | AW25: =IF($AE25=1,1.3*(IF(AK25=1,1.4*BC$1,BC$1)),(IF(AK25=1,1.4*BC$1,BC$1))) -> 936.92308 | AX25: =IF($AE25=1,1.3*(IF(AL25=1,1.4*BD$1,BD$1)),(IF(AL25=1,1.4*BD$1,BD$1))) -> 242.30769 | AY25: =IF($AE25=1,1.3*(IF(AM25=1,1.4*BE$1,BE$1)),(IF(AM25=1,1.4*BE$1,BE$1))) -> 557.69231 | ... BB25: =IF($AE25=1,1.3*(IF(AP25=1,1.4*BH$1,BH$1)),(IF(AP25=1,1.4*BH$1,BH$1))) -> 168.26923 | BC25: =SUM(AR25:BB25) -> 3779.5 | BD25: =BC25*4.2 -> 15873.9 | BE25: =BD25*2 -> 31747.8 | BF25: =IF(AE25=1,$BK$1,$BL$1) -> 9230 | BG25: =BF25-BD25 -> -6643.9 | BH25: =(H25-BC25)*4.2 -> 926.1
A26: 1996328039 | B26: Муж | C26: 20 | D26: Довольно активный (выхожу из дома не менее 4 дней в неделю) | E26: Да, официально | F26: 60000 | G26: Москва | H26: 5000 | I26: 5 | J26: 3 | K26: 4 | L26: 6 | M26: 3 | N26: 8 | O26: 8 | P26: 5 | Q26: 4 | R26: 5 | S26: 7 | T26: Нет | U26: Нет | V26: Нет | W26: Нет | X26: Нет | Y26: Нет | Z26: Нет | AA26: Да | AB26: Да | AC26: Нет | AD26: Да | AE26: =IF(G48 = "Москва",1,0) -> 0 | AF26: =IF(T26="Да",1,0) -> 0 | AG26: =IF(U25="Да",1,0) -> 0 | AH26: =IF(V25="Да",1,0) -> 1 | AI26: =IF(W25="Да",1,0) -> 0 | AJ26: =IF(X25="Да",1,0) -> 0 | AK26: =IF(Y25="Да",1,0) -> 1 | AL26: =IF(Z25="Да",1,0) -> 0 | AM26: =IF(AA25="Да",1,0) -> 0 | AN26: =IF(AB25="Да",1,0) -> 0 | ... AP26: =IF(AD25="Да",1,0) -> 1 | AR26: =IF($AE26=1,1.3*(IF(AF26=1,1.4*AX$1,AX$1)),(IF(AF26=1,1.4*AX$1,AX$1))) -> 218.07692 | AS26: =IF($AE26=1,1.3*(IF(AG26=1,1.4*AY$1,AY$1)),(IF(AG26=1,1.4*AY$1,AY$1))) -> 192.30769 | AT26: =IF($AE26=1,1.3*(IF(AH26=1,1.4*AZ$1,AZ$1)),(IF(AH26=1,1.4*AZ$1,AZ$1))) -> 920.76923 | AU26: =IF($AE26=1,1.3*(IF(AI26=1,1.4*BA$1,BA$1)),(IF(AI26=1,1.4*BA$1,BA$1))) -> 230.76923 | AV26: =IF($AE26=1,1.3*(IF(AJ26=1,1.4*BB$1,BB$1)),(IF(AJ26=1,1.4*BB$1,BB$1))) -> 35.384615 | AW26: =IF($AE26=1,1.3*(IF(AK26=1,1.4*BC$1,BC$1)),(IF(AK26=1,1.4*BC$1,BC$1))) -> 936.92308 | AX26: =IF($AE26=1,1.3*(IF(AL26=1,1.4*BD$1,BD$1)),(IF(AL26=1,1.4*BD$1,BD$1))) -> 242.30769 | AY26: =IF($AE26=1,1.3*(IF(AM26=1,1.4*BE$1,BE$1)),(IF(AM26=1,1.4*BE$1,BE$1))) -> 557.69231 | ... BB26: =IF($AE26=1,1.3*(IF(AP26=1,1.4*BH$1,BH$1)),(IF(AP26=1,1.4*BH$1,BH$1))) -> 168.26923 | BC26: =SUM(AR26:BB26) -> 3580.5769 | BD26: =BC26*4.2 -> 15038.423 | BE26: =BD26*2 -> 30076.846 | BF26: =IF(AE26=1,$BK$1,$BL$1) -> 9230 | BG26: =BF26-BD26 -> -5808.4231 | BH26: =(H26-BC26)*4.2 -> 5961.5769
A27: 1996328591 | B27: Муж | C27: 20 | D27: Активный (выхожу из дома не менее 6 дней в неделю) | E27: Да, официально | F27: 30000 | G27: Москва | H27: 10000 | I27: 5 | J27: 5 | K27: 8 | L27: 9 | M27: 3 | N27: 10 | O27: 2 | P27: 10 | Q27: 3 | R27: 8 | S27: 8 | T27: Нет | U27: Нет | V27: Нет | W27: Нет | X27: Нет | Y27: Нет | Z27: Нет | AA27: Нет | AB27: Нет | AC27: Нет | AD27: Нет | AE27: =IF(G49 = "Москва",1,0) -> 0 | AF27: =IF(T27="Да",1,0) -> 0 | AG27: =IF(U26="Да",1,0) -> 0 | AH27: =IF(V26="Да",1,0) -> 0 | AI27: =IF(W26="Да",1,0) -> 0 | AJ27: =IF(X26="Да",1,0) -> 0 | AK27: =IF(Y26="Да",1,0) -> 0 | AL27: =IF(Z26="Да",1,0) -> 0 | AM27: =IF(AA26="Да",1,0) -> 1 | AN27: =IF(AB26="Да",1,0) -> 1 | ... AP27: =IF(AD26="Да",1,0) -> 1 | AR27: =IF($AE27=1,1.3*(IF(AF27=1,1.4*AX$1,AX$1)),(IF(AF27=1,1.4*AX$1,AX$1))) -> 218.07692 | AS27: =IF($AE27=1,1.3*(IF(AG27=1,1.4*AY$1,AY$1)),(IF(AG27=1,1.4*AY$1,AY$1))) -> 192.30769 | AT27: =IF($AE27=1,1.3*(IF(AH27=1,1.4*AZ$1,AZ$1)),(IF(AH27=1,1.4*AZ$1,AZ$1))) -> 657.69231 | AU27: =IF($AE27=1,1.3*(IF(AI27=1,1.4*BA$1,BA$1)),(IF(AI27=1,1.4*BA$1,BA$1))) -> 230.76923 | AV27: =IF($AE27=1,1.3*(IF(AJ27=1,1.4*BB$1,BB$1)),(IF(AJ27=1,1.4*BB$1,BB$1))) -> 35.384615 | AW27: =IF($AE27=1,1.3*(IF(AK27=1,1.4*BC$1,BC$1)),(IF(AK27=1,1.4*BC$1,BC$1))) -> 669.23077 | AX27: =IF($AE27=1,1.3*(IF(AL27=1,1.4*BD$1,BD$1)),(IF(AL27=1,1.4*BD$1,BD$1))) -> 242.30769 | AY27: =IF($AE27=1,1.3*(IF(AM27=1,1.4*BE$1,BE$1)),(IF(AM27=1,1.4*BE$1,BE$1))) -> 780.76923 | ... BB27: =IF($AE27=1,1.3*(IF(AP27=1,1.4*BH$1,BH$1)),(IF(AP27=1,1.4*BH$1,BH$1))) -> 168.26923 | BC27: =SUM(AR27:BB27) -> 3292.2692 | BD27: =BC27*4.2 -> 13827.531 | BE27: =BD27*2 -> 27655.062 | BF27: =IF(AE27=1,$BK$1,$BL$1) -> 9230 | BG27: =BF27-BD27 -> -4597.5308 | BH27: =(H27-BC27)*4.2 -> 28172.469
A28: 1996330348 | B28: Жен | C28: 20 | D28: Активный (выхожу из дома не менее 6 дней в неделю) | E28: Да, официально | F28: 60000 | G28: Москва | H28: 7000 | I28: 8 | J28: 3 | K28: 10 | L28: 10 | M28: 3 | N28: 7 | O28: 5 | P28: 5 | Q28: 7 | R28: 3 | S28: 10 | T28: Да | U28: Нет | V28: Нет | W28: Да | X28: Нет | Y28: Да | Z28: Нет | AA28: Нет | AB28: Да | AC28: Нет | AD28: Да | AE28: =IF(G50 = "Москва",1,0) -> 0 | AF28: =IF(T28="Да",1,0) -> 1 | AG28: =IF(U27="Да",1,0) -> 0 | AH28: =IF(V27="Да",1,0) -> 0 | AI28: =IF(W27="Да",1,0) -> 0 | AJ28: =IF(X27="Да",1,0) -> 0 | AK28: =IF(Y27="Да",1,0) -> 0 | AL28: =IF(Z27="Да",1,0) -> 0 | AM28: =IF(AA27="Да",1,0) -> 0 | AN28: =IF(AB27="Да",1,0) -> 0 | ... AP28: =IF(AD27="Да",1,0) -> 0 | AR28: =IF($AE28=1,1.3*(IF(AF28=1,1.4*AX$1,AX$1)),(IF(AF28=1,1.4*AX$1,AX$1))) -> 305.30769 | AS28: =IF($AE28=1,1.3*(IF(AG28=1,1.4*AY$1,AY$1)),(IF(AG28=1,1.4*AY$1,AY$1))) -> 192.30769 | AT28: =IF($AE28=1,1.3*(IF(AH28=1,1.4*AZ$1,AZ$1)),(IF(AH28=1,1.4*AZ$1,AZ$1))) -> 657.69231 | AU28: =IF($AE28=1,1.3*(IF(AI28=1,1.4*BA$1,BA$1)),(IF(AI28=1,1.4*BA$1,BA$1))) -> 230.76923 | AV28: =IF($AE28=1,1.3*(IF(AJ28=1,1.4*BB$1,BB$1)),(IF(AJ28=1,1.4*BB$1,BB$1))) -> 35.384615 | AW28: =IF($AE28=1,1.3*(IF(AK28=1,1.4*BC$1,BC$1)),(IF(AK28=1,1.4*BC$1,BC$1))) -> 669.23077 | AX28: =IF($AE28=1,1.3*(IF(AL28=1,1.4*BD$1,BD$1)),(IF(AL28=1,1.4*BD$1,BD$1))) -> 242.30769 | AY28: =IF($AE28=1,1.3*(IF(AM28=1,1.4*BE$1,BE$1)),(IF(AM28=1,1.4*BE$1,BE$1))) -> 557.69231 | ... BB28: =IF($AE28=1,1.3*(IF(AP28=1,1.4*BH$1,BH$1)),(IF(AP28=1,1.4*BH$1,BH$1))) -> 120.19231 | BC28: =SUM(AR28:BB28) -> 3088.9615 | BD28: =BC28*4.2 -> 12973.638 | BE28: =BD28*2 -> 25947.277 | BF28: =IF(AE28=1,$BK$1,$BL$1) -> 9230 | BG28: =BF28-BD28 -> -3743.6385 | BH28: =(H28-BC28)*4.2 -> 16426.362
A29: 1996330598 | B29: Жен | C29: 20 | D29: Довольно активный (выхожу из дома не менее 4 дней в неделю) | E29: Да, официально | F29: 60000 | G29: Москва | H29: 15000 | I29: 7 | J29: 4 | K29: 7 | L29: 6 | M29: 6 | N29: 8 | O29: 6 | P29: 7 | Q29: 7 | R29: 7 | S29: 4 | T29: Нет | U29: Нет | V29: Нет | W29: Да | X29: Нет | Y29: Да | Z29: Да | AA29: Нет | AB29: Да | AC29: Да | AD29: Нет | AE29: =IF(G51 = "Москва",1,0) -> 0 | AF29: =IF(T29="Да",1,0) -> 0 | AG29: =IF(U28="Да",1,0) -> 0 | AH29: =IF(V28="Да",1,0) -> 0 | AI29: =IF(W28="Да",1,0) -> 1 | AJ29: =IF(X28="Да",1,0) -> 0 | AK29: =IF(Y28="Да",1,0) -> 1 | AL29: =IF(Z28="Да",1,0) -> 0 | AM29: =IF(AA28="Да",1,0) -> 0 | AN29: =IF(AB28="Да",1,0) -> 1 | ... AP29: =IF(AD28="Да",1,0) -> 1 | AR29: =IF($AE29=1,1.3*(IF(AF29=1,1.4*AX$1,AX$1)),(IF(AF29=1,1.4*AX$1,AX$1))) -> 218.07692 | AS29: =IF($AE29=1,1.3*(IF(AG29=1,1.4*AY$1,AY$1)),(IF(AG29=1,1.4*AY$1,AY$1))) -> 192.30769 | AT29: =IF($AE29=1,1.3*(IF(AH29=1,1.4*AZ$1,AZ$1)),(IF(AH29=1,1.4*AZ$1,AZ$1))) -> 657.69231 | AU29: =IF($AE29=1,1.3*(IF(AI29=1,1.4*BA$1,BA$1)),(IF(AI29=1,1.4*BA$1,BA$1))) -> 323.07692 | AV29: =IF($AE29=1,1.3*(IF(AJ29=1,1.4*BB$1,BB$1)),(IF(AJ29=1,1.4*BB$1,BB$1))) -> 35.384615 | AW29: =IF($AE29=1,1.3*(IF(AK29=1,1.4*BC$1,BC$1)),(IF(AK29=1,1.4*BC$1,BC$1))) -> 936.92308 | AX29: =IF($AE29=1,1.3*(IF(AL29=1,1.4*BD$1,BD$1)),(IF(AL29=1,1.4*BD$1,BD$1))) -> 242.30769 | AY29: =IF($AE29=1,1.3*(IF(AM29=1,1.4*BE$1,BE$1)),(IF(AM29=1,1.4*BE$1,BE$1))) -> 557.69231 | ... BB29: =IF($AE29=1,1.3*(IF(AP29=1,1.4*BH$1,BH$1)),(IF(AP29=1,1.4*BH$1,BH$1))) -> 168.26923 | BC29: =SUM(AR29:BB29) -> 3429.1923 | BD29: =BC29*4.2 -> 14402.608 | BE29: =BD29*2 -> 28805.215 | BF29: =IF(AE29=1,$BK$1,$BL$1) -> 9230 | BG29: =BF29-BD29 -> -5172.6077 | BH29: =(H29-BC29)*4.2 -> 48597.392
A30: 1996331297 | B30: Муж | C30: 20 | D30: Довольно активный (выхожу из дома не менее 4 дней в неделю) | E30: Нет | F30: 12000 | G30: Москва | H30: 20000 | I30: 5 | J30: 5 | K30: 7 | L30: 4 | M30: 1 | N30: 10 | O30: 1 | P30: 10 | Q30: 10 | R30: 5 | S30: 2 | T30: Нет | U30: Нет | V30: Да | W30: Нет | X30: Нет | Y30: Да | Z30: Нет | AA30: Да | AB30: Да | AC30: Нет | AD30: Нет | AE30: =IF(G52 = "Москва",1,0) -> 0 | AF30: =IF(T30="Да",1,0) -> 0 | AG30: =IF(U29="Да",1,0) -> 0 | AH30: =IF(V29="Да",1,0) -> 0 | AI30: =IF(W29="Да",1,0) -> 1 | AJ30: =IF(X29="Да",1,0) -> 0 | AK30: =IF(Y29="Да",1,0) -> 1 | AL30: =IF(Z29="Да",1,0) -> 1 | AM30: =IF(AA29="Да",1,0) -> 0 | AN30: =IF(AB29="Да",1,0) -> 1 | ... AP30: =IF(AD29="Да",1,0) -> 0 | AR30: =IF($AE30=1,1.3*(IF(AF30=1,1.4*AX$1,AX$1)),(IF(AF30=1,1.4*AX$1,AX$1))) -> 218.07692 | AS30: =IF($AE30=1,1.3*(IF(AG30=1,1.4*AY$1,AY$1)),(IF(AG30=1,1.4*AY$1,AY$1))) -> 192.30769 | AT30: =IF($AE30=1,1.3*(IF(AH30=1,1.4*AZ$1,AZ$1)),(IF(AH30=1,1.4*AZ$1,AZ$1))) -> 657.69231 | AU30: =IF($AE30=1,1.3*(IF(AI30=1,1.4*BA$1,BA$1)),(IF(AI30=1,1.4*BA$1,BA$1))) -> 323.07692 | AV30: =IF($AE30=1,1.3*(IF(AJ30=1,1.4*BB$1,BB$1)),(IF(AJ30=1,1.4*BB$1,BB$1))) -> 35.384615 | AW30: =IF($AE30=1,1.3*(IF(AK30=1,1.4*BC$1,BC$1)),(IF(AK30=1,1.4*BC$1,BC$1))) -> 936.92308 | AX30: =IF($AE30=1,1.3*(IF(AL30=1,1.4*BD$1,BD$1)),(IF(AL30=1,1.4*BD$1,BD$1))) -> 339.23077 | AY30: =IF($AE30=1,1.3*(IF(AM30=1,1.4*BE$1,BE$1)),(IF(AM30=1,1.4*BE$1,BE$1))) -> 557.69231 | ... BB30: =IF($AE30=1,1.3*(IF(AP30=1,1.4*BH$1,BH$1)),(IF(AP30=1,1.4*BH$1,BH$1))) -> 120.19231 | BC30: =SUM(AR30:BB30) -> 3489.8846 | BD30: =BC30*4.2 -> 14657.515 | BE30: =BD30*2 -> 29315.031 | BF30: =IF(AE30=1,$BK$1,$BL$1) -> 9230 | BG30: =BF30-BD30 -> -5427.5154 | BH30: =(H30-BC30)*4.2 -> 69342.485
A31: 1996352201 | B31: Муж | C31: 20 | D31: Скорее пассивный (выхожу из дома не менее 2 дней в неделю) | E31: Нет | F31: 12000 | G31: Волжский, Волгоградская область | H31: 20000 | I31: 2 | J31: 7 | K31: 7 | L31: 8 | M31: 1 | N31: 10 | O31: 3 | P31: 9 | Q31: 10 | R31: 5 | S31: 1 | T31: Нет | U31: Да | V31: Нет | W31: Да | X31: Нет | Y31: Да | Z31: Нет | AA31: Да | AB31: Да | AC31: Да | AD31: Нет | AE31: =IF(G53 = "Москва",1,0) -> 0 | AF31: =IF(T31="Да",1,0) -> 0 | AG31: =IF(U30="Да",1,0) -> 0 | AH31: =IF(V30="Да",1,0) -> 1 | AI31: =IF(W30="Да",1,0) -> 0 | AJ31: =IF(X30="Да",1,0) -> 0 | AK31: =IF(Y30="Да",1,0) -> 1 | AL31: =IF(Z30="Да",1,0) -> 0 | AM31: =IF(AA30="Да",1,0) -> 1 | AN31: =IF(AB30="Да",1,0) -> 1 | ... AP31: =IF(AD30="Да",1,0) -> 0 | AR31: =IF($AE31=1,1.3*(IF(AF31=1,1.4*AX$1,AX$1)),(IF(AF31=1,1.4*AX$1,AX$1))) -> 218.07692 | AS31: =IF($AE31=1,1.3*(IF(AG31=1,1.4*AY$1,AY$1)),(IF(AG31=1,1.4*AY$1,AY$1))) -> 192.30769 | AT31: =IF($AE31=1,1.3*(IF(AH31=1,1.4*AZ$1,AZ$1)),(IF(AH31=1,1.4*AZ$1,AZ$1))) -> 920.76923 | AU31: =IF($AE31=1,1.3*(IF(AI31=1,1.4*BA$1,BA$1)),(IF(AI31=1,1.4*BA$1,BA$1))) -> 230.76923 | AV31: =IF($AE31=1,1.3*(IF(AJ31=1,1.4*BB$1,BB$1)),(IF(AJ31=1,1.4*BB$1,BB$1))) -> 35.384615 | AW31: =IF($AE31=1,1.3*(IF(AK31=1,1.4*BC$1,BC$1)),(IF(AK31=1,1.4*BC$1,BC$1))) -> 936.92308 | AX31: =IF($AE31=1,1.3*(IF(AL31=1,1.4*BD$1,BD$1)),(IF(AL31=1,1.4*BD$1,BD$1))) -> 242.30769 | AY31: =IF($AE31=1,1.3*(IF(AM31=1,1.4*BE$1,BE$1)),(IF(AM31=1,1.4*BE$1,BE$1))) -> 780.76923 | ... BB31: =IF($AE31=1,1.3*(IF(AP31=1,1.4*BH$1,BH$1)),(IF(AP31=1,1.4*BH$1,BH$1))) -> 120.19231 | BC31: =SUM(AR31:BB31) -> 3774.9615 | BD31: =BC31*4.2 -> 15854.838 | BE31: =BD31*2 -> 31709.677 | BF31: =IF(AE31=1,$BK$1,$BL$1) -> 9230 | BG31: =BF31-BD31 -> -6624.8385 | BH31: =(H31-BC31)*4.2 -> 68145.162
A32: 1996357490 | B32: Муж | C32: 20 | D32: Довольно активный (выхожу из дома не менее 4 дней в неделю) | E32: Да, неофициально | F32: 60000 | G32: Москва | H32: 1000 | I32: 3 | J32: 2 | K32: 3 | L32: 7 | M32: 1 | N32: 5 | O32: 5 | P32: 10 | Q32: 6 | R32: 2 | S32: 2 | T32: Нет | U32: Нет | V32: Нет | W32: Да | X32: Нет | Y32: Нет | Z32: Нет | AA32: Да | AB32: Да | AC32: Нет | AD32: Нет | AE32: =IF(G54 = "Москва",1,0) -> 0 | AF32: =IF(T32="Да",1,0) -> 0 | AG32: =IF(U31="Да",1,0) -> 1 | AH32: =IF(V31="Да",1,0) -> 0 | AI32: =IF(W31="Да",1,0) -> 1 | AJ32: =IF(X31="Да",1,0) -> 0 | AK32: =IF(Y31="Да",1,0) -> 1 | AL32: =IF(Z31="Да",1,0) -> 0 | AM32: =IF(AA31="Да",1,0) -> 1 | AN32: =IF(AB31="Да",1,0) -> 1 | ... AP32: =IF(AD31="Да",1,0) -> 0 | AR32: =IF($AE32=1,1.3*(IF(AF32=1,1.4*AX$1,AX$1)),(IF(AF32=1,1.4*AX$1,AX$1))) -> 218.07692 | AS32: =IF($AE32=1,1.3*(IF(AG32=1,1.4*AY$1,AY$1)),(IF(AG32=1,1.4*AY$1,AY$1))) -> 269.23077 | AT32: =IF($AE32=1,1.3*(IF(AH32=1,1.4*AZ$1,AZ$1)),(IF(AH32=1,1.4*AZ$1,AZ$1))) -> 657.69231 | AU32: =IF($AE32=1,1.3*(IF(AI32=1,1.4*BA$1,BA$1)),(IF(AI32=1,1.4*BA$1,BA$1))) -> 323.07692 | AV32: =IF($AE32=1,1.3*(IF(AJ32=1,1.4*BB$1,BB$1)),(IF(AJ32=1,1.4*BB$1,BB$1))) -> 35.384615 | AW32: =IF($AE32=1,1.3*(IF(AK32=1,1.4*BC$1,BC$1)),(IF(AK32=1,1.4*BC$1,BC$1))) -> 936.92308 | AX32: =IF($AE32=1,1.3*(IF(AL32=1,1.4*BD$1,BD$1)),(IF(AL32=1,1.4*BD$1,BD$1))) -> 242.30769 | AY32: =IF($AE32=1,1.3*(IF(AM32=1,1.4*BE$1,BE$1)),(IF(AM32=1,1.4*BE$1,BE$1))) -> 780.76923 | ... BB32: =IF($AE32=1,1.3*(IF(AP32=1,1.4*BH$1,BH$1)),(IF(AP32=1,1.4*BH$1,BH$1))) -> 120.19231 | BC32: =SUM(AR32:BB32) -> 3692.9615 | BD32: =BC32*4.2 -> 15510.438 | BE32: =BD32*2 -> 31020.877 | BF32: =IF(AE32=1,$BK$1,$BL$1) -> 9230 | BG32: =BF32-BD32 -> -6280.4385 | BH32: =(H32-BC32)*4.2 -> -11310.438
A33: 1996382686 | B33: Муж | C33: 20 | D33: Довольно активный (выхожу из дома не менее 4 дней в неделю) | E33: Нет | F33: 12000 | G33: Щёлково, Москва и Московская область | H33: 2777 | I33: 7 | J33: 7 | K33: 8 | L33: 4 | M33: 3 | N33: 7 | O33: 3 | P33: 7 | Q33: 7 | R33: 10 | S33: 7 | T33: Да | U33: Нет | V33: Нет | W33: Нет | X33: Да | Y33: Да | Z33: Нет | AA33: Нет | AB33: Да | AC33: Да | AD33: Да | AE33: =IF(G55 = "Москва",1,0) -> 0 | AF33: =IF(T33="Да",1,0) -> 1 | AG33: =IF(U32="Да",1,0) -> 0 | AH33: =IF(V32="Да",1,0) -> 0 | AI33: =IF(W32="Да",1,0) -> 1 | AJ33: =IF(X32="Да",1,0) -> 0 | AK33: =IF(Y32="Да",1,0) -> 0 | AL33: =IF(Z32="Да",1,0) -> 0 | AM33: =IF(AA32="Да",1,0) -> 1 | AN33: =IF(AB32="Да",1,0) -> 1 | ... AP33: =IF(AD32="Да",1,0) -> 0 | AR33: =IF($AE33=1,1.3*(IF(AF33=1,1.4*AX$1,AX$1)),(IF(AF33=1,1.4*AX$1,AX$1))) -> 305.30769 | AS33: =IF($AE33=1,1.3*(IF(AG33=1,1.4*AY$1,AY$1)),(IF(AG33=1,1.4*AY$1,AY$1))) -> 192.30769 | AT33: =IF($AE33=1,1.3*(IF(AH33=1,1.4*AZ$1,AZ$1)),(IF(AH33=1,1.4*AZ$1,AZ$1))) -> 657.69231 | AU33: =IF($AE33=1,1.3*(IF(AI33=1,1.4*BA$1,BA$1)),(IF(AI33=1,1.4*BA$1,BA$1))) -> 323.07692 | AV33: =IF($AE33=1,1.3*(IF(AJ33=1,1.4*BB$1,BB$1)),(IF(AJ33=1,1.4*BB$1,BB$1))) -> 35.384615 | AW33: =IF($AE33=1,1.3*(IF(AK33=1,1.4*BC$1,BC$1)),(IF(AK33=1,1.4*BC$1,BC$1))) -> 669.23077 | AX33: =IF($AE33=1,1.3*(IF(AL33=1,1.4*BD$1,BD$1)),(IF(AL33=1,1.4*BD$1,BD$1))) -> 242.30769 | AY33: =IF($AE33=1,1.3*(IF(AM33=1,1.4*BE$1,BE$1)),(IF(AM33=1,1.4*BE$1,BE$1))) -> 780.76923 | ... BB33: =IF($AE33=1,1.3*(IF(AP33=1,1.4*BH$1,BH$1)),(IF(AP33=1,1.4*BH$1,BH$1))) -> 120.19231 | BC33: =SUM(AR33:BB33) -> 3423.7308 | BD33: =BC33*4.2 -> 14379.669 | BE33: =BD33*2 -> 28759.338 | BF33: =IF(AE33=1,$BK$1,$BL$1) -> 9230 | BG33: =BF33-BD33 -> -5149.6692 | BH33: =(H33-BC33)*4.2 -> -2716.2692
A34: 1996462484 | B34: Жен | C34: 35 | D34: Активный (выхожу из дома не менее 6 дней в неделю) | E34: Да, официально | F34: 60000 | G34: Улан-Удэ, Республика Бурятия | H34: 20000 | I34: 2 | J34: 2 | K34: 10 | L34: 10 | M34: 2 | N34: 10 | O34: 10 | P34: 4 | Q34: 10 | R34: 4 | S34: 10 | T34: Нет | U34: Нет | V34: Да | W34: Да | X34: Нет | Y34: Да | Z34: Нет | AA34: Нет | AB34: Да | AC34: Нет | AD34: Нет | AE34: =IF(G56 = "Москва",1,0) -> 0 | AF34: =IF(T34="Да",1,0) -> 0 | AG34: =IF(U33="Да",1,0) -> 0 | AH34: =IF(V33="Да",1,0) -> 0 | AI34: =IF(W33="Да",1,0) -> 0 | AJ34: =IF(X33="Да",1,0) -> 1 | AK34: =IF(Y33="Да",1,0) -> 1 | AL34: =IF(Z33="Да",1,0) -> 0 | AM34: =IF(AA33="Да",1,0) -> 0 | AN34: =IF(AB33="Да",1,0) -> 1 | ... AP34: =IF(AD33="Да",1,0) -> 1 | AR34: =IF($AE34=1,1.3*(IF(AF34=1,1.4*AX$1,AX$1)),(IF(AF34=1,1.4*AX$1,AX$1))) -> 218.07692 | AS34: =IF($AE34=1,1.3*(IF(AG34=1,1.4*AY$1,AY$1)),(IF(AG34=1,1.4*AY$1,AY$1))) -> 192.30769 | AT34: =IF($AE34=1,1.3*(IF(AH34=1,1.4*AZ$1,AZ$1)),(IF(AH34=1,1.4*AZ$1,AZ$1))) -> 657.69231 | AU34: =IF($AE34=1,1.3*(IF(AI34=1,1.4*BA$1,BA$1)),(IF(AI34=1,1.4*BA$1,BA$1))) -> 230.76923 | AV34: =IF($AE34=1,1.3*(IF(AJ34=1,1.4*BB$1,BB$1)),(IF(AJ34=1,1.4*BB$1,BB$1))) -> 49.538462 | AW34: =IF($AE34=1,1.3*(IF(AK34=1,1.4*BC$1,BC$1)),(IF(AK34=1,1.4*BC$1,BC$1))) -> 936.92308 | AX34: =IF($AE34=1,1.3*(IF(AL34=1,1.4*BD$1,BD$1)),(IF(AL34=1,1.4*BD$1,BD$1))) -> 242.30769 | AY34: =IF($AE34=1,1.3*(IF(AM34=1,1.4*BE$1,BE$1)),(IF(AM34=1,1.4*BE$1,BE$1))) -> 557.69231 | ... BB34: =IF($AE34=1,1.3*(IF(AP34=1,1.4*BH$1,BH$1)),(IF(AP34=1,1.4*BH$1,BH$1))) -> 168.26923 | BC34: =SUM(AR34:BB34) -> 3362.8846 | BD34: =BC34*4.2 -> 14124.115 | BE34: =BD34*2 -> 28248.231 | BF34: =IF(AE34=1,$BK$1,$BL$1) -> 9230 | BG34: =BF34-BD34 -> -4894.1154 | BH34: =(H34-BC34)*4.2 -> 69875.885
A35: 1996671051 | B35: Жен | C35: 20 | D35: Довольно активный (выхожу из дома не менее 4 дней в неделю) | E35: Да, официально | F35: 30000 | G35: Тула, Тульская область | H35: 5000 | I35: 3 | J35: 1 | K35: 10 | L35: 8 | M35: 1 | N35: 10 | O35: 10 | P35: 4 | Q35: 4 | R35: 9 | S35: 9 | T35: Нет | U35: Нет | V35: Да | W35: Да | X35: Нет | Y35: Да | Z35: Да | AA35: Нет | AB35: Да | AC35: Да | AD35: Да | AE35: =IF(G57 = "Москва",1,0) -> 0 | AF35: =IF(T35="Да",1,0) -> 0 | AG35: =IF(U34="Да",1,0) -> 0 | AH35: =IF(V34="Да",1,0) -> 1 | AI35: =IF(W34="Да",1,0) -> 1 | AJ35: =IF(X34="Да",1,0) -> 0 | AK35: =IF(Y34="Да",1,0) -> 1 | AL35: =IF(Z34="Да",1,0) -> 0 | AM35: =IF(AA34="Да",1,0) -> 0 | AN35: =IF(AB34="Да",1,0) -> 1 | ... AP35: =IF(AD34="Да",1,0) -> 0 | AR35: =IF($AE35=1,1.3*(IF(AF35=1,1.4*AX$1,AX$1)),(IF(AF35=1,1.4*AX$1,AX$1))) -> 218.07692 | AS35: =IF($AE35=1,1.3*(IF(AG35=1,1.4*AY$1,AY$1)),(IF(AG35=1,1.4*AY$1,AY$1))) -> 192.30769 | AT35: =IF($AE35=1,1.3*(IF(AH35=1,1.4*AZ$1,AZ$1)),(IF(AH35=1,1.4*AZ$1,AZ$1))) -> 920.76923 | AU35: =IF($AE35=1,1.3*(IF(AI35=1,1.4*BA$1,BA$1)),(IF(AI35=1,1.4*BA$1,BA$1))) -> 323.07692 | AV35: =IF($AE35=1,1.3*(IF(AJ35=1,1.4*BB$1,BB$1)),(IF(AJ35=1,1.4*BB$1,BB$1))) -> 35.384615 | AW35: =IF($AE35=1,1.3*(IF(AK35=1,1.4*BC$1,BC$1)),(IF(AK35=1,1.4*BC$1,BC$1))) -> 936.92308 | AX35: =IF($AE35=1,1.3*(IF(AL35=1,1.4*BD$1,BD$1)),(IF(AL35=1,1.4*BD$1,BD$1))) -> 242.30769 | AY35: =IF($AE35=1,1.3*(IF(AM35=1,1.4*BE$1,BE$1)),(IF(AM35=1,1.4*BE$1,BE$1))) -> 557.69231 | ... BB35: =IF($AE35=1,1.3*(IF(AP35=1,1.4*BH$1,BH$1)),(IF(AP35=1,1.4*BH$1,BH$1))) -> 120.19231 | BC35: =SUM(AR35:BB35) -> 3644.1923 | BD35: =BC35*4.2 -> 15305.608 | BE35: =BD35*2 -> 30611.215 | BF35: =IF(AE35=1,$BK$1,$BL$1) -> 9230 | BG35: =BF35-BD35 -> -6075.6077 | BH35: =(H35-BC35)*4.2 -> 5694.3923
A36: 1997094996 | B36: Жен | C36: 20 | D36: Активный (выхожу из дома не менее 6 дней в неделю) | E36: Да, официально | F36: 60000 | G36: Волжский, Волгоградская область | H36: 5000 | I36: 1 | J36: 10 | K36: 10 | L36: 10 | M36: 1 | N36: 5 | O36: 5 | P36: 10 | Q36: 5 | R36: 3 | S36: 3 | T36: Нет | U36: Нет | V36: Да | W36: Да | X36: Нет | Y36: Да | Z36: Да | AA36: Да | AB36: Да | AC36: Нет | AD36: Нет | AE36: =IF(G58 = "Москва",1,0) -> 0 | AF36: =IF(T36="Да",1,0) -> 0 | AG36: =IF(U35="Да",1,0) -> 0 | AH36: =IF(V35="Да",1,0) -> 1 | AI36: =IF(W35="Да",1,0) -> 1 | AJ36: =IF(X35="Да",1,0) -> 0 | AK36: =IF(Y35="Да",1,0) -> 1 | AL36: =IF(Z35="Да",1,0) -> 1 | AM36: =IF(AA35="Да",1,0) -> 0 | AN36: =IF(AB35="Да",1,0) -> 1 | ... AP36: =IF(AD35="Да",1,0) -> 1 | AR36: =IF($AE36=1,1.3*(IF(AF36=1,1.4*AX$1,AX$1)),(IF(AF36=1,1.4*AX$1,AX$1))) -> 218.07692 | AS36: =IF($AE36=1,1.3*(IF(AG36=1,1.4*AY$1,AY$1)),(IF(AG36=1,1.4*AY$1,AY$1))) -> 192.30769 | AT36: =IF($AE36=1,1.3*(IF(AH36=1,1.4*AZ$1,AZ$1)),(IF(AH36=1,1.4*AZ$1,AZ$1))) -> 920.76923 | AU36: =IF($AE36=1,1.3*(IF(AI36=1,1.4*BA$1,BA$1)),(IF(AI36=1,1.4*BA$1,BA$1))) -> 323.07692 | AV36: =IF($AE36=1,1.3*(IF(AJ36=1,1.4*BB$1,BB$1)),(IF(AJ36=1,1.4*BB$1,BB$1))) -> 35.384615 | AW36: =IF($AE36=1,1.3*(IF(AK36=1,1.4*BC$1,BC$1)),(IF(AK36=1,1.4*BC$1,BC$1))) -> 936.92308 | AX36: =IF($AE36=1,1.3*(IF(AL36=1,1.4*BD$1,BD$1)),(IF(AL36=1,1.4*BD$1,BD$1))) -> 339.23077 | AY36: =IF($AE36=1,1.3*(IF(AM36=1,1.4*BE$1,BE$1)),(IF(AM36=1,1.4*BE$1,BE$1))) -> 557.69231 | ... BB36: =IF($AE36=1,1.3*(IF(AP36=1,1.4*BH$1,BH$1)),(IF(AP36=1,1.4*BH$1,BH$1))) -> 168.26923 | BC36: =SUM(AR36:BB36) -> 3801.0385 | BD36: =BC36*4.2 -> 15964.362 | BE36: =BD36*2 -> 31928.723 | BF36: =IF(AE36=1,$BK$1,$BL$1) -> 9230 | BG36: =BF36-BD36 -> -6734.3615 | BH36: =(H36-BC36)*4.2 -> 5035.6385
A37: 1997394046 | B37: Жен | C37: 20 | D37: Активный (выхожу из дома не менее 6 дней в неделю) | E37: Да, неофициально | F37: 12000 | G37: Волжский, Волгоградская область | H37: 10000 | I37: 1 | J37: 1 | K37: 10 | L37: 10 | M37: 1 | N37: 10 | O37: 10 | P37: 8 | Q37: 10 | R37: 5 | S37: 5 | T37: Нет | U37: Нет | V37: Да | W37: Да | X37: Нет | Y37: Да | Z37: Да | AA37: Да | AB37: Да | AC37: Да | AD37: Да | AE37: =IF(G59 = "Москва",1,0) -> 0 | AF37: =IF(T37="Да",1,0) -> 0 | AG37: =IF(U36="Да",1,0) -> 0 | AH37: =IF(V36="Да",1,0) -> 1 | AI37: =IF(W36="Да",1,0) -> 1 | AJ37: =IF(X36="Да",1,0) -> 0 | AK37: =IF(Y36="Да",1,0) -> 1 | AL37: =IF(Z36="Да",1,0) -> 1 | AM37: =IF(AA36="Да",1,0) -> 1 | AN37: =IF(AB36="Да",1,0) -> 1 | ... AP37: =IF(AD36="Да",1,0) -> 0 | AR37: =IF($AE37=1,1.3*(IF(AF37=1,1.4*AX$1,AX$1)),(IF(AF37=1,1.4*AX$1,AX$1))) -> 218.07692 | AS37: =IF($AE37=1,1.3*(IF(AG37=1,1.4*AY$1,AY$1)),(IF(AG37=1,1.4*AY$1,AY$1))) -> 192.30769 | AT37: =IF($AE37=1,1.3*(IF(AH37=1,1.4*AZ$1,AZ$1)),(IF(AH37=1,1.4*AZ$1,AZ$1))) -> 920.76923 | AU37: =IF($AE37=1,1.3*(IF(AI37=1,1.4*BA$1,BA$1)),(IF(AI37=1,1.4*BA$1,BA$1))) -> 323.07692 | AV37: =IF($AE37=1,1.3*(IF(AJ37=1,1.4*BB$1,BB$1)),(IF(AJ37=1,1.4*BB$1,BB$1))) -> 35.384615 | AW37: =IF($AE37=1,1.3*(IF(AK37=1,1.4*BC$1,BC$1)),(IF(AK37=1,1.4*BC$1,BC$1))) -> 936.92308 | AX37: =IF($AE37=1,1.3*(IF(AL37=1,1.4*BD$1,BD$1)),(IF(AL37=1,1.4*BD$1,BD$1))) -> 339.23077 | AY37: =IF($AE37=1,1.3*(IF(AM37=1,1.4*BE$1,BE$1)),(IF(AM37=1,1.4*BE$1,BE$1))) -> 780.76923 | ... BB37: =IF($AE37=1,1.3*(IF(AP37=1,1.4*BH$1,BH$1)),(IF(AP37=1,1.4*BH$1,BH$1))) -> 120.19231 | BC37: =SUM(AR37:BB37) -> 3964.1923 | BD37: =BC37*4.2 -> 16649.608 | BE37: =BD37*2 -> 33299.215 | BF37: =IF(AE37=1,$BK$1,$BL$1) -> 9230 | BG37: =BF37-BD37 -> -7419.6077 | BH37: =(H37-BC37)*4.2 -> 25350.392
A38: 1997430362 | B38: Муж | C38: 18 | D38: Активный (выхожу из дома не менее 6 дней в неделю) | E38: Нет | F38: 12000 | G38: Волжский, Волгоградская область | H38: 4000 | I38: 5 | J38: 5 | K38: 8 | L38: 5 | M38: 4 | N38: 10 | O38: 3 | P38: 8 | Q38: 8 | R38: 9 | S38: 9 | T38: Да | U38: Нет | V38: Нет | W38: Нет | X38: Нет | Y38: Да | Z38: Нет | AA38: Нет | AB38: Да | AC38: Да | AD38: Да | AE38: =IF(G60 = "Москва",1,0) -> 0 | AF38: =IF(T38="Да",1,0) -> 1 | AG38: =IF(U37="Да",1,0) -> 0 | AH38: =IF(V37="Да",1,0) -> 1 | AI38: =IF(W37="Да",1,0) -> 1 | AJ38: =IF(X37="Да",1,0) -> 0 | AK38: =IF(Y37="Да",1,0) -> 1 | AL38: =IF(Z37="Да",1,0) -> 1 | AM38: =IF(AA37="Да",1,0) -> 1 | AN38: =IF(AB37="Да",1,0) -> 1 | ... AP38: =IF(AD37="Да",1,0) -> 1 | AR38: =IF($AE38=1,1.3*(IF(AF38=1,1.4*AX$1,AX$1)),(IF(AF38=1,1.4*AX$1,AX$1))) -> 305.30769 | AS38: =IF($AE38=1,1.3*(IF(AG38=1,1.4*AY$1,AY$1)),(IF(AG38=1,1.4*AY$1,AY$1))) -> 192.30769 | AT38: =IF($AE38=1,1.3*(IF(AH38=1,1.4*AZ$1,AZ$1)),(IF(AH38=1,1.4*AZ$1,AZ$1))) -> 920.76923 | AU38: =IF($AE38=1,1.3*(IF(AI38=1,1.4*BA$1,BA$1)),(IF(AI38=1,1.4*BA$1,BA$1))) -> 323.07692 | AV38: =IF($AE38=1,1.3*(IF(AJ38=1,1.4*BB$1,BB$1)),(IF(AJ38=1,1.4*BB$1,BB$1))) -> 35.384615 | AW38: =IF($AE38=1,1.3*(IF(AK38=1,1.4*BC$1,BC$1)),(IF(AK38=1,1.4*BC$1,BC$1))) -> 936.92308 | AX38: =IF($AE38=1,1.3*(IF(AL38=1,1.4*BD$1,BD$1)),(IF(AL38=1,1.4*BD$1,BD$1))) -> 339.23077 | AY38: =IF($AE38=1,1.3*(IF(AM38=1,1.4*BE$1,BE$1)),(IF(AM38=1,1.4*BE$1,BE$1))) -> 780.76923 | ... BB38: =IF($AE38=1,1.3*(IF(AP38=1,1.4*BH$1,BH$1)),(IF(AP38=1,1.4*BH$1,BH$1))) -> 168.26923 | BC38: =SUM(AR38:BB38) -> 4111.3462 | BD38: =BC38*4.2 -> 17267.654 | BE38: =BD38*2 -> 34535.308 | BF38: =IF(AE38=1,$BK$1,$BL$1) -> 9230 | BG38: =BF38-BD38 -> -8037.6538 | BH38: =(H38-BC38)*4.2 -> -467.65385
... A40: 1999577997 | B40: Жен | C40: 50 | D40: Активный (выхожу из дома не менее 6 дней в неделю) | E40: Да, официально | F40: 60000 | G40: Волжский, Волгоградская область | H40: 5000 | I40: 2 | J40: 5 | K40: 5 | L40: 5 | M40: 1 | N40: 10 | O40: 3 | P40: 7 | Q40: 7 | R40: 8 | S40: 5 | T40: Нет | U40: Да | V40: Да | W40: Нет | X40: Нет | Y40: Да | Z40: Нет | AA40: Нет | AB40: Да | AC40: Да | AD40: Да | AE40: =IF(G62 = "Москва",1,0) -> 0 | AF40: =IF(T40="Да",1,0) -> 0 | AG40: =IF(U39="Да",1,0) -> 0 | AH40: =IF(V39="Да",1,0) -> 1 | AI40: =IF(W39="Да",1,0) -> 0 | AJ40: =IF(X39="Да",1,0) -> 0 | AK40: =IF(Y39="Да",1,0) -> 1 | AL40: =IF(Z39="Да",1,0) -> 0 | AM40: =IF(AA39="Да",1,0) -> 1 | AN40: =IF(AB39="Да",1,0) -> 0 | ... AP40: =IF(AD39="Да",1,0) -> 0 | AR40: =IF($AE40=1,1.3*(IF(AF40=1,1.4*AX$1,AX$1)),(IF(AF40=1,1.4*AX$1,AX$1))) -> 218.07692 | AS40: =IF($AE40=1,1.3*(IF(AG40=1,1.4*AY$1,AY$1)),(IF(AG40=1,1.4*AY$1,AY$1))) -> 192.30769 | AT40: =IF($AE40=1,1.3*(IF(AH40=1,1.4*AZ$1,AZ$1)),(IF(AH40=1,1.4*AZ$1,AZ$1))) -> 920.76923 | AU40: =IF($AE40=1,1.3*(IF(AI40=1,1.4*BA$1,BA$1)),(IF(AI40=1,1.4*BA$1,BA$1))) -> 230.76923 | AV40: =IF($AE40=1,1.3*(IF(AJ40=1,1.4*BB$1,BB$1)),(IF(AJ40=1,1.4*BB$1,BB$1))) -> 35.384615 | AW40: =IF($AE40=1,1.3*(IF(AK40=1,1.4*BC$1,BC$1)),(IF(AK40=1,1.4*BC$1,BC$1))) -> 936.92308 | AX40: =IF($AE40=1,1.3*(IF(AL40=1,1.4*BD$1,BD$1)),(IF(AL40=1,1.4*BD$1,BD$1))) -> 242.30769 | AY40: =IF($AE40=1,1.3*(IF(AM40=1,1.4*BE$1,BE$1)),(IF(AM40=1,1.4*BE$1,BE$1))) -> 780.76923 | ... BB40: =IF($AE40=1,1.3*(IF(AP40=1,1.4*BH$1,BH$1)),(IF(AP40=1,1.4*BH$1,BH$1))) -> 120.19231 | BC40: =SUM(AR40:BB40) -> 3767.4231 | BD40: =BC40*4.2 -> 15823.177 | BE40: =BD40*2 -> 31646.354 | BF40: =IF(AE40=1,$BK$1,$BL$1) -> 9230 | BG40: =BF40-BD40 -> -6593.1769 | BH40: =(H40-BC40)*4.2 -> 5176.8231
A41: 2009568744 | B41: Жен | C41: 20 | D41: Активный (выхожу из дома не менее 6 дней в неделю) | E41: Нет | F41: 12000 | G41: Новосибирск, Новосибирская область | H41: 20000 | I41: 8 | J41: 1 | K41: 8 | L41: 9 | M41: 1 | N41: 10 | O41: 1 | P41: 10 | Q41: 3 | R41: 3 | S41: 10 | T41: Да | U41: Нет | V41: Да | W41: Да | X41: Нет | Y41: Да | Z41: Нет | AA41: Да | AB41: Нет | AC41: Нет | AD41: Да | AE41: =IF(G63 = "Москва",1,0) -> 0 | AF41: =IF(T41="Да",1,0) -> 1 | AG41: =IF(U40="Да",1,0) -> 1 | AH41: =IF(V40="Да",1,0) -> 1 | AI41: =IF(W40="Да",1,0) -> 0 | AJ41: =IF(X40="Да",1,0) -> 0 | AK41: =IF(Y40="Да",1,0) -> 1 | AL41: =IF(Z40="Да",1,0) -> 0 | AM41: =IF(AA40="Да",1,0) -> 0 | AN41: =IF(AB40="Да",1,0) -> 1 | ... AP41: =IF(AD40="Да",1,0) -> 1 | AR41: =IF($AE41=1,1.3*(IF(AF41=1,1.4*AX$1,AX$1)),(IF(AF41=1,1.4*AX$1,AX$1))) -> 305.30769 | AS41: =IF($AE41=1,1.3*(IF(AG41=1,1.4*AY$1,AY$1)),(IF(AG41=1,1.4*AY$1,AY$1))) -> 269.23077 | AT41: =IF($AE41=1,1.3*(IF(AH41=1,1.4*AZ$1,AZ$1)),(IF(AH41=1,1.4*AZ$1,AZ$1))) -> 920.76923 | AU41: =IF($AE41=1,1.3*(IF(AI41=1,1.4*BA$1,BA$1)),(IF(AI41=1,1.4*BA$1,BA$1))) -> 230.76923 | AV41: =IF($AE41=1,1.3*(IF(AJ41=1,1.4*BB$1,BB$1)),(IF(AJ41=1,1.4*BB$1,BB$1))) -> 35.384615 | AW41: =IF($AE41=1,1.3*(IF(AK41=1,1.4*BC$1,BC$1)),(IF(AK41=1,1.4*BC$1,BC$1))) -> 936.92308 | AX41: =IF($AE41=1,1.3*(IF(AL41=1,1.4*BD$1,BD$1)),(IF(AL41=1,1.4*BD$1,BD$1))) -> 242.30769 | AY41: =IF($AE41=1,1.3*(IF(AM41=1,1.4*BE$1,BE$1)),(IF(AM41=1,1.4*BE$1,BE$1))) -> 557.69231 | ... BB41: =IF($AE41=1,1.3*(IF(AP41=1,1.4*BH$1,BH$1)),(IF(AP41=1,1.4*BH$1,BH$1))) -> 168.26923 | BC41: =SUM(AR41:BB41) -> 3775.9615 | BD41: =BC41*4.2 -> 15859.038 | BE41: =BD41*2 -> 31718.077 | BF41: =IF(AE41=1,$BK$1,$BL$1) -> 9230 | BG41: =BF41-BD41 -> -6629.0385 | BH41: =(H41-BC41)*4.2 -> 68140.962

Sheet Лист1
A1: Субъект РФ | B1: Величина прожиточного минимума на 2025 год (в руб.) | F1: Нормативный акт, установивший величину прожиточного минимума
B2: на душу населения | C2: для трудоспособного населения | D2: для пенсионеров | E2: для детей | K2: Наименование продукта | L2: Хлебобулочные изделия и крупы | M2: Картофель | N2: Овощи | O2: Фрукты | P2: Сахар | Q2: Мясо | R2: Рыба | S2: Молочные продукты | T2: Яйца | U2: Масло и жиры | V2: Чай и специи
A3: Москва | B3: 23908 | C3: 27302 | D3: 17897 | E3: 20663 | F3: Постановление Правительства Москвы от 05.11.2024 N 2482-ПП | I3: =MEDIAN(I4:I87) -> 18459
A4: Московская область | B4: 19302 | C4: 21039 | D4: 16600 | E4: 18723 | F4: Постановление Правительства Московской области от 13.08.2024 N 851-ПП | I4: 21039
A5: Санкт-Петербург | B5: 19329 | C5: 21069 | D5: 16623 | E5: 18749 | F5: Постановление Правительства Санкт-Петербурга от 08.08.2024 N 682 | I5: 21069
A6: Ленинградская область | B6: 18974 | C6: 20682 | D6: 16318 | E6: 18 405 | F6: Постановление Правительства Ленинградской области от 02.08.2024 N 529 | I6: 20682
A7: Республика Адыгея (Адыгея) | B7: 15250 | C7: 16623 | D7: 13115 | E7: 14793 | F7: Постановление Кабинета Министров Республики Адыгея от 19.07.2024 N 108 | I7: 16623
A8: Республика Алтай | B8: 16846 | C8: 18362 | D8: 14488 | E8: 16341 | F8: Постановление Правительства Республики Алтай от 06.09.2024 N 312 | I8: 18362
A9: Республика Башкортостан | B9: 15782 | C9: 17202 | D9: 13573 | E9: 15309 | F9: Постановление Правительства Республики Башкортостан от 31.07.2024 N 323 | I9: 17202
A10: Республика Бурятия | B10: 19329 | C10: 21069 | D10: 16623 | E10: 18749 | F10: Постановление Правительства Республики Бурятия от 08.08.2024 N 456 | I10: 21069
A11: Республика Дагестан | B11: 16137 | C11: 17589 | D11: 13878 | E11: 15653 | F11: Постановление Правительства Республики Дагестан от 31.07.2024 N 227 | I11: 17589
A12: Республика Ингушетия | B12: 16669 | C12: 18169 | D12: 14335 | E12: 16169 | F12: Постановление Правительства Республики Ингушетия от 01.08.2024 N 135 | I12: 18169
A13: Кабардино-Балкарская Республика | B13: 18974 | C13: 20682 | D13: 16318 | E13: 18405 | F13: Постановление Правительства Кабардино-Балкарской Республики от 13.09.2024 N 142-ПП | I13: 20682
A14: Республика Калмыкия | B14: 17378 | C14: 18942 | D14: 14945 | E14: 16857 | F14: Постановление Правительства Республики Калмыкия от 19.08.2024 N 251 | I14: 18942
A15: Карачаево-Черкесская Республика | B15: 16669 | C15: 18169 | D15: 14335 | E15: 16169 | F15: Постановление Правительства Карачаево-Черкесской Республики от 01.08.2024 N 158 | I15: 18169
A16: Республика Карелия | B16: 19 684 <*> | C16: 21 456 <*> | D16: 16 928 <*> | E16: 19 093 <*> | F16: Постановление Правительства Республики Карелия от 30.08.2024 N 270-П | I16: 21 456 <*>
A17: Республика Коми | B17: 20 393 <*> | C17: 22 228 <*> | D17: 17 538 <*> | E17: 19 781 <*> | F17: Постановление Правительства Республики Коми от 29.08.2024 N 363 | I17: 22 228 <*>
A18: Республика Крым | B18: 17201 | C18: 18749 | D18: 14793 | E18: 16685 | F18: Постановление Совета министров Республики Крым от 12.08.2024 N 452 | I18: 18749
A19: Республика Марий Эл | B19: 15605 | C19: 17009 | D19: 13420 | E19: 15137 | F19: Постановление Правительства Республики Марий Эл от 30.08.2024 N 325 | I19: 17009
A20: Республика Мордовия | B20: 15073 | C20: 16430 | D20: 12963 | E20: 14621 | F20: Постановление Правительства Республики Мордовия от 05.07.2024 N 576 | I20: 16430
A21: Республика Саха (Якутия) | B21: 26 777 <*> | C21: 29 187 <*> | D21: 23 028 <*> | E21: 25 974 <*> | F21: Постановление Правительства Республики Саха (Якутия) от 26.08.2024 N 394 | I21: 29 187 <*>
A22: Республика Северная Осетия - Алания | B22: 15960 | C22: 17396 | D22: 13726 | E22: 15481 | F22: Постановление Правительства Республики Северная Осетия-Алания от 08.08.2024 N 361 | I22: 17396
A23: Республика Татарстан (Татарстан) | B23: 15073 | C23: 16430 | D23: 12963 | E23: 14621 | F23: Постановление Кабинета Министров Республики Татарстан от 31.07.2024 N 609 | I23: 16430
A24: Республика Тыва | B24: 17910 | C24: 19522 | D24: 15403 | E24: 17373 | F24: Постановление Правительства Республики Тыва от 20.08.2024 N 413 | I24: 19522
A25: Удмуртская Республика | B25: 15782 | C25: 17202 | D25: 13573 | E25: 15309 | F25: Постановление Правительства Удмуртской Республики от 23.07.2024 N 384 | I25: 17202
A26: Республика Хакасия | B26: 18088 | C26: 19716 | D26: 15556 | E26: 17545 | F26: Постановление Правительства Республики Хакасия от 26.07.2024 N 434 | I26: 19716
A27: Чеченская Республика | B27: 17024 | C27: 18556 | D27: 14641 | E27: 16513 | F27: Постановление Правительства Чеченской Республики от 14.08.2024 N 175 | I27: 18556
A28: Чувашская Республика - Чувашия | B28: 15428 | C28: 16817 | D28: 13268 | E28: 14965 | F28: Постановление Кабинета Министров Чувашской Республики от 14.08.2024 N 470 | I28: 16817
A29: Алтайский край | B29: 15782 | C29: 17202 | D29: 13573 | E29: 15309 | F29: Постановление Правительства Алтайского края от 11.09.2024 N 337 | I29: 17202
A30: Забайкальский край | B30: 20748 | C30: 22615 | D30: 17843 | E30: 20126 | F30: Постановление Правительства Забайкальского края от 11.09.2024 N 454 | I30: 22615
A31: Камчатский край | B31: 31210 | C31: 34019 | D31: 26841 | E31: 30692 | F31: Постановление Правительства Камчатского края от 16.08.2024 N 400-П | I31: 34019
A32: Краснодарский край | B32: 17024 | C32: 18556 | D32: 14641 | E32: 16513 | F32: Постановление Губернатора Краснодарского края от 06.09.2024 N 575 | I32: 18556
A33: Красноярский край | B33: 19 684 <*> | C33: 21 456 <*> | D33: 16 928 <*> | E33: 19 093 <*> | F33: Постановление Правительства Красноярского края от 16.07.2024 N 517-п | I33: 21 456 <*>
A34: Пермский край | B34: 16314 | C34: 17782 | D34: 14030 | E34: 15825 | F34: Постановление Правительства Пермского края от 11.09.2024 N 611-п | I34: 17782
A35: Приморский край | B35: 21102 | C35: 23001 | D35: 18148 | E35: 20469 | F35: Постановление Правительства Приморского края от 09.09.2024 N 636-пп | I35: 23001
A36: Ставропольский край | B36: 15960 | C36: 17396 | D36: 13726 | E36: 15481 | F36: Постановление Правительства Ставропольского края от 25.08.2024 N 476-п | I36: 17396
A37: Хабаровский край | B37: 21634 | C37: 23581 | D37: 18605 | E37: 22844 | F37: Постановление Правительства Хабаровского края от 12.08.2024 N 285-пр | I37: 23581
A38: Амурская область | B38: 20 393 <*> | C38: 22 228 <*> | D38: 17 538 <*> | E38: 20 090 <*> | F38: Постановление Правительства Амурской области от 06.09.2024 N 695 | I38: 22 228 <*>
A39: Архангельская область | B39: 20 570 <*> | C39: 22 421 <*> | D39: 17 690 <*> | E39: 19 953 <*> | F39: Постановление Правительства Архангельской области от 26.08.2024 N 669-пп | I39: 22 421 <*>
A40: Астраханская область | B40: 17201 | C40: 18749 | D40: 14793 | E40: 16685 | F40: Постановление Правительства Астраханской области от 26.08.2024 N 551-П | I40: 18749
A41: Белгородская область | B41: 14896 | C41: 16237 | D41: 12811 | E41: 14449 | F41: Постановление Правительства Белгородской области от 29.07.2024 N 326-пп | I41: 16237
A42: Брянская область | B42: 16314 | C42: 17782 | D42: 14030 | E42: 15825 | F42: Постановление Правительства Брянской области от 15.07.2024 N 313-п | I42: 17782
A43: Владимирская область | B43: 17201 | C43: 18749 | D43: 14793 | E43: 16685 | F43: Постановление Правительства Владимирской области от 26.07.2024 N 453 | I43: 18749
A44: Волгоградская область | B44: 15250 | C44: 16623 | D44: 13115 | E44: 14793 | F44: Постановление Администрации Волгоградской области от 03.09.2024 N 532-п | I44: 16623
A45: Вологодская область | B45: 17910 | C45: 19522 | D45: 15403 | E45: 17373 | F45: Постановление Правительства Вологодской области от 23.08.2024 N 1048 | I45: 19522
A46: Воронежская область | B46: 15605 | C46: 17009 | D46: 13420 | E46: 15137 | F46: Постановление Правительства Воронежской области от 09.09.2024 N 622 | I46: 17009
A47: Ивановская область | B47: 16669 | C47: 18169 | D47: 14335 | E47: 16169 | F47: Постановление Правительства Ивановской области от 24.07.2024 N 324-п | I47: 18169
A48: Иркутская область | B48: 18 797 <*> | C48: 20 489 <*> | D48: 16 165 <*> | E48: 18 233 <*> | F48: Постановление Правительства Иркутской области от 12.07.2024 N 547-пп | I48: 20 489 <*>
A49: Калининградская область | B49: 18265 | C49: 19909 | D49: 15708 | E49: 17717 | F49: Постановление Правительства Калининградской области от 05.09.2024 N 359-п | I49: 19909
A50: Калужская область | B50: 17024 | C50: 18556 | D50: 14641 | E50: 16513 | F50: Постановление Правительства Калужской области от 23.08.2024 N 511 | I50: 18556
A51: Кемеровская область - Кузбасс | B51: 16137 | C51: 17589 | D51: 13878 | E51: 15653 | F51: Постановление Правительства Кемеровской области - Кузбасса от 25.07.2024 N 469 | I51: 17589
A52: Кировская область | B52: 15782 | C52: 17202 | D52: 13573 | E52: 15309 | F52: Постановление Правительства Кировской области от 09.08.2024 N 343-П | I52: 17202
A53: Костромская область | B53: 16314 | C53: 17782 | D53: 14030 | E53: 15825 | F53: Постановление Администрации Костромской области от 15.07.2024 N 245-а | I53: 17782
A54: Курганская область | B54: 16669 | C54: 18169 | D54: 14335 | E54: 16169 | F54: Постановление Правительства Курганской области от 07.08.2024 N 246 | I54: 18169
A55: Курская область | B55: 15428 | C55: 16817 | D55: 13268 | E55: 14965 | F55: Постановление Правительства Курской области от 29.07.2024 N 603-пп | I55: 16817
A56: Липецкая область | B56: 14718 | C56: 16043 | D56: 12657 | E56: 14276 | F56: Постановление Правительства Липецкой области от 30.07.2024 N 446 | I56: 16043
A57: Магаданская область | B57: 30855 | C57: 33632 | D57: 26535 | E57: 30829 | F57: Постановление Правительства Магаданской области от 29.08.2024 N 422-пп | I57: 33632
A58: Мурманская область | B58: 25390 | C58: 27675 | D58: 21835 | E58: 24628 | F58: Постановление Правительства Мурманской области от 12.09.2024 N 620-ПП | I58: 27675
A59: Нижегородская область | B59: 16669 | C59: 18169 | D59: 14335 | E59: 16169 | F59: Постановление Правительства Нижегородской области от 29.07.2024 N 433 | I59: 18169
A60: Новгородская область | B60: 17378 | C60: 18942 | D60: 14945 | E60: 16857 | F60: Постановление Правительства Новгородской области от 08.08.2024 N 357 | I60: 18942
... A75: Тверская область | B75: 17378 | C75: 18942 | D75: 14945 | E75: 16857 | F75: Постановление Правительства Тверской области от 27.09.2024 N 427-пп | I75: 18942
A76: Томская область | B76: 17 378 <*> | C76: 18 942 <*> | D76: 14 945 <*> | E76: 16 857 <*> | F76: Постановление Администрации Томской области от 30.07.2024 N 301а | I76: 18 942 <*>
A77: Тульская область | B77: 17733 | C77: 19329 | D77: 15250 | E77: 17201 | F77: Постановление Правительства Тульской области от 29.08.2024 N 452 | I77: 19329
A78: Тюменская область | B78: 17733 | C78: 19329 | D78: 15250 | E78: 17201 | F78: Постановление Правительства Тюменской области от 29.07.2024 N 508-п | I78: 19329
A79: Ульяновская область | B79: 15782 | C79: 17202 | D79: 13573 | E79: 15309 | F79: Постановление Правительства Ульяновской области от 30.07.2024 N 436-П | I79: 17202
A80: Челябинская область | B80: 16314 | C80: 17782 | D80: 14030 | E80: 15825 | F80: Постановление Правительства Челябинской области от 09.09.2024 N 516-П | I80: 17782
A81: Ярославская область | B81: 17733 | C81: 19329 | D81: 15250 | E81: 17201 | F81: Постановление Правительства Ярославской области от 06.08.2024 N 820-п | I81: 19329
A82: Севастополь | B82: 18088 | C82: 19716 | D82: 15556 | E82: 17545 | F82: Постановление Правительства Севастополя от 05.09.2024 N 410-ПП | I82: 19716
A83: Еврейская автономная область | B83: 22166 | C83: 24161 | D83: 19063 | E83: 21501 | F83: Постановление правительства Еврейской автономной области от 06.08.2024 N 318-пп | I83: 24161
A84: Ненецкий автономный округ | B84: 29389 | C84: 32034 | D84: 25275 | E84: 30706 | F84: Постановление администрации Ненецкого автономного округа от 02.09.2024 N 206-п | I84: 32034
A85: Ханты-Мансийский автономный округ - Югра | B85: 21252 | C85: 23165 | D85: 18334 | E85: 21286 | F85: Постановление Правительства Ханты-Мансийского автономного округа - Югры от 09.09.2024 N 326-п | I85: 23165
A86: Чукотский автономный округ | B86: 46283 | C86: 50448 | D86: 39803 | E86: 44895 | F86: Постановление Правительства Чукотского автономного округа от 26.08.2024 N 294 | I86: 50448
A87: Ямало-Ненецкий автономный округ | B87: 24294 | C87: 26480 | D87: 20893 | E87: 23565 | F87: Постановление Правительства Ямало-Ненецкого автономного округа от 05.08.2024 N 419-П | I87: 26480
